Workbook

Sheet Dev Tracker
A1: Project Name | B1: Website Url | C1: Task | D1: Priority | E1: Assign | F1: S Date | G1: E Date | H1: As Per WO | I1: Status | J1: Env | K1: Efforts | L1: Actual Effort | M1: Informed | N1: Support Needed / Blocker | O1: Dependency Detail | P1: Page Url | Q1: Mail Subject | R1: Internal Mail Subject | S1: Functionality | U1: Gmail Thread ID | V1: Google Task ID
A2: Adfactors PR Private Limited | B2: intranet.adfactorspr.com | C2: Demo Page | D2: Low | E2: Parthiban | F2: 46141 | G2: 46146 | I2: Under Review & Testing | J2: Staging | K2: =IF( COUNTIFS('Dev Tracker Sub'!$A$2:$A$4685, TRIM($B2&""), 'Dev Tracker Sub'!$B$2:$B$4685, TRIM($C2&""))=0, "No Subtasks", IF( SUMPRODUCT( --(TRIM('Dev Tracker Sub'!$A$2:$A$4685&"")=TRIM($B2&"")), --(TRIM('Dev Tracker Sub'!$B$2:$B$4685&"")=TRIM($C2&"")), --(LEN(TRIM('Dev Tracker Sub'!$L$2:$L$4685&""))=0) )>0, "⚠ Missing Effort", SUMIFS( 'Dev Tracker Sub'!$L$2:$L$4685, 'Dev Tracker Sub'!$A$2:$A$4685, TRIM($B2&""), 'Dev Tracker Sub'!$B$2:$B$4685, TRIM($C2&"") ) ) ) -> 5 | L2: =IF( COUNTIFS('Dev Tracker Sub'!$A$2:$A$4683, TRIM($B2&""), 'Dev Tracker Sub'!$B$2:$B$4683, TRIM($C2&""))=0, "No Subtasks", IF( SUMPRODUCT( --(TRIM('Dev Tracker Sub'!$A$2:$A$4683&"")=TRIM($B2&"")), --(TRIM('Dev Tracker Sub'!$B$2:$B$4683&"")=TRIM($C2&"")), --(LEN(TRIM('Dev Tracker Sub'!$M$2:$M$4683&""))=0) )>0, "⚠ Missing Effort", SUMIFS( 'Dev Tracker Sub'!$M$2:$M$4683, 'Dev Tracker Sub'!$A$2:$A$4683, TRIM($B2&""), 'Dev Tracker Sub'!$B$2:$B$4683, TRIM($C2&"") ) ) ) -> 4.5 | N2: All the changes have been completed. We are waiting for approval to go live | O2: Awaiting for approval to go live | R2: [Dev Tracker] TASK UPDATE: Demo Page | U2: 19ec0731129c8883
A3: Adfactors PR Private Limited | B3: intranet.adfactorspr.com | C3: Intranet Tech Queries | D3: Low | E3: Sowndar | F3: 46142 | G3: 46149 | I3: Under Review & Testing | J3: Production | K3: =IF( COUNTIFS('Dev Tracker Sub'!$A$2:$A$4685, TRIM($B3&""), 'Dev Tracker Sub'!$B$2:$B$4685, TRIM($C3&""))=0, "No Subtasks", IF( SUMPRODUCT( --(TRIM('Dev Tracker Sub'!$A$2:$A$4685&"")=TRIM($B3&"")), --(TRIM('Dev Tracker Sub'!$B$2:$B$4685&"")=TRIM($C3&"")), --(LEN(TRIM('Dev Tracker Sub'!$L$2:$L$4685&""))=0) )>0, "⚠ Missing Effort", SUMIFS( 'Dev Tracker Sub'!$L$2:$L$4685, 'Dev Tracker Sub'!$A$2:$A$4685, TRIM($B3&""), 'Dev Tracker Sub'!$B$2:$B$4685, TRIM($C3&"") ) ) ) -> 6.5 | L3: =IF( COUNTIFS('Dev Tracker Sub'!$A$2:$A$4683, TRIM($B3&""), 'Dev Tracker Sub'!$B$2:$B$4683, TRIM($C3&""))=0, "No Subtasks", IF( SUMPRODUCT( --(TRIM('Dev Tracker Sub'!$A$2:$A$4683&"")=TRIM($B3&"")), --(TRIM('Dev Tracker Sub'!$B$2:$B$4683&"")=TRIM($C3&"")), --(LEN(TRIM('Dev Tracker Sub'!$M$2:$M$4683&""))=0) )>0, "⚠ Missing Effort", SUMIFS( 'Dev Tracker Sub'!$M$2:$M$4683, 'Dev Tracker Sub'!$A$2:$A$4683, TRIM($B3&""), 'Dev Tracker Sub'!$B$2:$B$4683, TRIM($C3&"") ) ) ) -> 6.5 | N3: Vishal Said He will come back to us | R3: [Dev Tracker] TASK UPDATE: Intranet Tech Queries | U3: 19ec52bb83377384
A4: Adfactors PR Private Limited | B4: intranet.adfactorspr.com | C4: Content Update June | D4: Low | F4: 46174 | G4: 46186 | I4: In Progress | J4: Staging | K4: =IF( COUNTIFS('Dev Tracker Sub'!$A$2:$A$4685, TRIM($B4&""), 'Dev Tracker Sub'!$B$2:$B$4685, TRIM($C4&""))=0, "No Subtasks", IF( SUMPRODUCT( --(TRIM('Dev Tracker Sub'!$A$2:$A$4685&"")=TRIM($B4&"")), --(TRIM('Dev Tracker Sub'!$B$2:$B$4685&"")=TRIM($C4&"")), --(LEN(TRIM('Dev Tracker Sub'!$L$2:$L$4685&""))=0) )>0, "⚠ Missing Effort", SUMIFS( 'Dev Tracker Sub'!$L$2:$L$4685, 'Dev Tracker Sub'!$A$2:$A$4685, TRIM($B4&""), 'Dev Tracker Sub'!$B$2:$B$4685, TRIM($C4&"") ) ) ) -> 5 | L4: =IF( COUNTIFS('Dev Tracker Sub'!$A$2:$A$4683, TRIM($B4&""), 'Dev Tracker Sub'!$B$2:$B$4683, TRIM($C4&""))=0, "No Subtasks", IF( SUMPRODUCT( --(TRIM('Dev Tracker Sub'!$A$2:$A$4683&"")=TRIM($B4&"")), --(TRIM('Dev Tracker Sub'!$B$2:$B$4683&"")=TRIM($C4&"")), --(LEN(TRIM('Dev Tracker Sub'!$M$2:$M$4683&""))=0) )>0, "⚠ Missing Effort", SUMIFS( 'Dev Tracker Sub'!$M$2:$M$4683, 'Dev Tracker Sub'!$A$2:$A$4683, TRIM($B4&""), 'Dev Tracker Sub'!$B$2:$B$4683, TRIM($C4&"") ) ) ) -> 4.5 | N4: Update the content in awards page Create a new Casestydy In live sort and update the Leadership team members Update content in Cross sell inivative winner list | R4: TASK UPDATE: Content Update June | U4: 19ed29ab81158007
A5: Adfactors PR Private Limited | B5: intranet.adfactorspr.com | C5: Adfactor Admin Dashboard | D5: Low | E5: Parthiban | H5: 46077 | I5: On Hold / Blocked | J5: Staging | K5: =IF( COUNTIFS('Dev Tracker Sub'!$A$2:$A$4685, TRIM($B5&""), 'Dev Tracker Sub'!$B$2:$B$4685, TRIM($C5&""))=0, "No Subtasks", IF( SUMPRODUCT( --(TRIM('Dev Tracker Sub'!$A$2:$A$4685&"")=TRIM($B5&"")), --(TRIM('Dev Tracker Sub'!$B$2:$B$4685&"")=TRIM($C5&"")), --(LEN(TRIM('Dev Tracker Sub'!$L$2:$L$4685&""))=0) )>0, "⚠ Missing Effort", SUMIFS( 'Dev Tracker Sub'!$L$2:$L$4685, 'Dev Tracker Sub'!$A$2:$A$4685, TRIM($B5&""), 'Dev Tracker Sub'!$B$2:$B$4685, TRIM($C5&"") ) ) ) -> ⚠ Missing Effort | L5: =IF( COUNTIFS('Dev Tracker Sub'!$A$2:$A$4683, TRIM($B5&""), 'Dev Tracker Sub'!$B$2:$B$4683, TRIM($C5&""))=0, "No Subtasks", IF( SUMPRODUCT( --(TRIM('Dev Tracker Sub'!$A$2:$A$4683&"")=TRIM($B5&"")), --(TRIM('Dev Tracker Sub'!$B$2:$B$4683&"")=TRIM($C5&"")), --(LEN(TRIM('Dev Tracker Sub'!$M$2:$M$4683&""))=0) )>0, "⚠ Missing Effort", SUMIFS( 'Dev Tracker Sub'!$M$2:$M$4683, 'Dev Tracker Sub'!$A$2:$A$4683, TRIM($B5&""), 'Dev Tracker Sub'!$B$2:$B$4683, TRIM($C5&"") ) ) ) -> 3.5 | N5: Following the Adfactor dashboard submission, we have finalized the functional requirements and staging updates. Although changes were ready by March 24th, the site has been offline since March 26th due to server instability. We provided the database to the server team on April 9th. To resolve the remaining issues, we must create a new image directory with the correct write permissions; this is essential for posts to be saved and displayed correctly. We also require a WAF permission update | R5: [Dev Tracker] TASK UPDATE: Adfactor Admin Dashboard | U5: 19ec6ac88dbc8391
A6: Adfactors PR Private Limited | B6: intranet.adfactorspr.com | C6: Dev Update June | D6: Low | E6: Parthiban | I6: In Progress | J6: Staging | K6: =IF( COUNTIFS('Dev Tracker Sub'!$A$2:$A$4685, TRIM($B6&""), 'Dev Tracker Sub'!$B$2:$B$4685, TRIM($C6&""))=0, "No Subtasks", IF( SUMPRODUCT( --(TRIM('Dev Tracker Sub'!$A$2:$A$4685&"")=TRIM($B6&"")), --(TRIM('Dev Tracker Sub'!$B$2:$B$4685&"")=TRIM($C6&"")), --(LEN(TRIM('Dev Tracker Sub'!$L$2:$L$4685&""))=0) )>0, "⚠ Missing Effort", SUMIFS( 'Dev Tracker Sub'!$L$2:$L$4685, 'Dev Tracker Sub'!$A$2:$A$4685, TRIM($B6&""), 'Dev Tracker Sub'!$B$2:$B$4685, TRIM($C6&"") ) ) ) -> 32.5 | L6: =IF( COUNTIFS('Dev Tracker Sub'!$A$2:$A$4683, TRIM($B6&""), 'Dev Tracker Sub'!$B$2:$B$4683, TRIM($C6&""))=0, "No Subtasks", IF( SUMPRODUCT( --(TRIM('Dev Tracker Sub'!$A$2:$A$4683&"")=TRIM($B6&"")), --(TRIM('Dev Tracker Sub'!$B$2:$B$4683&"")=TRIM($C6&"")), --(LEN(TRIM('Dev Tracker Sub'!$M$2:$M$4683&""))=0) )>0, "⚠ Missing Effort", SUMIFS( 'Dev Tracker Sub'!$M$2:$M$4683, 'Dev Tracker Sub'!$A$2:$A$4683, TRIM($B6&""), 'Dev Tracker Sub'!$B$2:$B$4683, TRIM($C6&"") ) ) ) -> 15.5 | N6: Update the content in awards page Create a new Casestydy In live sort and update the Leadership team members Update content in Cross sell inivative winner list Update and fix the issue in SQL for restore Database List the Case study with published and Article date "change name Adfactors PR 1/3 carosel badge Remove bold for value in current affairs System generated post Text changes Enable the Auto post generation Fix the EmployeeID in Post moderation Add AE AM decathlon in utilities page" Left align the text in system generated post | R6: TASK UPDATE: Dev Update June | U6: 19ed29ae59265021
A7: Adfactors PR Private Limited | B7: intranet.adfactorspr.com | C7: Case Study Page May 2026 | D7: Medium | I7: Pipeline / To Do | J7: Local | K7: =IF( COUNTIFS('Dev Tracker Sub'!$A$2:$A$4685, TRIM($B7&""), 'Dev Tracker Sub'!$B$2:$B$4685, TRIM($C7&""))=0, "No Subtasks", IF( SUMPRODUCT( --(TRIM('Dev Tracker Sub'!$A$2:$A$4685&"")=TRIM($B7&"")), --(TRIM('Dev Tracker Sub'!$B$2:$B$4685&"")=TRIM($C7&"")), --(LEN(TRIM('Dev Tracker Sub'!$L$2:$L$4685&""))=0) )>0, "⚠ Missing Effort", SUMIFS( 'Dev Tracker Sub'!$L$2:$L$4685, 'Dev Tracker Sub'!$A$2:$A$4685, TRIM($B7&""), 'Dev Tracker Sub'!$B$2:$B$4685, TRIM($C7&"") ) ) ) -> 0 | L7: =IF( COUNTIFS('Dev Tracker Sub'!$A$2:$A$4683, TRIM($B7&""), 'Dev Tracker Sub'!$B$2:$B$4683, TRIM($C7&""))=0, "No Subtasks", IF( SUMPRODUCT( --(TRIM('Dev Tracker Sub'!$A$2:$A$4683&"")=TRIM($B7&"")), --(TRIM('Dev Tracker Sub'!$B$2:$B$4683&"")=TRIM($C7&"")), --(LEN(TRIM('Dev Tracker Sub'!$M$2:$M$4683&""))=0) )>0, "⚠ Missing Effort", SUMIFS( 'Dev Tracker Sub'!$M$2:$M$4683, 'Dev Tracker Sub'!$A$2:$A$4683, TRIM($B7&""), 'Dev Tracker Sub'!$B$2:$B$4683, TRIM($C7&"") ) ) ) -> 0 | O7: Need to develop new Case Study page template. Client logos/design assets if required. | R7: TASK UPDATE: Case Study Page May 2026 | U7: 19ed1518e71e4cb5
A8: Adfactors PR Private Limited | B8: work.adfactorspr.com | C8: Restore Work.Adfactor | D8: Low | I8: Pipeline / To Do | J8: Local | K8: =IF( COUNTIFS('Dev Tracker Sub'!$A$2:$A$4685, TRIM($B8&""), 'Dev Tracker Sub'!$B$2:$B$4685, TRIM($C8&""))=0, "No Subtasks", IF( SUMPRODUCT( --(TRIM('Dev Tracker Sub'!$A$2:$A$4685&"")=TRIM($B8&"")), --(TRIM('Dev Tracker Sub'!$B$2:$B$4685&"")=TRIM($C8&"")), --(LEN(TRIM('Dev Tracker Sub'!$L$2:$L$4685&""))=0) )>0, "⚠ Missing Effort", SUMIFS( 'Dev Tracker Sub'!$L$2:$L$4685, 'Dev Tracker Sub'!$A$2:$A$4685, TRIM($B8&""), 'Dev Tracker Sub'!$B$2:$B$4685, TRIM($C8&"") ) ) ) -> No Subtasks | L8: =IF( COUNTIFS('Dev Tracker Sub'!$A$2:$A$4683, TRIM($B8&""), 'Dev Tracker Sub'!$B$2:$B$4683, TRIM($C8&""))=0, "No Subtasks", IF( SUMPRODUCT( --(TRIM('Dev Tracker Sub'!$A$2:$A$4683&"")=TRIM($B8&"")), --(TRIM('Dev Tracker Sub'!$B$2:$B$4683&"")=TRIM($C8&"")), --(LEN(TRIM('Dev Tracker Sub'!$M$2:$M$4683&""))=0) )>0, "⚠ Missing Effort", SUMIFS( 'Dev Tracker Sub'!$M$2:$M$4683, 'Dev Tracker Sub'!$A$2:$A$4683, TRIM($B8&""), 'Dev Tracker Sub'!$B$2:$B$4683, TRIM($C8&"") ) ) ) -> No Subtasks | R8: [Dev Tracker] TASK UPDATE: Restore Work.Adfactor | U8: 19e3488183ba4491
A9: Diriyah Gate Development Authority | B9: www.dgda.gov.sa | C9: Raise Concern | D9: Medium | F9: 46155 | G9: 46160 | H9: 46160 | I9: Under Review & Testing | J9: Production | K9: =IF( COUNTIFS('Dev Tracker Sub'!$A$2:$A$4685, TRIM($B9&""), 'Dev Tracker Sub'!$B$2:$B$4685, TRIM($C9&""))=0, "No Subtasks", IF( SUMPRODUCT( --(TRIM('Dev Tracker Sub'!$A$2:$A$4685&"")=TRIM($B9&"")), --(TRIM('Dev Tracker Sub'!$B$2:$B$4685&"")=TRIM($C9&"")), --(LEN(TRIM('Dev Tracker Sub'!$L$2:$L$4685&""))=0) )>0, "⚠ Missing Effort", SUMIFS( 'Dev Tracker Sub'!$L$2:$L$4685, 'Dev Tracker Sub'!$A$2:$A$4685, TRIM($B9&""), 'Dev Tracker Sub'!$B$2:$B$4685, TRIM($C9&"") ) ) ) -> 9 | L9: =IF( COUNTIFS('Dev Tracker Sub'!$A$2:$A$4683, TRIM($B9&""), 'Dev Tracker Sub'!$B$2:$B$4683, TRIM($C9&""))=0, "No Subtasks", IF( SUMPRODUCT( --(TRIM('Dev Tracker Sub'!$A$2:$A$4683&"")=TRIM($B9&"")), --(TRIM('Dev Tracker Sub'!$B$2:$B$4683&"")=TRIM($C9&"")), --(LEN(TRIM('Dev Tracker Sub'!$M$2:$M$4683&""))=0) )>0, "⚠ Missing Effort", SUMIFS( 'Dev Tracker Sub'!$M$2:$M$4683, 'Dev Tracker Sub'!$A$2:$A$4683, TRIM($B9&""), 'Dev Tracker Sub'!$B$2:$B$4683, TRIM($C9&"") ) ) ) -> 9.5 | N9: Shared with Client Waiting for approval | O9: Need Approval From Saad | P9: https://release-dgda.d1pchk3m069rke.amplifyapp.com/en/contact-us/general-inquiries | Q9: Open Data Form - DGDA | R9: TASK UPDATE: Open data form Phase - 2 | U9: 19ec976388afdc2e
A10: Diriyah Gate Development Authority | B10: www.dgda.gov.sa | C10: Events Application and Diriyah Horizon | D10: Low | F10: 46156 | I10: In Progress | K10: =IF( COUNTIFS('Dev Tracker Sub'!$A$2:$A$4685, TRIM($B10&""), 'Dev Tracker Sub'!$B$2:$B$4685, TRIM($C10&""))=0, "No Subtasks", IF( SUMPRODUCT( --(TRIM('Dev Tracker Sub'!$A$2:$A$4685&"")=TRIM($B10&"")), --(TRIM('Dev Tracker Sub'!$B$2:$B$4685&"")=TRIM($C10&"")), --(LEN(TRIM('Dev Tracker Sub'!$L$2:$L$4685&""))=0) )>0, "⚠ Missing Effort", SUMIFS( 'Dev Tracker Sub'!$L$2:$L$4685, 'Dev Tracker Sub'!$A$2:$A$4685, TRIM($B10&""), 'Dev Tracker Sub'!$B$2:$B$4685, TRIM($C10&"") ) ) ) -> 48.5 | L10: =IF( COUNTIFS('Dev Tracker Sub'!$A$2:$A$4683, TRIM($B10&""), 'Dev Tracker Sub'!$B$2:$B$4683, TRIM($C10&""))=0, "No Subtasks", IF( SUMPRODUCT( --(TRIM('Dev Tracker Sub'!$A$2:$A$4683&"")=TRIM($B10&"")), --(TRIM('Dev Tracker Sub'!$B$2:$B$4683&"")=TRIM($C10&"")), --(LEN(TRIM('Dev Tracker Sub'!$M$2:$M$4683&""))=0) )>0, "⚠ Missing Effort", SUMIFS( 'Dev Tracker Sub'!$M$2:$M$4683, 'Dev Tracker Sub'!$A$2:$A$4683, TRIM($B10&""), 'Dev Tracker Sub'!$B$2:$B$4683, TRIM($C10&"") ) ) ) -> 39.5 | R10: [Dev Tracker] TASK UPDATE: Events Application and Diriyah Horizon | U10: 19ed0e33d52ddeef
A11: Diriyah Gate Development Authority | B11: www.dgda.gov.sa | C11: DGDA Maintenance June 2026 | D11: Low | F11: 46143 | I11: In Progress | K11: =IF( COUNTIFS('Dev Tracker Sub'!$A$2:$A$4685, TRIM($B11&""), 'Dev Tracker Sub'!$B$2:$B$4685, TRIM($C11&""))=0, "No Subtasks", IF( SUMPRODUCT( --(TRIM('Dev Tracker Sub'!$A$2:$A$4685&"")=TRIM($B11&"")), --(TRIM('Dev Tracker Sub'!$B$2:$B$4685&"")=TRIM($C11&"")), --(LEN(TRIM('Dev Tracker Sub'!$L$2:$L$4685&""))=0) )>0, "⚠ Missing Effort", SUMIFS( 'Dev Tracker Sub'!$L$2:$L$4685, 'Dev Tracker Sub'!$A$2:$A$4685, TRIM($B11&""), 'Dev Tracker Sub'!$B$2:$B$4685, TRIM($C11&"") ) ) ) -> ⚠ Missing Effort | L11: =IF( COUNTIFS('Dev Tracker Sub'!$A$2:$A$4683, TRIM($B11&""), 'Dev Tracker Sub'!$B$2:$B$4683, TRIM($C11&""))=0, "No Subtasks", IF( SUMPRODUCT( --(TRIM('Dev Tracker Sub'!$A$2:$A$4683&"")=TRIM($B11&"")), --(TRIM('Dev Tracker Sub'!$B$2:$B$4683&"")=TRIM($C11&"")), --(LEN(TRIM('Dev Tracker Sub'!$M$2:$M$4683&""))=0) )>0, "⚠ Missing Effort", SUMIFS( 'Dev Tracker Sub'!$M$2:$M$4683, 'Dev Tracker Sub'!$A$2:$A$4683, TRIM($B11&""), 'Dev Tracker Sub'!$B$2:$B$4683, TRIM($C11&"") ) ) ) -> 29.95 | R11: [Dev Tracker] TASK UPDATE: DGDA Maintenance May 2026 | U11: 19ed0e4ad0604eff
A12: Diriyah Gate Development Authority | B12: www.dgda.gov.sa | C12: National Design System (DGA) | D12: Medium | E12: Abhicheke | F12: 46025 | G12: 46078 | H12: 46078 | I12: Under Review & Testing | J12: UAT | K12: =IF( COUNTIFS('Dev Tracker Sub'!$A$2:$A$4685, TRIM($B12&""), 'Dev Tracker Sub'!$B$2:$B$4685, TRIM($C12&""))=0, "No Subtasks", IF( SUMPRODUCT( --(TRIM('Dev Tracker Sub'!$A$2:$A$4685&"")=TRIM($B12&"")), --(TRIM('Dev Tracker Sub'!$B$2:$B$4685&"")=TRIM($C12&"")), --(LEN(TRIM('Dev Tracker Sub'!$L$2:$L$4685&""))=0) )>0, "⚠ Missing Effort", SUMIFS( 'Dev Tracker Sub'!$L$2:$L$4685, 'Dev Tracker Sub'!$A$2:$A$4685, TRIM($B12&""), 'Dev Tracker Sub'!$B$2:$B$4685, TRIM($C12&"") ) ) ) -> 202.5 | L12: =IF( COUNTIFS('Dev Tracker Sub'!$A$2:$A$4683, TRIM($B12&""), 'Dev Tracker Sub'!$B$2:$B$4683, TRIM($C12&""))=0, "No Subtasks", IF( SUMPRODUCT( --(TRIM('Dev Tracker Sub'!$A$2:$A$4683&"")=TRIM($B12&"")), --(TRIM('Dev Tracker Sub'!$B$2:$B$4683&"")=TRIM($C12&"")), --(LEN(TRIM('Dev Tracker Sub'!$M$2:$M$4683&""))=0) )>0, "⚠ Missing Effort", SUMIFS( 'Dev Tracker Sub'!$M$2:$M$4683, 'Dev Tracker Sub'!$A$2:$A$4683, TRIM($B12&""), 'Dev Tracker Sub'!$B$2:$B$4683, TRIM($C12&"") ) ) ) -> 184.5 | N12: Main project development has been underway since February 25th. Although the National Design phase was on hold as of February 12th, we received confirmation to initiate work on April 7th. The team was requested to share a first draft by April 15th, and a preview link was sent to the DGDA team on April 16th. We reshared the homepage with them on April 17th and are currently awaiting feedback to proceed with the remaining pages. A review meeting was scheduled for April 28th, and we are now awaiting a post-meeting update from the DGDA. We have received the approve the other page 07 May the team will start working on rest of the page Based on Saad He Approved and proceed with everything. Regarding the quality assurance phase, a new joiner from Saad's team will be responsible for cross-checking the work once development is complete (11 May), | O12: Send the email to Saad and get the clarification for the icon | P12: https://feat-national-design-system-v16-main.d38541r9nlp4br.amplifyapp.com/ | Q12: DGA timeline Development for DGA guidelines and Website Content | R12: [Dev Tracker] TASK UPDATE: National Design System (DGA) | U12: 19ed187f836ec16f
A13: Diriyah Gate Development Authority | B13: www.dgda.gov.sa | C13: Quamatic Integration | D13: Low | F13: 46097 | I13: On Hold / Blocked | K13: =IF( COUNTIFS('Dev Tracker Sub'!$A$2:$A$4685, TRIM($B13&""), 'Dev Tracker Sub'!$B$2:$B$4685, TRIM($C13&""))=0, "No Subtasks", IF( SUMPRODUCT( --(TRIM('Dev Tracker Sub'!$A$2:$A$4685&"")=TRIM($B13&"")), --(TRIM('Dev Tracker Sub'!$B$2:$B$4685&"")=TRIM($C13&"")), --(LEN(TRIM('Dev Tracker Sub'!$L$2:$L$4685&""))=0) )>0, "⚠ Missing Effort", SUMIFS( 'Dev Tracker Sub'!$L$2:$L$4685, 'Dev Tracker Sub'!$A$2:$A$4685, TRIM($B13&""), 'Dev Tracker Sub'!$B$2:$B$4685, TRIM($C13&"") ) ) ) -> 9 | L13: =IF( COUNTIFS('Dev Tracker Sub'!$A$2:$A$4683, TRIM($B13&""), 'Dev Tracker Sub'!$B$2:$B$4683, TRIM($C13&""))=0, "No Subtasks", IF( SUMPRODUCT( --(TRIM('Dev Tracker Sub'!$A$2:$A$4683&"")=TRIM($B13&"")), --(TRIM('Dev Tracker Sub'!$B$2:$B$4683&"")=TRIM($C13&"")), --(LEN(TRIM('Dev Tracker Sub'!$M$2:$M$4683&""))=0) )>0, "⚠ Missing Effort", SUMIFS( 'Dev Tracker Sub'!$M$2:$M$4683, 'Dev Tracker Sub'!$A$2:$A$4683, TRIM($B13&""), 'Dev Tracker Sub'!$B$2:$B$4683, TRIM($C13&"") ) ) ) -> 3 | N13: Following our March 16th call, we requested the UAT URL for testing. Although we suggested a single endpoint on April 2nd, the team confirmed this was not feasible. On April 8th, we followed up regarding current access restrictions and are awaiting Dayel’s guidance on Qmatic access. Per yesterday's meeting, Saad needs to provide confirmation; until then, API integration is on hold while we focus on other changes and the NDS. The API integration is currently blocked by IP restrictions. We are also awaiting the Qmatic API documents, as the previous files were inaccessible. Finally, we requested VPN access on March 31st and are waiting for the necessary APIs from the Qmatic team | O13: API integration paused due to access constraints. Saad to advise once sorted. 503 Service Unavailable SMS API Working Good Waiting for Production URL The production URL auth is failed | R13: [Dev Tracker] TASK UPDATE: Quamatic Integration | U13: 19e3488d3a8b0c0a
A14: Diriyah Gate Development Authority | B14: www.dgda.gov.sa | C14: Emergency services form | D14: Low | E14: Abhicheke | F14: 46093 | I14: On Hold / Blocked | K14: =IF( COUNTIFS('Dev Tracker Sub'!$A$2:$A$4685, TRIM($B14&""), 'Dev Tracker Sub'!$B$2:$B$4685, TRIM($C14&""))=0, "No Subtasks", IF( SUMPRODUCT( --(TRIM('Dev Tracker Sub'!$A$2:$A$4685&"")=TRIM($B14&"")), --(TRIM('Dev Tracker Sub'!$B$2:$B$4685&"")=TRIM($C14&"")), --(LEN(TRIM('Dev Tracker Sub'!$L$2:$L$4685&""))=0) )>0, "⚠ Missing Effort", SUMIFS( 'Dev Tracker Sub'!$L$2:$L$4685, 'Dev Tracker Sub'!$A$2:$A$4685, TRIM($B14&""), 'Dev Tracker Sub'!$B$2:$B$4685, TRIM($C14&"") ) ) ) -> 8.75 | L14: =IF( COUNTIFS('Dev Tracker Sub'!$A$2:$A$4683, TRIM($B14&""), 'Dev Tracker Sub'!$B$2:$B$4683, TRIM($C14&""))=0, "No Subtasks", IF( SUMPRODUCT( --(TRIM('Dev Tracker Sub'!$A$2:$A$4683&"")=TRIM($B14&"")), --(TRIM('Dev Tracker Sub'!$B$2:$B$4683&"")=TRIM($C14&"")), --(LEN(TRIM('Dev Tracker Sub'!$M$2:$M$4683&""))=0) )>0, "⚠ Missing Effort", SUMIFS( 'Dev Tracker Sub'!$M$2:$M$4683, 'Dev Tracker Sub'!$A$2:$A$4683, TRIM($B14&""), 'Dev Tracker Sub'!$B$2:$B$4683, TRIM($C14&"") ) ) ) -> 8.75 | N14: Since completing the form and OTP integration on March 12th, we have been working through several integration blockers. The current SMS API is restricted to Arabic numbers, which prevents us from finalizing the global OTP functionality. Additionally, while GIS token generation is successful, we are encountering an 'Invalid URL' error when testing KMZ files. We held a technical call on April 28th to address why the third API remains non-functional. We are currently awaiting follow-up responses from Waleed and Kamran regarding the GIS fix and the SMS production credentials, respectively. | O14: 3rd Api not working 1st and 2nd Api Working For SMS API Production URL I tried both No Auth and Basic Auth username - ffffa747-d38b-3971-83e5-facd68d4fd40 Password - SAPCPI_SMS__API_OAUTH_e650058 but it show unauthorized_client | R14: [Dev Tracker] TASK UPDATE: Emergency services form | S14: SMS Api Need to Implement | U14: 19e3488fe21c9b07
A15: Diriyah Gate Development Authority | B15: www.dgda.gov.sa | C15: Eservices and Qmatic Webpages | D15: Low | I15: In Progress | J15: Local | K15: =IF( COUNTIFS('Dev Tracker Sub'!$A$2:$A$4685, TRIM($B15&""), 'Dev Tracker Sub'!$B$2:$B$4685, TRIM($C15&""))=0, "No Subtasks", IF( SUMPRODUCT( --(TRIM('Dev Tracker Sub'!$A$2:$A$4685&"")=TRIM($B15&"")), --(TRIM('Dev Tracker Sub'!$B$2:$B$4685&"")=TRIM($C15&"")), --(LEN(TRIM('Dev Tracker Sub'!$L$2:$L$4685&""))=0) )>0, "⚠ Missing Effort", SUMIFS( 'Dev Tracker Sub'!$L$2:$L$4685, 'Dev Tracker Sub'!$A$2:$A$4685, TRIM($B15&""), 'Dev Tracker Sub'!$B$2:$B$4685, TRIM($C15&"") ) ) ) -> 0.25 | L15: =IF( COUNTIFS('Dev Tracker Sub'!$A$2:$A$4683, TRIM($B15&""), 'Dev Tracker Sub'!$B$2:$B$4683, TRIM($C15&""))=0, "No Subtasks", IF( SUMPRODUCT( --(TRIM('Dev Tracker Sub'!$A$2:$A$4683&"")=TRIM($B15&"")), --(TRIM('Dev Tracker Sub'!$B$2:$B$4683&"")=TRIM($C15&"")), --(LEN(TRIM('Dev Tracker Sub'!$M$2:$M$4683&""))=0) )>0, "⚠ Missing Effort", SUMIFS( 'Dev Tracker Sub'!$M$2:$M$4683, 'Dev Tracker Sub'!$A$2:$A$4683, TRIM($B15&""), 'Dev Tracker Sub'!$B$2:$B$4683, TRIM($C15&"") ) ) ) -> 0.25 | N15: Team has reviewed the websites and shared the estimation with Saad on 19/04. AW backend access to review in detail, request raised with Saad. Need to schedule a call with Qmatic team 29/04 | R15: [Dev Tracker] TASK UPDATE: Eservices and Qmatic Webpages | U15: 19ddd4c15de487fd
A16: Diriyah Gate Development Authority | B16: www.dgda.gov.sa | C16: Research Inquiry Forms | D16: Low | F16: 46133 | G16: 46134 | I16: Waiting for Client Input | J16: Staging | K16: =IF( COUNTIFS('Dev Tracker Sub'!$A$2:$A$4685, TRIM($B16&""), 'Dev Tracker Sub'!$B$2:$B$4685, TRIM($C16&""))=0, "No Subtasks", IF( SUMPRODUCT( --(TRIM('Dev Tracker Sub'!$A$2:$A$4685&"")=TRIM($B16&"")), --(TRIM('Dev Tracker Sub'!$B$2:$B$4685&"")=TRIM($C16&"")), --(LEN(TRIM('Dev Tracker Sub'!$L$2:$L$4685&""))=0) )>0, "⚠ Missing Effort", SUMIFS( 'Dev Tracker Sub'!$L$2:$L$4685, 'Dev Tracker Sub'!$A$2:$A$4685, TRIM($B16&""), 'Dev Tracker Sub'!$B$2:$B$4685, TRIM($C16&"") ) ) ) -> 9.25 | L16: =IF( COUNTIFS('Dev Tracker Sub'!$A$2:$A$4683, TRIM($B16&""), 'Dev Tracker Sub'!$B$2:$B$4683, TRIM($C16&""))=0, "No Subtasks", IF( SUMPRODUCT( --(TRIM('Dev Tracker Sub'!$A$2:$A$4683&"")=TRIM($B16&"")), --(TRIM('Dev Tracker Sub'!$B$2:$B$4683&"")=TRIM($C16&"")), --(LEN(TRIM('Dev Tracker Sub'!$M$2:$M$4683&""))=0) )>0, "⚠ Missing Effort", SUMIFS( 'Dev Tracker Sub'!$M$2:$M$4683, 'Dev Tracker Sub'!$A$2:$A$4683, TRIM($B16&""), 'Dev Tracker Sub'!$B$2:$B$4683, TRIM($C16&"") ) ) ) -> 8.75 | N16: Team has initiated the work on the form; preview link will be shared on 22/04. Preview link shared with Dayel on 23/04. CRM integration pending with DGDA. | O16: Need Arabic content and Description Form need to map on c4c | P16: https://main.d3jcmxm4xwijj.amplifyapp.com/en/contact-us/research-inquiry | R16: [Dev Tracker] TASK UPDATE: Research Inquiry Forms | U16: 19dbe08a710e8032
A17: Diriyah Gate Development Authority | B17: www.dgda.gov.sa | C17: DGDA Application PT Finding | D17: Low | I17: Local | K17: =IF( COUNTIFS('Dev Tracker Sub'!$A$2:$A$4685, TRIM($B17&""), 'Dev Tracker Sub'!$B$2:$B$4685, TRIM($C17&""))=0, "No Subtasks", IF( SUMPRODUCT( --(TRIM('Dev Tracker Sub'!$A$2:$A$4685&"")=TRIM($B17&"")), --(TRIM('Dev Tracker Sub'!$B$2:$B$4685&"")=TRIM($C17&"")), --(LEN(TRIM('Dev Tracker Sub'!$L$2:$L$4685&""))=0) )>0, "⚠ Missing Effort", SUMIFS( 'Dev Tracker Sub'!$L$2:$L$4685, 'Dev Tracker Sub'!$A$2:$A$4685, TRIM($B17&""), 'Dev Tracker Sub'!$B$2:$B$4685, TRIM($C17&"") ) ) ) -> 0.25 | L17: =IF( COUNTIFS('Dev Tracker Sub'!$A$2:$A$4683, TRIM($B17&""), 'Dev Tracker Sub'!$B$2:$B$4683, TRIM($C17&""))=0, "No Subtasks", IF( SUMPRODUCT( --(TRIM('Dev Tracker Sub'!$A$2:$A$4683&"")=TRIM($B17&"")), --(TRIM('Dev Tracker Sub'!$B$2:$B$4683&"")=TRIM($C17&"")), --(LEN(TRIM('Dev Tracker Sub'!$M$2:$M$4683&""))=0) )>0, "⚠ Missing Effort", SUMIFS( 'Dev Tracker Sub'!$M$2:$M$4683, 'Dev Tracker Sub'!$A$2:$A$4683, TRIM($B17&""), 'Dev Tracker Sub'!$B$2:$B$4683, TRIM($C17&"") ) ) ) -> 0.25 | N17: Email received from Faisal on 21/04 to update the Next.js version of the DGDA website. AW confirmation from Saad to proceed further. | R17: [Dev Tracker] TASK UPDATE: DGDA Application PT Finding | U17: 19ddd4bbfdf4fdb8
A18: Diriyah Gate Development Authority | B18: www.dgda.gov.sa | C18: EMS Project | D18: Low | I18: In Progress
A19: Diriyah Gate Development Authority | B19: www.dgda.gov.sa | C19: DGDA EMS Infra set up | D19: Low | E19: Moswin | I19: Pipeline / To Do | J19: Local | K19: =IF( COUNTIFS('Dev Tracker Sub'!$A$2:$A$4685, TRIM($B19&""), 'Dev Tracker Sub'!$B$2:$B$4685, TRIM($C19&""))=0, "No Subtasks", IF( SUMPRODUCT( --(TRIM('Dev Tracker Sub'!$A$2:$A$4685&"")=TRIM($B19&"")), --(TRIM('Dev Tracker Sub'!$B$2:$B$4685&"")=TRIM($C19&"")), --(LEN(TRIM('Dev Tracker Sub'!$L$2:$L$4685&""))=0) )>0, "⚠ Missing Effort", SUMIFS( 'Dev Tracker Sub'!$L$2:$L$4685, 'Dev Tracker Sub'!$A$2:$A$4685, TRIM($B19&""), 'Dev Tracker Sub'!$B$2:$B$4685, TRIM($C19&"") ) ) ) -> No Subtasks | L19: =IF( COUNTIFS('Dev Tracker Sub'!$A$2:$A$4683, TRIM($B19&""), 'Dev Tracker Sub'!$B$2:$B$4683, TRIM($C19&""))=0, "No Subtasks", IF( SUMPRODUCT( --(TRIM('Dev Tracker Sub'!$A$2:$A$4683&"")=TRIM($B19&"")), --(TRIM('Dev Tracker Sub'!$B$2:$B$4683&"")=TRIM($C19&"")), --(LEN(TRIM('Dev Tracker Sub'!$M$2:$M$4683&""))=0) )>0, "⚠ Missing Effort", SUMIFS( 'Dev Tracker Sub'!$M$2:$M$4683, 'Dev Tracker Sub'!$A$2:$A$4683, TRIM($B19&""), 'Dev Tracker Sub'!$B$2:$B$4683, TRIM($C19&"") ) ) ) -> No Subtasks | R19: TASK UPDATE: DGDA EMS Infra set up | U19: 19ec4f56005ae817
A20: FIA | B20: farnboroughairshow.com | C20: Expo Platform Changes | D20: Low | E20: Sowndar | F20: 46119 | G20: 46122 | I20: Under Review & Testing | J20: Staging | K20: =IF( COUNTIFS('Dev Tracker Sub'!$A$2:$A$4685, TRIM($B20&""), 'Dev Tracker Sub'!$B$2:$B$4685, TRIM($C20&""))=0, "No Subtasks", IF( SUMPRODUCT( --(TRIM('Dev Tracker Sub'!$A$2:$A$4685&"")=TRIM($B20&"")), --(TRIM('Dev Tracker Sub'!$B$2:$B$4685&"")=TRIM($C20&"")), --(LEN(TRIM('Dev Tracker Sub'!$L$2:$L$4685&""))=0) )>0, "⚠ Missing Effort", SUMIFS( 'Dev Tracker Sub'!$L$2:$L$4685, 'Dev Tracker Sub'!$A$2:$A$4685, TRIM($B20&""), 'Dev Tracker Sub'!$B$2:$B$4685, TRIM($C20&"") ) ) ) -> 50 | L20: =IF( COUNTIFS('Dev Tracker Sub'!$A$2:$A$4683, TRIM($B20&""), 'Dev Tracker Sub'!$B$2:$B$4683, TRIM($C20&""))=0, "No Subtasks", IF( SUMPRODUCT( --(TRIM('Dev Tracker Sub'!$A$2:$A$4683&"")=TRIM($B20&"")), --(TRIM('Dev Tracker Sub'!$B$2:$B$4683&"")=TRIM($C20&"")), --(LEN(TRIM('Dev Tracker Sub'!$M$2:$M$4683&""))=0) )>0, "⚠ Missing Effort", SUMIFS( 'Dev Tracker Sub'!$M$2:$M$4683, 'Dev Tracker Sub'!$A$2:$A$4683, TRIM($B20&""), 'Dev Tracker Sub'!$B$2:$B$4683, TRIM($C20&"") ) ) ) -> 23.95 | N20: The Expo platform team's questions have been clarified and shared. We are currently awaiting a response. | Q20: 1) Request for Timeline – FIA Application API Requirement 2) FIA Application - API Process & Data Flow Documentation – Review and Feedback Requested | R20: [Dev Tracker] TASK UPDATE: Expo Platform Changes | U20: 19ecc0b18b5671d1
A21: FIA | B21: farnboroughairshow.com | C21: FIA Website – VAPT Assessment Timeline | D21: Low | I21: Pipeline / To Do | J21: Local | K21: =IF( COUNTIFS('Dev Tracker Sub'!$A$2:$A$4685, TRIM($B21&""), 'Dev Tracker Sub'!$B$2:$B$4685, TRIM($C21&""))=0, "No Subtasks", IF( SUMPRODUCT( --(TRIM('Dev Tracker Sub'!$A$2:$A$4685&"")=TRIM($B21&"")), --(TRIM('Dev Tracker Sub'!$B$2:$B$4685&"")=TRIM($C21&"")), --(LEN(TRIM('Dev Tracker Sub'!$L$2:$L$4685&""))=0) )>0, "⚠ Missing Effort", SUMIFS( 'Dev Tracker Sub'!$L$2:$L$4685, 'Dev Tracker Sub'!$A$2:$A$4685, TRIM($B21&""), 'Dev Tracker Sub'!$B$2:$B$4685, TRIM($C21&"") ) ) ) -> No Subtasks | L21: =IF( COUNTIFS('Dev Tracker Sub'!$A$2:$A$4683, TRIM($B21&""), 'Dev Tracker Sub'!$B$2:$B$4683, TRIM($C21&""))=0, "No Subtasks", IF( SUMPRODUCT( --(TRIM('Dev Tracker Sub'!$A$2:$A$4683&"")=TRIM($B21&"")), --(TRIM('Dev Tracker Sub'!$B$2:$B$4683&"")=TRIM($C21&"")), --(LEN(TRIM('Dev Tracker Sub'!$M$2:$M$4683&""))=0) )>0, "⚠ Missing Effort", SUMIFS( 'Dev Tracker Sub'!$M$2:$M$4683, 'Dev Tracker Sub'!$A$2:$A$4683, TRIM($B21&""), 'Dev Tracker Sub'!$B$2:$B$4683, TRIM($C21&"") ) ) ) -> No Subtasks | Q21: FIA Website – VAPT Assessment Timeline | R21: [Dev Tracker] TASK UPDATE: FIA Website – VAPT Assessment Timeline | U21: 19e348987fbfe133
A22: FIA | B22: events.farnboroughinternational.org | C22: Update 8.18.5 to Umbraco 13 | D22: Low | E22: Sai | I22: Pipeline / To Do | J22: Local | K22: =IF( COUNTIFS('Dev Tracker Sub'!$A$2:$A$4685, TRIM($B22&""), 'Dev Tracker Sub'!$B$2:$B$4685, TRIM($C22&""))=0, "No Subtasks", IF( SUMPRODUCT( --(TRIM('Dev Tracker Sub'!$A$2:$A$4685&"")=TRIM($B22&"")), --(TRIM('Dev Tracker Sub'!$B$2:$B$4685&"")=TRIM($C22&"")), --(LEN(TRIM('Dev Tracker Sub'!$L$2:$L$4685&""))=0) )>0, "⚠ Missing Effort", SUMIFS( 'Dev Tracker Sub'!$L$2:$L$4685, 'Dev Tracker Sub'!$A$2:$A$4685, TRIM($B22&""), 'Dev Tracker Sub'!$B$2:$B$4685, TRIM($C22&"") ) ) ) -> No Subtasks | L22: =IF( COUNTIFS('Dev Tracker Sub'!$A$2:$A$4683, TRIM($B22&""), 'Dev Tracker Sub'!$B$2:$B$4683, TRIM($C22&""))=0, "No Subtasks", IF( SUMPRODUCT( --(TRIM('Dev Tracker Sub'!$A$2:$A$4683&"")=TRIM($B22&"")), --(TRIM('Dev Tracker Sub'!$B$2:$B$4683&"")=TRIM($C22&"")), --(LEN(TRIM('Dev Tracker Sub'!$M$2:$M$4683&""))=0) )>0, "⚠ Missing Effort", SUMIFS( 'Dev Tracker Sub'!$M$2:$M$4683, 'Dev Tracker Sub'!$A$2:$A$4683, TRIM($B22&""), 'Dev Tracker Sub'!$B$2:$B$4683, TRIM($C22&"") ) ) ) -> No Subtasks | N22: Awating Client Input | R22: [Dev Tracker] TASK UPDATE: Update 8.18.5 to Umbraco 13 | U22: 19e3489b196ae0f1
A23: FIA | B23: farnboroughairshow.com | C23: FIA Maintenance June 2026 | D23: Low | F23: 46143 | I23: In Progress | J23: Local | K23: =IF( COUNTIFS('Dev Tracker Sub'!$A$2:$A$4685, TRIM($B23&""), 'Dev Tracker Sub'!$B$2:$B$4685, TRIM($C23&""))=0, "No Subtasks", IF( SUMPRODUCT( --(TRIM('Dev Tracker Sub'!$A$2:$A$4685&"")=TRIM($B23&"")), --(TRIM('Dev Tracker Sub'!$B$2:$B$4685&"")=TRIM($C23&"")), --(LEN(TRIM('Dev Tracker Sub'!$L$2:$L$4685&""))=0) )>0, "⚠ Missing Effort", SUMIFS( 'Dev Tracker Sub'!$L$2:$L$4685, 'Dev Tracker Sub'!$A$2:$A$4685, TRIM($B23&""), 'Dev Tracker Sub'!$B$2:$B$4685, TRIM($C23&"") ) ) ) -> 8 | L23: =IF( COUNTIFS('Dev Tracker Sub'!$A$2:$A$4683, TRIM($B23&""), 'Dev Tracker Sub'!$B$2:$B$4683, TRIM($C23&""))=0, "No Subtasks", IF( SUMPRODUCT( --(TRIM('Dev Tracker Sub'!$A$2:$A$4683&"")=TRIM($B23&"")), --(TRIM('Dev Tracker Sub'!$B$2:$B$4683&"")=TRIM($C23&"")), --(LEN(TRIM('Dev Tracker Sub'!$M$2:$M$4683&""))=0) )>0, "⚠ Missing Effort", SUMIFS( 'Dev Tracker Sub'!$M$2:$M$4683, 'Dev Tracker Sub'!$A$2:$A$4683, TRIM($B23&""), 'Dev Tracker Sub'!$B$2:$B$4683, TRIM($C23&"") ) ) ) -> 8 | R23: [Dev Tracker] TASK UPDATE: FIA Maintenance May 2026 | U23: 19e7db8b3ccc4784
A24: FIA | B24: farnboroughairshow.com | C24: Umbraco Update 13 to 17 | D24: Low | H24: 46266 | I24: Pipeline / To Do | J24: Local | K24: =IF( COUNTIFS('Dev Tracker Sub'!$A$2:$A$4685, TRIM($B24&""), 'Dev Tracker Sub'!$B$2:$B$4685, TRIM($C24&""))=0, "No Subtasks", IF( SUMPRODUCT( --(TRIM('Dev Tracker Sub'!$A$2:$A$4685&"")=TRIM($B24&"")), --(TRIM('Dev Tracker Sub'!$B$2:$B$4685&"")=TRIM($C24&"")), --(LEN(TRIM('Dev Tracker Sub'!$L$2:$L$4685&""))=0) )>0, "⚠ Missing Effort", SUMIFS( 'Dev Tracker Sub'!$L$2:$L$4685, 'Dev Tracker Sub'!$A$2:$A$4685, TRIM($B24&""), 'Dev Tracker Sub'!$B$2:$B$4685, TRIM($C24&"") ) ) ) -> No Subtasks | L24: =IF( COUNTIFS('Dev Tracker Sub'!$A$2:$A$4683, TRIM($B24&""), 'Dev Tracker Sub'!$B$2:$B$4683, TRIM($C24&""))=0, "No Subtasks", IF( SUMPRODUCT( --(TRIM('Dev Tracker Sub'!$A$2:$A$4683&"")=TRIM($B24&"")), --(TRIM('Dev Tracker Sub'!$B$2:$B$4683&"")=TRIM($C24&"")), --(LEN(TRIM('Dev Tracker Sub'!$M$2:$M$4683&""))=0) )>0, "⚠ Missing Effort", SUMIFS( 'Dev Tracker Sub'!$M$2:$M$4683, 'Dev Tracker Sub'!$A$2:$A$4683, TRIM($B24&""), 'Dev Tracker Sub'!$B$2:$B$4683, TRIM($C24&"") ) ) ) -> No Subtasks | R24: TASK UPDATE: Umbraco Update 13 to 17
A25: Vajra Global | B25: vajraglobal.com | C25: Updated SEO Automation BRD | D25: Low | E25: Sowndar | I25: In Progress | J25: Local | K25: =IF( COUNTIFS('Dev Tracker Sub'!$A$2:$A$4685, TRIM($B25&""), 'Dev Tracker Sub'!$B$2:$B$4685, TRIM($C25&""))=0, "No Subtasks", IF( SUMPRODUCT( --(TRIM('Dev Tracker Sub'!$A$2:$A$4685&"")=TRIM($B25&"")), --(TRIM('Dev Tracker Sub'!$B$2:$B$4685&"")=TRIM($C25&"")), --(LEN(TRIM('Dev Tracker Sub'!$L$2:$L$4685&""))=0) )>0, "⚠ Missing Effort", SUMIFS( 'Dev Tracker Sub'!$L$2:$L$4685, 'Dev Tracker Sub'!$A$2:$A$4685, TRIM($B25&""), 'Dev Tracker Sub'!$B$2:$B$4685, TRIM($C25&"") ) ) ) -> No Subtasks | L25: =IF( COUNTIFS('Dev Tracker Sub'!$A$2:$A$4683, TRIM($B25&""), 'Dev Tracker Sub'!$B$2:$B$4683, TRIM($C25&""))=0, "No Subtasks", IF( SUMPRODUCT( --(TRIM('Dev Tracker Sub'!$A$2:$A$4683&"")=TRIM($B25&"")), --(TRIM('Dev Tracker Sub'!$B$2:$B$4683&"")=TRIM($C25&"")), --(LEN(TRIM('Dev Tracker Sub'!$M$2:$M$4683&""))=0) )>0, "⚠ Missing Effort", SUMIFS( 'Dev Tracker Sub'!$M$2:$M$4683, 'Dev Tracker Sub'!$A$2:$A$4683, TRIM($B25&""), 'Dev Tracker Sub'!$B$2:$B$4683, TRIM($C25&"") ) ) ) -> No Subtasks | N25: Indexing, Keyword research, Competitor Analysis API Credits, Techinical Feasbility Token Common feature | R25: [Dev Tracker] TASK UPDATE: Updated SEO Automation BRD | U25: 19df666b384b7115
A26: Vajra Global | B26: vajraglobal.com | C26: Seo Automation Tool | D26: Low | E26: Rackesh Kumaran | I26: In Progress | J26: Local | K26: =IF( COUNTIFS('Dev Tracker Sub'!$A$2:$A$4685, TRIM($B26&""), 'Dev Tracker Sub'!$B$2:$B$4685, TRIM($C26&""))=0, "No Subtasks", IF( SUMPRODUCT( --(TRIM('Dev Tracker Sub'!$A$2:$A$4685&"")=TRIM($B26&"")), --(TRIM('Dev Tracker Sub'!$B$2:$B$4685&"")=TRIM($C26&"")), --(LEN(TRIM('Dev Tracker Sub'!$L$2:$L$4685&""))=0) )>0, "⚠ Missing Effort", SUMIFS( 'Dev Tracker Sub'!$L$2:$L$4685, 'Dev Tracker Sub'!$A$2:$A$4685, TRIM($B26&""), 'Dev Tracker Sub'!$B$2:$B$4685, TRIM($C26&"") ) ) ) -> 148 | L26: =IF( COUNTIFS('Dev Tracker Sub'!$A$2:$A$4683, TRIM($B26&""), 'Dev Tracker Sub'!$B$2:$B$4683, TRIM($C26&""))=0, "No Subtasks", IF( SUMPRODUCT( --(TRIM('Dev Tracker Sub'!$A$2:$A$4683&"")=TRIM($B26&"")), --(TRIM('Dev Tracker Sub'!$B$2:$B$4683&"")=TRIM($C26&"")), --(LEN(TRIM('Dev Tracker Sub'!$M$2:$M$4683&""))=0) )>0, "⚠ Missing Effort", SUMIFS( 'Dev Tracker Sub'!$M$2:$M$4683, 'Dev Tracker Sub'!$A$2:$A$4683, TRIM($B26&""), 'Dev Tracker Sub'!$B$2:$B$4683, TRIM($C26&"") ) ) ) -> 150 | R26: TASK UPDATE: Seo Automation Tool
A27: Vajra Global | B27: vajraglobal.com | C27: Server Monitoring Implementation Plan | D27: Low | E27: Moswin | I27: In Progress | J27: Local | R27: TASK UPDATE: Server Monitoring Implementation Plan

Sheet Pending Changes
A1: Timestamp | B1: Subject | C1: MainRowIndex
A2: 46157.575 | B2: Project Update: Open data form Phase - 2 | C2: 22
A3: 46157.575 | B3: Project Update: Open data form Phase - 2 | C3: 22
A4: 46157.589 | B4: National Design System (DGA) | C4: 10
A5: 46157.589 | B5: National Design System (DGA) | C5: 10
A6: 46157.598 | B6: Project Update: Open data form Phase - 2 | C6: 10
A7: 46157.598 | B7: Project Update: Open data form Phase - 2 | C7: 10
A8: 46157.598 | B8: Project Update: Open data form Phase - 2 | C8: 10
A9: 46157.598 | B9: Project Update: Open data form Phase - 2 | C9: 10
A10: 46157.627 | B10: National Design System (DGA) | C10: 11
A11: 46157.627 | B11: National Design System (DGA) | C11: 11
A12: 46157.627 | B12: National Design System (DGA) | C12: 11
A13: 46157.627 | B13: National Design System (DGA) | C13: 11
... A61: 46159.402 | B61: Project Update: Demo Page | C61: 2
A62: 46159.404
A63: 46159.452 | B63: [Dev Tracker] TASK UPDATE: Demo Page | C63: 2
A64: 46159.468 | B64: [Dev Tracker] TASK UPDATE: Open data form Phase - 2 | C64: 10
A65: 46159.468 | B65: [Dev Tracker] TASK UPDATE: Open data form Phase - 2 | C65: 10
A66: 46159.484 | B66: [Dev Tracker] TASK UPDATE: Demo Page | C66: 2
A67: 46159.484 | B67: [Dev Tracker] TASK UPDATE: Demo Page | C67: 2
A68: 46160.4 | B68: [Dev Tracker] TASK UPDATE: Open data form Phase - 2 | C68: 10
A69: 46160.4 | B69: [Dev Tracker] TASK UPDATE: Open data form Phase - 2 | C69: 10
A70: 46160.739 | B70: [Dev Tracker] TASK UPDATE: Open data form Phase - 2 | C70: 10
A71: 46160.808 | B71: [Dev Tracker] TASK UPDATE: Demo Page | C71: 2
A72: 46160.808 | B72: [Dev Tracker] TASK UPDATE: Demo Page | C72: 2
A73: 46160.812 | B73: [Dev Tracker] TASK UPDATE: Open data form Phase - 2 | C73: 10
A74: 46160.812 | B74: [Dev Tracker] TASK UPDATE: Open data form Phase - 2 | C74: 10
... A349: 46192.419 | B349: TASK UPDATE: Seo Automation Tool | C349: 26

Sheet Completed Tracker
A1: Project Name | B1: Website Url | C1: Task | D1: Priority | E1: Assign | F1: S Date | G1: E Date | H1: As Per WO | I1: Status | J1: Env | K1: Efforts | L1: Actual Effort | M1: Informed | N1: Comment | O1: Dependency Detail | P1: Page Url | Q1: Mail Subject | R1: Internal Mail Subject
A2: Adfactors PR Private Limited | B2: intranet.adfactorspr.com | C2: Holiday List Page | D2: Low | E2: Parthiban | F2: 45995 | G2: 46003 | I2: Completed | J2: Production | K2: 50 | M2: 15 | N2: Page Develoment has completed asked the content for this
A3: Diriyah Gate Development Authority | B3: www.dgs.sa | C3: DGS Registration form | D3: Low | E3: Sowndar | F3: 45980 | G3: 45980 | I3: Completed | J3: Production | K3: 20 | N3: The C4C team is currently conducting the review and testing of the form within SAP. We sent a follow-up yesterday, as they had anticipated completing this process today (December 2, 2025). Upon the conclusion of testing and client sign-off, the next step is immediate deployment to the live environment. However, the team has decided they do not wish to proceed with the SAP integration; instead, they prefer to continue using the existing process of fetching email details and storing them in an Excel file.
A4: FIA | B4: farnborough.com | C4: Update the form date format | D4: Low | E4: Abhicheke | F4: 45999 | G4: 45999 | I4: Completed | J4: Production | N4: Done Moved To Production
A5: Diriyah Gate Development Authority | B5: www.dgs.sa | C5: SEO Assets for DGS Site | D5: Low | E5: Regan | F5: 45980 | I5: Completed | N5: We have shared the document with the client on December 1, 2025 and are now awaiting their reply and approval. 2nd follow-up sent on December 8, 2025. Awaiting client response Once they approve the changes and provide the Arabic content, we will update the DGS live environment. Since the the event has complete we consider this task has closed | Q5: DGS Microsite | R5: SEO Assets for DGS Site (Discussed 11-11-2025)
A6: Diriyah Gate Development Authority | B6: www.dgs.sa | C6: Missing Content on DGS Page | D6: Low | E6: Regan | I6: Completed | N6: We sent a follow-up on December 1, 2025, second follow-up , December 8, 2025. Since the the event has complete we consider this task has closed
A7: Diriyah Gate Development Authority | B7: www.dgda.gov.sa | C7: Initial Wireframes | D7: Low | E7: Balaji | F7: 46006 | G7: 46008 | I7: Completed
A8: Diriyah Gate Development Authority | B8: www.dgda.gov.sa | C8: Forms Character Limit for DGDA and DGS | D8: Low | E8: Regan | F8: 46006 | G8: 46014 | I8: Completed | J8: Production | N8: Dayel has agreed to proceed with the form limit, and the team has started working on it. | Q8: Validations required DGDA forms
A9: Diriyah Gate Development Authority | B9: www.dgda.gov.sa | C9: DGDA Version Update | D9: Low | E9: Abhicheke | F9: 46006 | G9: 46010 | H9: 46014 | I9: Completed | J9: Production | N9: Move the changes to live. 14.2.25 – 15.5.25
A10: Adfactors PR Private Limited | B10: intranet.adfactorspr.com | C10: Adfactor Home Page feature Phase 1 | D10: Low | E10: Parthiban | F10: 46006 | G10: 46008 | I10: Completed | J10: Production | K10: 20
A11: DGS | B11: www.dgs.sa | C11: DGS Home | D11: High | E11: Abhicheke | F11: 46015 | G11: 46028 | H11: 46022 | I11: Completed | J11: Production | N11: Client Approved on 05 Jan 2025 and updated the changes on live | Q11: DGS Microsite
A12: Diriyah Gate Development Authority | B12: www.dgda.gov.sa | C12: Hide Media From Search Console | D12: Low | E12: Regan | F12: 46001 | G12: 46002 | I12: On Hold / Blocked | N12: David needs to get back to us. As regan mentioned david was just asked like why this is showing
A13: Adfactors PR Private Limited | B13: intranet.adfactorspr.com | C13: Holiday List Page | D13: Low | E13: Parthiban | I13: Completed | J13: Production | N13: Changes has done by Adfactor Team
A14: FIA | B14: farnboroughairshow.com | C14: Phase 2 Brand GuidLine Change POI | D14: Low | E14: Abhicheke | F14: 45994 | G14: 46043 | I14: Completed | J14: Production | K14: 50 | N14: Done all the changes and Moved to Production on 21 Dec 2025. | Q14: Pioneers of Tomorrow - Brand Updates
A15: FIA | B15: farnboroughairshow.com | C15: FIA Changes on Show Theme | D15: Low | E15: Abhicheke | F15: 46001 | G15: 46041 | I15: Completed | J15: Production | K15: 10 | N15: Done all the changes and Moved to Production on 19 Dec 2025.
A16: FIA | B16: farnborough.com | C16: Farnborough Canceled Event | D16: Low | E16: Parthiban | F16: 46008 | G16: 46041 | H16: 46014 | I16: Completed | J16: Production | K16: 10 | N16: Done all the changes and Moved to Production on 19 Dec 2025.
A17: FIA | B17: farnboroughairshow.com | C17: FIA Version Update | D17: Low | E17: Abhicheke | F17: 46027 | G17: 46041 | I17: Completed | J17: Production | K17: 30 | N17: Version Update 13.9.1 to 13.13.0 in FarnboroughAirshow Updated the Umbraco version 13.10.0 to 13.13.0 in Farnborough Vennue
A18: FIA | B18: farnboroughairshow.com | C18: POT Feed Back changes | D18: Low | E18: Abhicheke | F18: 46031 | G18: 46041 | H18: 46034 | I18: Completed | J18: Production
A19: FIA | B19: farnboroughinternationalstudios.com | C19: Studio Site Version Update | D19: Low | E19: Abhicheke | F19: 46041 | G19: 46043 | I19: Completed | J19: Production | N19: Done all the changes and Moved to Production on 21 Dec 2025.
A20: FIA | B20: farnboroughinternationalstudios.com | C20: New Testimonial Page | D20: Low | E20: Abhicheke | F20: 46051 | G20: 46055 | H20: 46055 | I20: Completed | J20: Production | N20: Done all the changes and Moved to Production on 02 Feb 2026
A21: Diriyah Gate Development Authority | B21: www.dgda.gov.sa | C21: Form Failed Feb-2026 | D21: Low | E21: Abhicheke | F21: 46057 | G21: 46058 | H21: 46058 | I21: Completed | J21: Production | N21: We recommend the to reduce the file size from 5mb to 2mb since the size of payload is very high after change this it start working without any issue
A22: FIA | B22: farnboroughairshow.com | C22: Phase 1 Brand GuidLine Change | D22: Low | E22: Abhicheke | F22: 45982 | G22: 46043 | H22: 45992 | I22: Completed | J22: Production | K22: 70 | M22: 20 | N22: Done all the changes and Moved to Production on 21 Dec 2025. However the recent sub task(Came after 21 Dec 2025) which we need to approve to move live. Waiting for Client Approval
A23: Adfactors PR Private Limited | B23: intranet.adfactorspr.com | C23: Adfactor Home Page feature Phase 2 | D23: Low | E23: Parthiban | I23: Completed | J23: Production
A24: Diriyah Gate Development Authority | B24: www.dgda.gov.sa | C24: Summer Program Page | D24: Low | E24: Abhicheke | F24: 45993 | G24: 46002 | I24: Closed – Billable | J24: Staging | K24: 30 | N24: DGDA has updated the Arabic site content and finalized development. Staging and CRM integration were completed on Dec 23rd. Per Dayel’s instructions, the schedule is postponed to Nov 2026, and this task is now considered closed. As discussed with Saad Event postponned to November 2026, will close the activity. | P24: Payload: Diriyah Horizons - Leadership Programme - Fields Name Payload | Q24: Summer Program Page | R24: Arabic Content and Missing Form Fields for Summer Camp Page
A25: Diriyah Gate Development Authority | B25: www.dgda.gov.sa | C25: Leadership component | D25: Low | E25: Abhicheke | F25: 46058 | G25: 46065 | I25: Completed | J25: Production | N25: We updated the Leadership Component design, including new content and imagery, and submitted it on 09 Feb. Per the client's request on 12 Feb, However, per client instructions on 12 Feb, the final launch is on hold pending direction from their top management. Work completed on 9 Feb, CEO message live 24 Feb | Q25: Leadership component Development for DGA guidelines and Website Content
A26: Adfactors PR Private Limited | B26: intranet.adfactorspr.com | C26: Academy Page | D26: Low | E26: Parthiban | F26: 46058 | G26: 46065 | I26: Completed | J26: Production | N26: The page was completed and moved to staging. A follow-up was sent on 10/02. The team gave another set of V2 changes on 11/02, which were completed and shared with the client on 13/02. The asked to add few other section we added and share it with client on 19 Feb Few other changes requested by Client AW Completed and Moved To Production on 09 March | Q26: New Intranet Page - Adfactors Academy
A27: Adfactors PR Private Limited | B27: intranet.adfactorspr.com | C27: Author Name on Articale Page | D27: Low | F27: 46069 | G27: 46069 | H27: 46073 | I27: Completed | J27: Production | N27: Give two option to the Client waiting for Input from them Completed and Moved To Production on 09 March
A28: Adfactors PR Private Limited | B28: intranet.adfactorspr.com | C28: AF Server Changes | D28: Low | E28: Sowndar | F28: 46065 | G28: 46066 | H28: 46072 | I28: Completed | J28: Production | N28: Team is start working this on 13 Feb. The team need cross testing the full website FTP The changes has done eveything is working ask expected. Completed Three website need to move one more site once it is done point to new server | Q28: Request for Review – New Intranet Website Before Migration
A29: Diriyah Gate Development Authority | B29: www.dgda.gov.sa | C29: Founding day 2026 | D29: Low | F29: 46071 | G29: 46072 | H29: 46080 | I29: Completed | J29: Staging | N29: Compleleted and share it with client on 20 Feb. AW for Feedback. Since the event is finished we need to rised the billing only eventhout it is not moved to live | Q29: Founding Day 2026
A30: Adfactors PR Private Limited | B30: intranet.adfactorspr.com | C30: Academy Page - 2 | D30: Low | E30: Parthiban | F30: 46070 | G30: 46070 | H30: 46073 | I30: Completed | J30: Production | N30: Updated the content from live to staging, removed tab spacing where empty, and completed the share with the client on 17 March | Q30: New Intranet Page - Adfactors Academy
A31: Diriyah Gate Development Authority | B31: www.dgda.gov.sa | C31: Form Tracking GA | D31: Low | E31: Ranjith | F31: 45975 | G31: 46021 | I31: Completed | J31: Production | K31: 30 | N31: Ranjith confirmed the implementation is functional and has updated the client. Following the DGDA review AW response from David. Since i spoke to Regan he | R31: Regarding the DGDA Form changes | S31: Improve this
A32: FIA | B32: farnboroughairshow.com | C32: FIA AGF Page changes | D32: Low | E32: Parthiban | F32: 46034 | G32: 46035 | H32: 46035 | I32: Completed | J32: Production | K32: 6 | N32: Completed and share it with Clinet. The client mentioned the will update the content and do the changes
A33: FIA | B33: farnboroughairshow.com | C33: Feb Maintenance changes - 2026 | D33: Low | F33: 46078 | G33: 46078 | H33: 46080 | I33: Completed | J33: Production | N33: Completed
A34: FIA | B34: farnboroughairshow.com | C34: MPU Functionality | D34: Low | F34: 46090 | G34: 46091 | H34: 46091 | I34: Completed | J34: Production
A35: FIA | B35: farnboroughairshow.com | C35: FIECC - Landing page | D35: Low | F35: 46094 | G35: 46097 | H35: 46097 | I35: Completed | J35: Production | N35: Shared with Client on 16 March However they haven't white list the IP from thir end for staging so they couldn't access the website so the will do the check once white list Moved To Production 24 March 1.Currently, we have Lorem Ipsum on the live site. 2.Currently, we have a dummy banner and gallery images on the live site. 3.Currently, we do not have the Checklist ID for the form; the submitted data will be sent to event-enquiries@farnborough.com. 4.Currently, we have a dummy sample PDF, which will be downloaded after someone submits the form.
A36: Diriyah Gate Development Authority | B36: www.dgda.gov.sa | C36: AlMedad Form | I36: Completed | J36: Production | N36: AlMedad Form Submission error due to arabic content on input value | Q36: [NEW TASK] [DGDA] SignUp Form Button Changes
A37: FIA | B37: aerospaceglobalforum.com | C37: Update 10.8.7 to Umbraco 13 | D37: Low | E37: Sai | I37: Closed / Cancelled | N37: Awating Client Input | R37: Website Update - Phase 1.
A38: FIA | B38: farnboroughairshow.com | C38: FIA.com - Marketing Toolkit Page | E38: Parthiban | F38: 46113 | G38: 46121 | I38: Completed | J38: Production | K38: =IF( COUNTIFS('Dev Tracker Sub'!$A$2:$A$4685, TRIM($B38&""), 'Dev Tracker Sub'!$B$2:$B$4685, TRIM($C38&""))=0, "No Subtasks", IF( SUMPRODUCT( --(TRIM('Dev Tracker Sub'!$A$2:$A$4685&"")=TRIM($B38&"")), --(TRIM('Dev Tracker Sub'!$B$2:$B$4685&"")=TRIM($C38&"")), --(LEN(TRIM('Dev Tracker Sub'!$L$2:$L$4685&""))=0) )>0, "⚠ Missing Effort", SUMIFS( 'Dev Tracker Sub'!$L$2:$L$4685, 'Dev Tracker Sub'!$A$2:$A$4685, TRIM($B38&""), 'Dev Tracker Sub'!$B$2:$B$4685, TRIM($C38&"") ) ) ) -> 13.5 | L38: =IF( COUNTIFS('Dev Tracker Sub'!$A$2:$A$4683, TRIM($B38&""), 'Dev Tracker Sub'!$B$2:$B$4683, TRIM($C38&""))=0, "No Subtasks", IF( SUMPRODUCT( --(TRIM('Dev Tracker Sub'!$A$2:$A$4683&"")=TRIM($B38&"")), --(TRIM('Dev Tracker Sub'!$B$2:$B$4683&"")=TRIM($C38&"")), --(LEN(TRIM('Dev Tracker Sub'!$M$2:$M$4683&""))=0) )>0, "⚠ Missing Effort", SUMIFS( 'Dev Tracker Sub'!$M$2:$M$4683, 'Dev Tracker Sub'!$A$2:$A$4683, TRIM($B38&""), 'Dev Tracker Sub'!$B$2:$B$4683, TRIM($C38&"") ) ) ) -> 1.5 | N38: Done the changes and moved to staging AW for Customer feed back | R38: [NEW TASK] [FIA] - FIA.com - Marketing Toolkit Page
A39: Diriyah Gate Development Authority | B39: www.dgda.gov.sa | C39: Urban Living | D39: Low | E39: Regan | I39: Closed – Billable | K39: =IF( COUNTIFS('Dev Tracker Sub'!$A$2:$A$4685, TRIM($B39&""), 'Dev Tracker Sub'!$B$2:$B$4685, TRIM($C39&""))=0, "No Subtasks", IF( SUMPRODUCT( --(TRIM('Dev Tracker Sub'!$A$2:$A$4685&"")=TRIM($B39&"")), --(TRIM('Dev Tracker Sub'!$B$2:$B$4685&"")=TRIM($C39&"")), --(LEN(TRIM('Dev Tracker Sub'!$L$2:$L$4685&""))=0) )>0, "⚠ Missing Effort", SUMIFS( 'Dev Tracker Sub'!$L$2:$L$4685, 'Dev Tracker Sub'!$A$2:$A$4685, TRIM($B39&""), 'Dev Tracker Sub'!$B$2:$B$4685, TRIM($C39&"") ) ) ) -> No Subtasks | L39: =IF( COUNTIFS('Dev Tracker Sub'!$A$2:$A$4683, TRIM($B39&""), 'Dev Tracker Sub'!$B$2:$B$4683, TRIM($C39&""))=0, "No Subtasks", IF( SUMPRODUCT( --(TRIM('Dev Tracker Sub'!$A$2:$A$4683&"")=TRIM($B39&"")), --(TRIM('Dev Tracker Sub'!$B$2:$B$4683&"")=TRIM($C39&"")), --(LEN(TRIM('Dev Tracker Sub'!$M$2:$M$4683&""))=0) )>0, "⚠ Missing Effort", SUMIFS( 'Dev Tracker Sub'!$M$2:$M$4683, 'Dev Tracker Sub'!$A$2:$A$4683, TRIM($B39&""), 'Dev Tracker Sub'!$B$2:$B$4683, TRIM($C39&"") ) ) ) -> No Subtasks | N39: Map approach shared with DGDA on 25/11, AW feedback. Also we are waiting to hear from UMA team on the section mapping for Urban Living. Waiting for UMA section mapping As discussed, we will proceed with the closure as there are no plans for now to launch this page.
A40: Diriyah Gate Development Authority | B40: www.dgda.gov.sa | C40: 360 Degree Image new website | D40: Low | E40: Regan | I40: Closed / Cancelled | K40: =IF( COUNTIFS('Dev Tracker Sub'!$A$2:$A$4685, TRIM($B40&""), 'Dev Tracker Sub'!$B$2:$B$4685, TRIM($C40&""))=0, "No Subtasks", IF( SUMPRODUCT( --(TRIM('Dev Tracker Sub'!$A$2:$A$4685&"")=TRIM($B40&"")), --(TRIM('Dev Tracker Sub'!$B$2:$B$4685&"")=TRIM($C40&"")), --(LEN(TRIM('Dev Tracker Sub'!$L$2:$L$4685&""))=0) )>0, "⚠ Missing Effort", SUMIFS( 'Dev Tracker Sub'!$L$2:$L$4685, 'Dev Tracker Sub'!$A$2:$A$4685, TRIM($B40&""), 'Dev Tracker Sub'!$B$2:$B$4685, TRIM($C40&"") ) ) ) -> 0 | L40: =IF( COUNTIFS('Dev Tracker Sub'!$A$2:$A$4683, TRIM($B40&""), 'Dev Tracker Sub'!$B$2:$B$4683, TRIM($C40&""))=0, "No Subtasks", IF( SUMPRODUCT( --(TRIM('Dev Tracker Sub'!$A$2:$A$4683&"")=TRIM($B40&"")), --(TRIM('Dev Tracker Sub'!$B$2:$B$4683&"")=TRIM($C40&"")), --(LEN(TRIM('Dev Tracker Sub'!$M$2:$M$4683&""))=0) )>0, "⚠ Missing Effort", SUMIFS( 'Dev Tracker Sub'!$M$2:$M$4683, 'Dev Tracker Sub'!$A$2:$A$4683, TRIM($B40&""), 'Dev Tracker Sub'!$B$2:$B$4683, TRIM($C40&"") ) ) ) -> 0 | N40: Infra - 70Hrs Developement and testing - 120Hrs David said on December 1, 2025 he will come back to us
A41: Diriyah Gate Development Authority | B41: www.dgda.gov.sa | C41: Content Update – Feb 2026 | D41: Medium | E41: Abhicheke | F41: 46055 | G41: 46058 | H41: 46058 | I41: Closed – Billable | J41: Production | K41: =IF( COUNTIFS('Dev Tracker Sub'!$A$2:$A$4685, TRIM($B41&""), 'Dev Tracker Sub'!$B$2:$B$4685, TRIM($C41&""))=0, "No Subtasks", IF( SUMPRODUCT( --(TRIM('Dev Tracker Sub'!$A$2:$A$4685&"")=TRIM($B41&"")), --(TRIM('Dev Tracker Sub'!$B$2:$B$4685&"")=TRIM($C41&"")), --(LEN(TRIM('Dev Tracker Sub'!$L$2:$L$4685&""))=0) )>0, "⚠ Missing Effort", SUMIFS( 'Dev Tracker Sub'!$L$2:$L$4685, 'Dev Tracker Sub'!$A$2:$A$4685, TRIM($B41&""), 'Dev Tracker Sub'!$B$2:$B$4685, TRIM($C41&"") ) ) ) -> 0 | L41: =IF( COUNTIFS('Dev Tracker Sub'!$A$2:$A$4683, TRIM($B41&""), 'Dev Tracker Sub'!$B$2:$B$4683, TRIM($C41&""))=0, "No Subtasks", IF( SUMPRODUCT( --(TRIM('Dev Tracker Sub'!$A$2:$A$4683&"")=TRIM($B41&"")), --(TRIM('Dev Tracker Sub'!$B$2:$B$4683&"")=TRIM($C41&"")), --(LEN(TRIM('Dev Tracker Sub'!$M$2:$M$4683&""))=0) )>0, "⚠ Missing Effort", SUMIFS( 'Dev Tracker Sub'!$M$2:$M$4683, 'Dev Tracker Sub'!$A$2:$A$4683, TRIM($B41&""), 'Dev Tracker Sub'!$B$2:$B$4683, TRIM($C41&"") ) ) ) -> 0 | N41: Completed and Initial preview links were distributed on 5 February. Following this, Saad requested a hold on 12 February pending executive direction.Preview shared, waiting sign-off from top management. To Be Billed in Feb - April 2026 | Q41: Development for DGA guidelines and Website Content | R41: Content Update Required for DGDA
A42: Diriyah Gate Development Authority | B42: www.dgda.gov.sa | C42: XMCC Migration | D42: High | E42: Regan | I42: Closed / Cancelled | J42: Production | K42: =IF( COUNTIFS('Dev Tracker Sub'!$A$2:$A$4685, TRIM($B42&""), 'Dev Tracker Sub'!$B$2:$B$4685, TRIM($C42&""))=0, "No Subtasks", IF( SUMPRODUCT( --(TRIM('Dev Tracker Sub'!$A$2:$A$4685&"")=TRIM($B42&"")), --(TRIM('Dev Tracker Sub'!$B$2:$B$4685&"")=TRIM($C42&"")), --(LEN(TRIM('Dev Tracker Sub'!$L$2:$L$4685&""))=0) )>0, "⚠ Missing Effort", SUMIFS( 'Dev Tracker Sub'!$L$2:$L$4685, 'Dev Tracker Sub'!$A$2:$A$4685, TRIM($B42&""), 'Dev Tracker Sub'!$B$2:$B$4685, TRIM($C42&"") ) ) ) -> 0 | L42: =IF( COUNTIFS('Dev Tracker Sub'!$A$2:$A$4683, TRIM($B42&""), 'Dev Tracker Sub'!$B$2:$B$4683, TRIM($C42&""))=0, "No Subtasks", IF( SUMPRODUCT( --(TRIM('Dev Tracker Sub'!$A$2:$A$4683&"")=TRIM($B42&"")), --(TRIM('Dev Tracker Sub'!$B$2:$B$4683&"")=TRIM($C42&"")), --(LEN(TRIM('Dev Tracker Sub'!$M$2:$M$4683&""))=0) )>0, "⚠ Missing Effort", SUMIFS( 'Dev Tracker Sub'!$M$2:$M$4683, 'Dev Tracker Sub'!$A$2:$A$4683, TRIM($B42&""), 'Dev Tracker Sub'!$B$2:$B$4683, TRIM($C42&"") ) ) ) -> 0 | N42: Sitecore team to review the exisitng code for any impacts, AW update. Github access granted to them on 11/12. Last update is that migration planned for March 31st. Follow up sent on 11/2 Awaiting update from migration team. Awaiting for update from DGDA to initiate as we have recived confirmation to work on DGA (NDS) As Per 13 April Meeting Saad to confirm IT strategy on CH1. Migration cannot run in parallel with DGA. XMCC Migration Dropped | R42: Sitecore Migration CH1 to XMCC | S42: Need to follow up
A43: Diriyah Gate Development Authority | B43: www.dgda.gov.sa | C43: Open data form | D43: Low | E43: DGDA | F43: 45974 | I43: Closed – Billable | J43: Production | K43: =IF( COUNTIFS('Dev Tracker Sub'!$A$2:$A$4685, TRIM($B43&""), 'Dev Tracker Sub'!$B$2:$B$4685, TRIM($C43&""))=0, "No Subtasks", IF( SUMPRODUCT( --(TRIM('Dev Tracker Sub'!$A$2:$A$4685&"")=TRIM($B43&"")), --(TRIM('Dev Tracker Sub'!$B$2:$B$4685&"")=TRIM($C43&"")), --(LEN(TRIM('Dev Tracker Sub'!$L$2:$L$4685&""))=0) )>0, "⚠ Missing Effort", SUMIFS( 'Dev Tracker Sub'!$L$2:$L$4685, 'Dev Tracker Sub'!$A$2:$A$4685, TRIM($B43&""), 'Dev Tracker Sub'!$B$2:$B$4685, TRIM($C43&"") ) ) ) -> No Subtasks | L43: =IF( COUNTIFS('Dev Tracker Sub'!$A$2:$A$4683, TRIM($B43&""), 'Dev Tracker Sub'!$B$2:$B$4683, TRIM($C43&""))=0, "No Subtasks", IF( SUMPRODUCT( --(TRIM('Dev Tracker Sub'!$A$2:$A$4683&"")=TRIM($B43&"")), --(TRIM('Dev Tracker Sub'!$B$2:$B$4683&"")=TRIM($C43&"")), --(LEN(TRIM('Dev Tracker Sub'!$M$2:$M$4683&""))=0) )>0, "⚠ Missing Effort", SUMIFS( 'Dev Tracker Sub'!$M$2:$M$4683, 'Dev Tracker Sub'!$A$2:$A$4683, TRIM($B43&""), 'Dev Tracker Sub'!$B$2:$B$4683, TRIM($C43&"") ) ) ) -> No Subtasks | N43: DGDA Website updates - SDAIA Compliance Development work is finished. The task has been handed over to Majd’s team (C4C) for testing and SAP form configuration. Deployment will proceed once their work and the C4C setup are finalized. Follow up sent to CRM team on 1 Feb. Completed by CRM team – awaiting confirmation As discussed 13 April, we will proceed with the closure as there are no plans from the team to proceed with live. Billed on June - Aug 2025 | P43: Payload: Data Request Open Data Form - Fields Name Payload | R43: Open Data Form | U43: 19dd348c2296a417
A44: Diriyah Gate Development Authority | B44: www.dgda.gov.sa | C44: Uma Form | D44: Low | E44: Abhicheke | F44: 46015 | I44: Closed – Billable | J44: Staging | K44: =IF( COUNTIFS('Dev Tracker Sub'!$A$2:$A$4685, TRIM($B44&""), 'Dev Tracker Sub'!$B$2:$B$4685, TRIM($C44&""))=0, "No Subtasks", IF( SUMPRODUCT( --(TRIM('Dev Tracker Sub'!$A$2:$A$4685&"")=TRIM($B44&"")), --(TRIM('Dev Tracker Sub'!$B$2:$B$4685&"")=TRIM($C44&"")), --(LEN(TRIM('Dev Tracker Sub'!$L$2:$L$4685&""))=0) )>0, "⚠ Missing Effort", SUMIFS( 'Dev Tracker Sub'!$L$2:$L$4685, 'Dev Tracker Sub'!$A$2:$A$4685, TRIM($B44&""), 'Dev Tracker Sub'!$B$2:$B$4685, TRIM($C44&"") ) ) ) -> 0 | L44: =IF( COUNTIFS('Dev Tracker Sub'!$A$2:$A$4683, TRIM($B44&""), 'Dev Tracker Sub'!$B$2:$B$4683, TRIM($C44&""))=0, "No Subtasks", IF( SUMPRODUCT( --(TRIM('Dev Tracker Sub'!$A$2:$A$4683&"")=TRIM($B44&"")), --(TRIM('Dev Tracker Sub'!$B$2:$B$4683&"")=TRIM($C44&"")), --(LEN(TRIM('Dev Tracker Sub'!$M$2:$M$4683&""))=0) )>0, "⚠ Missing Effort", SUMIFS( 'Dev Tracker Sub'!$M$2:$M$4683, 'Dev Tracker Sub'!$A$2:$A$4683, TRIM($B44&""), 'Dev Tracker Sub'!$B$2:$B$4683, TRIM($C44&"") ) ) ) -> 0 | N44: Development on all ER forms was completed and delivered on 6/1. The team is currently working on the Arabic content for the approved forms, with an ETA of 18/1. The forms were shared with the CRM team on 7/1; we are awaiting a response to proceed with integration. David sent a follow-up to the team, and an additional follow-up was sent on 2 Feb (still awaiting response). We Suggest To Set the call and discuss this. Forms delivered, waiting CRM integration response Saad asked us to hold and move to closed | Q44: DGDA Forms meeting with Technology + UMA + CRM | R44: Completed Uma Forms | Questions Regarding Missing Content
A45: Diriyah Gate Development Authority | B45: www.dgda.gov.sa | C45: DevSecOps Onboarding (Intoducing security scripts in our GitHub pipelines) DGDA DevSecOps pipelines set up | D45: Low | F45: 46009 | I45: Completed | J45: Production | K45: =IF( COUNTIFS('Dev Tracker Sub'!$A$2:$A$4685, TRIM($B45&""), 'Dev Tracker Sub'!$B$2:$B$4685, TRIM($C45&""))=0, "No Subtasks", IF( SUMPRODUCT( --(TRIM('Dev Tracker Sub'!$A$2:$A$4685&"")=TRIM($B45&"")), --(TRIM('Dev Tracker Sub'!$B$2:$B$4685&"")=TRIM($C45&"")), --(LEN(TRIM('Dev Tracker Sub'!$L$2:$L$4685&""))=0) )>0, "⚠ Missing Effort", SUMIFS( 'Dev Tracker Sub'!$L$2:$L$4685, 'Dev Tracker Sub'!$A$2:$A$4685, TRIM($B45&""), 'Dev Tracker Sub'!$B$2:$B$4685, TRIM($C45&"") ) ) ) -> No Subtasks | L45: =IF( COUNTIFS('Dev Tracker Sub'!$A$2:$A$4683, TRIM($B45&""), 'Dev Tracker Sub'!$B$2:$B$4683, TRIM($C45&""))=0, "No Subtasks", IF( SUMPRODUCT( --(TRIM('Dev Tracker Sub'!$A$2:$A$4683&"")=TRIM($B45&"")), --(TRIM('Dev Tracker Sub'!$B$2:$B$4683&"")=TRIM($C45&"")), --(LEN(TRIM('Dev Tracker Sub'!$M$2:$M$4683&""))=0) )>0, "⚠ Missing Effort", SUMIFS( 'Dev Tracker Sub'!$M$2:$M$4683, 'Dev Tracker Sub'!$A$2:$A$4683, TRIM($B45&""), 'Dev Tracker Sub'!$B$2:$B$4683, TRIM($C45&"") ) ) ) -> No Subtasks | N45: Alwosta submitted the Phase 1 questionnaire to DevSecOps on 22/12. We are pending an update from the DGDA Infra team before starting Phase 2. Following the delivery of prerequisites on 13/01 and a follow-up on 25/01, we coordinated with Busma to initiate the server setup. Ticket RITM0037232 was successfully raised today, 02 Feb Phase-2 pending Infra team approval Blocker: Saad to obtain IT update/clearance for Alwosta to run security scripts. | R45: Status Update on DGDA DevSecOps Pipelines Setup
A46: Diriyah Gate Development Authority | B46: www.dgda.gov.sa | C46: Cybersecurity Compliance Self-Assessment | D46: Low | I46: Completed | J46: Production | K46: =IF( COUNTIFS('Dev Tracker Sub'!$A$2:$A$4685, TRIM($B46&""), 'Dev Tracker Sub'!$B$2:$B$4685, TRIM($C46&""))=0, "No Subtasks", IF( SUMPRODUCT( --(TRIM('Dev Tracker Sub'!$A$2:$A$4685&"")=TRIM($B46&"")), --(TRIM('Dev Tracker Sub'!$B$2:$B$4685&"")=TRIM($C46&"")), --(LEN(TRIM('Dev Tracker Sub'!$L$2:$L$4685&""))=0) )>0, "⚠ Missing Effort", SUMIFS( 'Dev Tracker Sub'!$L$2:$L$4685, 'Dev Tracker Sub'!$A$2:$A$4685, TRIM($B46&""), 'Dev Tracker Sub'!$B$2:$B$4685, TRIM($C46&"") ) ) ) -> 4 | L46: =IF( COUNTIFS('Dev Tracker Sub'!$A$2:$A$4683, TRIM($B46&""), 'Dev Tracker Sub'!$B$2:$B$4683, TRIM($C46&""))=0, "No Subtasks", IF( SUMPRODUCT( --(TRIM('Dev Tracker Sub'!$A$2:$A$4683&"")=TRIM($B46&"")), --(TRIM('Dev Tracker Sub'!$B$2:$B$4683&"")=TRIM($C46&"")), --(LEN(TRIM('Dev Tracker Sub'!$M$2:$M$4683&""))=0) )>0, "⚠ Missing Effort", SUMIFS( 'Dev Tracker Sub'!$M$2:$M$4683, 'Dev Tracker Sub'!$A$2:$A$4683, TRIM($B46&""), 'Dev Tracker Sub'!$B$2:$B$4683, TRIM($C46&"") ) ) ) -> 0 | N46: Alwosta team has reviewd the document and updated wherever details can be added. AW claification on few sections, ETA - 9/3 The document was shared by Basmah for review, we have shared our feedback with them. No further action required. We will close it from our end. | R46: Project Update: Cybersecurity Compliance Self-Assessment
A47: Diriyah Gate Development Authority | B47: www.dgda.gov.sa | C47: Whatsapp integration | D47: Low | I47: Closed – Not Proceeding | K47: No Subtasks | L47: No Subtasks | N47: We are identifying vendors and have calls scheduled for 9 March. Following our discussion, Regan will coordinate with the client to gather further details and Enquire with the vendor SMS API MobiShastra API.https://www.mobishastra.com/sms-api.php Blocker: Waiting for AW confirmation to proceed further (sent 9/4). *ETA post-approval. | O47: Client will find the vendor and come back to us | R47: Project Update: Whatsapp integration | U47: 19dcd4a4dcd3b025 | V47: 46140.689
A48: FIA | B48: farnboroughairshow.com | C48: SignUp Changes on FIA | E48: Abhicheke | F48: 46114 | G48: 46114 | H48: 46114 | I48: Completed | J48: Production | K48: 2.5 | L48: 2.5 | N48: Once the client's content has been updated, we will proceed with the live deployment. | R48: [NEW TASK] [FIA] SignUp Form Button Changes | U48: 19dd34b868f7cea6 | V48: 46142.476
A49: FIA | B49: farnboroughairshow.com | C49: FIA Sign-Up Form Integration with Engage | D49: Low | E49: Parthiban | F49: 46112 | G49: 46121 | I49: Under Review & Testing | J49: Production | K49: 13 | L49: 1 | N49: Asked the Key For FIA | Q49: FIA API Method Update – Revised Effort & Cost Estimation | R49: Technical Details – FIA Sign-Up Form Integration with Engage | U49: 19dcd55452c6a307 | V49: 46142.476
A50: Adfactors PR Private Limited | B50: intranet.adfactorspr.com | C50: Adfactor Post By Admin | D50: Low | F50: 46098 | H50: 46105 | I50: Completed | J50: Production | K50: 0 | L50: 0 | N50: We completed the changes and shared them with the client on March 24th for approval to go live. However, the site has been down since March 26th due to server issues. We requested the team to move staging to live on April 28th. The database has been replaced, and we are currently working on the final changes. We are also facing a permission issue, which we raised with Pushphakhant from the server team. He will get back to us today, April 30th, to set up a call so we can check it together. | R50: Project Update: Adfactor Post By Admin | U50: 19dcd2cf998e87cc | V50: 46148.442
A51: Adfactors PR Private Limited | B51: intranet.adfactorspr.com | C51: Adfactor Restore | D51: Low | F51: 46090 | I51: In Progress | J51: Production | K51: ⚠ Missing Effort | L51: ⚠ Missing Effort | N51: Since providing the latest database and requirements on April 9th, the team has been progressing with the remaining pages. We are currently navigating some permission constraints and have coordinated with the server team to troubleshoot this during a call today (30 April). We are also tracking the issue regarding profile pictures in the live environment, which was reported via email on April 27th. | O51: Need to check Realuser profile picture in social feed we need Real User SSO Login credential for testing | R51: Project Update: Adfactor Restore | U51: 19dbe07c1c8a897c | V51: 46148.442
A52: FIA | B52: farnboroughairshow.com | C52: FIA2026: Aircraft & Agenda Pages | E52: Abhicheke | F52: 46113 | G52: 46121 | I52: Completed | J52: Production | K52: 6.5 | L52: 5 | O52: Need to move the code after enage api fix | Q52: FIA2026: Aircraft & Agenda Pages | R52: Project Update: FIA2026: Aircraft & Agenda Pages | U52: 19dbe2264c925c20 | W52: 46148.451
A53: FIA | B53: farnboroughairshow.com | C53: Exhibitor Listing | D53: Low | F53: 46073 | G53: 46078 | I53: Completed | J53: Production | K53: No Subtasks | L53: No Subtasks | O53: Need to move the code after enage api fix | R53: Project Update: Exhibitor Listing | W53: 46148.451
A54: FIA | B54: farnboroughairshow.com | C54: FIA Maintenance April 2026 | D54: Low | F54: 46120 | G54: 46120 | H54: 46120 | I54: Completed | J54: Production | K54: 15.5 | L54: 13 | R54: Project Update: FIA Maintenance April 2026 | U54: 19dbe28bbe45b817 | W54: 46148.451
A55: FIA | B55: farnborough.com | C55: Venue Maintenance April 2026 | D55: Low | F55: 46120 | G55: 46121 | I55: Waiting for Client Input | J55: Production | K55: 16.5 | L55: 15.5 | N55: Version Update has by abhi and Parthiban. Cross test done the entier website by them everything work as expeted | R55: Project Update: Venue Maintenance April 2026 | U55: 19dbdeb6c1b09ce7 | W55: 46148.451
A56: Vajra Global | B56: vajraglobal.com | C56: Adobe Experence Manger and workflow | D56: Low | E56: Rackesh Kumaran | F56: 46147 | G56: 46148 | I56: Completed | W56: 46149.592
A57: Adfactors PR Private Limited | B57: intranet.adfactorspr.com | C57: Core Value Page | D57: Low | E57: Abhicheke | F57: 46146 | I57: Completed | J57: Production | K57: 0.5 | L57: 0.5 | R57: [Dev Tracker] TASK UPDATE: Core Value Page | U57: 19dfbc3f12c44744 | V57: 46162.424
A58: Vajra Global | B58: vajraglobal.com | C58: Adobe Experience Manager and WorkFront | D58: Low | E58: Rackesh Kumaran | F58: 46147 | G58: 46148 | I58: Completed | J58: Local | K58: 17 | L58: 15 | N58: G Mentioned He will speak to deep try to get the access for backoffice from deep we will review the backend | R58: [Dev Tracker] TASK UPDATE: Adobe Experience Manager and WorkFront | U58: 19e348a16c2c39e7 | V58: 46175.369
A59: Adfactors PR Private Limited | B59: intranet.adfactorspr.com | C59: Content Update May | D59: Low | F59: 46143 | I59: Completed | J59: Production | K59: 22.15 | L59: 20.3 | N59: Remove the campaign Link in awards sheet and upload in Awards page Update the sheet and uplod content in AE, AM, Team Decathlon, Updated content in Live Update content in Awards page for 2022 2023,2024 staging Update content in Awards page for 2022 2023,2024 in Live Align the gold silver bronze in 2022 2023 2024 in award page in live | R59: [Dev Tracker] TASK UPDATE: Content Update May | U59: 19e8805287b6cb49 | V59: 46176.725
A60: Adfactors PR Private Limited | B60: intranet.adfactorspr.com | C60: Adfactor Restore May | D60: Low | F60: 46143 | I60: Completed | J60: Production | K60: 69.5 | L60: 66.15 | O60: Few Profile Pic is missing on the Server Database That Need to fix from their end | R60: [Dev Tracker] TASK UPDATE: Adfactor Restore May | U60: 19eac110abd6a112 | V60: 46184.401
A61: Adfactors PR Private Limited | B61: intranet.adfactorspr.com | C61: Image and Video Edit On Post | D61: Low | E61: Parthiban | F61: 46157 | G61: 46162 | I61: Completed | J61: Production | K61: 11 | L61: 9.5 | R61: [Dev Tracker] TASK UPDATE: Image and Video Edit On Post | S61: Users should be able to edit existing posts. Users should be able to: Add new images/videos Replace existing images/videos Remove existing media attachments The updated media should be saved successfully along with the post changes. The system should validate supported file formats and file size limits. Existing permissions and security validations should remain applicable during media updates. | U61: 19eb0c94eff21d41 | V61: 46184.405
A62: FIA | B62: farnboroughairshow.com | C62: FIA Maintenance May 2026 | D62: Low | F62: 46143 | I62: Completed | J62: Production | K62: 30.5 | L62: 27.5 | R62: [Dev Tracker] TASK UPDATE: FIA Maintenance May 2026 | U62: 19eadc814e627d62 | V62: 46184.508
A63: Adfactors PR Private Limited | B63: intranet.adfactorspr.com | C63: Home Page Changes May 2026 | D63: Medium | I63: Completed | J63: Production | K63: 5.5 | L63: 6 | R63: TASK UPDATE: Home Page Changes May 2026 | U63: 19eae0083be71160 | V63: 46185.439
A64: Adfactors PR Private Limited | B64: intranet.adfactorspr.com | C64: Brand Kit Page May 2026 | D64: Medium | I64: Completed | J64: Production | K64: 5 | L64: 4.5 | O64: Arrow design/reference for Brand Kit and site-wide updates. Icon for logo section for each items | Q64: Intranet Icons | R64: TASK UPDATE: Brand Kit Page May 2026 | U64: 19eac11e075ef2ab | V64: 46185.439
A65: Diriyah Gate Development Authority | B65: www.dgda.gov.sa | C65: DGDA Maintenance May 2026 | D65: Low | F65: 46143 | I65: Completed | J65: Production | K65: 9 | L65: 8 | R65: [Dev Tracker] TASK UPDATE: DGDA Maintenance May 2026 | U65: 19ebccfb12ea8eb7 | V65: 46186.262
A66: Diriyah Gate Development Authority | B66: www.dgda.gov.sa | C66: Open data form Phase - 2 | D66: Urgent | F66: 46155 | G66: 46160 | H66: 46160 | I66: Completed | J66: Production | K66: 28 | L66: 23.5 | P66: https://release-dgda.d1pchk3m069rke.amplifyapp.com/en/open-data | Q66: Open Data Form - DGDA | R66: TASK UPDATE: Open data form Phase - 2 | U66: 19eca52291fae749 | V66: UmNUMDNDTUQyaklRa3A5Zg | W66: 46190.546

Sheet Dev Tracker Sub
A1: Project Name | B1: Main Task Name | C1: Ticket Id | D1: Task | E1: Priority | F1: S Date | G1: E Date | H1: Assigned to | I1: Status | J1: Env | K1: As Per WO | L1: Efforts | M1: Actual Efforts | N1: Informed | O1: Support Needed / Blocker | P1: Dependency Detail | Q1: Page Url | R1: Mail Subject | S1: Internal Mail Subject | U1: Gmail Thread ID | V1: Google Subtask ID | W1: Main Google Task ID | X1: Google Nest Status
A2: farnboroughairshow.com | B2: Brand GuidLine Change | D2: Usage of the wireframes is fully set out in main brand guidelines | E2: Low | F2: 45986 | G2: 46041 | H2: Abhicheke | I2: Completed | J2: Production | K2: 45989 | L2: 0 | M2: 0
A3: farnboroughairshow.com | B3: Brand GuidLine Change | D3: Where recommended, these should be used across backgrounds and headers | E3: Low | F3: 45986 | G3: 46041 | H3: Abhicheke | I3: Completed | J3: Production | K3: 45989 | L3: 0 | M3: 0
A4: farnboroughairshow.com | B4: Brand GuidLine Change | D4: Brown Bold to be used for other headlines, H tags etc. | E4: Low | F4: 45986 | G4: 46041 | H4: Abhicheke | I4: Completed | J4: Production | K4: 45989 | L4: 0 | M4: 0
A5: farnboroughairshow.com | B5: Brand GuidLine Change | D5: Headers – add in a colour picker for banner descriptions, the same as with titles | E5: Low | F5: 45986 | G5: 46041 | I5: Completed | J5: Production | K5: 45989 | L5: 0 | M5: 0
A6: farnboroughairshow.com | B6: Brand GuidLine Change | D6: Ensure consistent line spacing between title and description. | E6: Low | F6: 45986 | G6: 46041 | H6: Abhicheke | I6: Completed | J6: Production | K6: 45989 | L6: 0 | M6: 0
A7: farnboroughairshow.com | B7: Brand GuidLine Change | D7: Footer – change section headers (Quick Links, Our Brands, Contact Us) to Brown Bold and white | E7: Low | F7: 45986 | G7: 46041 | H7: Abhicheke | I7: Completed | J7: Production | K7: 45989 | L7: 0 | M7: 0
A8: farnboroughairshow.com | B8: Brand GuidLine Change | D8: Add title to stats section | E8: Low | F8: 45986 | G8: 46041 | H8: Abhicheke | I8: Completed | J8: Production | K8: 45989 | L8: 0 | M8: 0
A9: farnboroughairshow.com | B9: Brand GuidLine Change | D9: Hide side by side section (video and 2024 report), will need it again post-airshow | E9: Low | F9: 45986 | G9: 46041 | H9: Abhicheke | I9: Completed | J9: Production | K9: 45989 | L9: 0 | M9: 0
A10: farnboroughairshow.com | B10: Brand GuidLine Change | D10: Add sixth theme onto the same line, currently displaying below the others (on staging site) | E10: Low | F10: 45986 | G10: 46041 | H10: Abhicheke | I10: Completed | J10: Production | K10: 45989 | L10: 0 | M10: 0
A11: farnboroughairshow.com | B11: Brand GuidLine Change | D11: Remove the share this page actions on detail pages: | E11: Low | F11: 45986 | G11: 46041 | H11: Abhicheke | I11: Completed | J11: Production | K11: 45989 | L11: 0 | M11: 0
A12: farnboroughairshow.com | B12: Brand GuidLine Change | D12: For example, the Sign-Up to FIA Insights bar should always be in grey if directly next to footer | E12: Low | F12: 45986 | G12: 46041 | H12: Abhicheke | I12: Completed | J12: Production | K12: 45989 | L12: 0 | M12: 0
A13: farnboroughairshow.com | B13: Brand GuidLine Change | D13: Avoid having 2 sections next to each other that use the Interstellar gradient. Sections should alternate between white background and either the gradient or grey | E13: Low | F13: 45986 | G13: 46041 | H13: Abhicheke | I13: Completed | J13: Production | K13: 45989 | L13: 0 | M13: 0
A14: farnboroughairshow.com | B14: Brand GuidLine Change | D14: Only to be used for Page Titles and some other headlines where specified (for example, the section headlines on the homepage) | E14: Low | F14: 45986 | G14: 46041 | H14: Abhicheke | I14: Completed | J14: Production | K14: 45989 | L14: 0 | M14: 0
A15: farnboroughairshow.com | B15: Brand GuidLine Change | D15: 3.Don't use ethnocentric for category headings or company names (use Brown) | E15: Low | F15: 45986 | G15: 46041 | H15: Abhicheke | I15: Completed | J15: Production | K15: 45989 | L15: 0 | M15: 0
A16: farnboroughairshow.com | B16: Brand GuidLine Change | D16: 4.Review category layout as there is quite a lot to display, on mobile especially you have to scroll a long way. Could this be changed to a simple drop-down filter? | E16: Low | F16: 45986 | G16: 46041 | H16: Abhicheke | I16: Completed | J16: Production | K16: 45989 | L16: 0 | M16: 0
A17: farnboroughairshow.com | B17: Brand GuidLine Change | D17: Replace carousel hero banner with video, centralise text and allow 2 button option. | E17: Low | F17: 45986 | G17: 46041 | H17: Abhicheke | I17: Completed | J17: Production | K17: 45989 | L17: 0 | M17: 0
... A26: farnboroughairshow.com | B26: Brand GuidLine Change | D26: Second Phase (January-March 2026) Redesign of pages (Exhibitor listing, What’s On/Agenda, Aircraft Listing) Further Pioneers pages (to be decided) Further design tweaks | E26: Low | F26: 45994 | G26: 46041 | H26: Abhicheke | I26: Completed | J26: Production | K26: 46002 | L26: 0 | M26: 0
A27: www.dgs.sa | B27: Missing Content on DGS Page | D27: Agenda - Waiting for PDF | E27: Medium | F27: 46001 | G27: 46001 | H27: Abhicheke | I27: Completed | J27: Production | K27: 46001 | L27: 0 | M27: 0 | O27: Received the PDF Today Updated On The DGS
A28: www.dgs.sa | B28: Missing Content on DGS Page | D28: Production Stream - Waiting for actual image, Content and video link | E28: Medium | I28: Completed | J28: Production | L28: 0 | M28: 0 | O28: AW contents from DGS follow up sent on 01-12-2025
A29: www.dgs.sa | B29: Missing Content on DGS Page | D29: Register Form - Need to Map by CRM Team | E29: Medium | I29: Completed | J29: Production | L29: 0 | M29: 0 | O29: AW contents from DGS follow up sent on 01-12-2025 | S29: We are working on this with C4C team and Update the Mapping and Fix the changes The team need to get back to Us(30-11-2025 to 01-12-2025)
A30: www.dgs.sa | B30: DGS Registration form | D30: FirstName And LastName Only allow 40 character | E30: Urgent | H30: Regan | I30: Completed | J30: Production | L30: 0 | M30: 0 | O30: We sent a follow-up yesterday (December 1, 2025), 2nd follow-up sent on December 8, 2025. Awaiting client response
A31: www.dgs.sa | B31: DGS Registration form | D31: Recaptcha Configuration and Update | E31: Medium | F31: 45992 | G31: 45995 | H31: Moswin | I31: Completed | J31: Production | L31: 0 | M31: 0 | S31: Immediate Assistance Needed – reCAPTCHA v3 Key Update for DGS
A32: intranet.adfactorspr.com | B32: Holiday List Page | D32: We need to identify the default location, filter the data accordingly, and display the result. | E32: Low | F32: 45995 | G32: 46003 | H32: Parthiban | I32: Completed | J32: Production | L32: 5 | M32: 0
A33: intranet.adfactorspr.com | B33: Adfactor Home Page feature | D33: The system needs to allow post creation and updating to be handled entirely within the popup, instead of within a separate section. | E33: Low | F33: 45995 | G33: 46003 | H33: Parthiban | I33: Completed | J33: Production | L33: 0 | M33: 0
A34: www.dgs.sa | B34: Missing Content on DGS Page | D34: Speaker - Waiting for actual image and content | E34: Medium | I34: Closed – Not Proceeding | J34: Production | L34: 0 | M34: 0 | O34: AW contents from DGS follow up sent on 01-12-2025
A35: www.dgs.sa | B35: Missing Content on DGS Page | D35: Accompanying Exhibition - Waiting for actual image and content | E35: Medium | I35: Closed – Not Proceeding | J35: Production | L35: 0 | M35: 0 | O35: AW contents from DGS follow up sent on 01-12-2025
A36: intranet.adfactorspr.com | B36: Holiday List Page | D36: The Calendar also needs to be updated based on the holiday list and the applied filters. | E36: Low | F36: 45995 | G36: 46003 | H36: Parthiban | I36: Completed | J36: Production | L36: 5 | M36: 0
A37: www.dgda.gov.sa | B37: DGDA Version Update | D37: Version update from 14.2.25 to 15.5.9 | E37: Low | F37: 46006 | G37: 46008 | H37: Abhicheke | I37: Completed | J37: Production | L37: 0 | M37: 0
A38: www.dgda.gov.sa | B38: DGDA Version Update | D38: Apply prefech and pre connect for the speed increase | E38: Low | F38: 46006 | G38: 46008 | H38: Abhicheke | I38: Completed | J38: Production | L38: 0 | M38: 0 | O38: desktop 40 -80 Mobile 32 - 50
A39: www.dgda.gov.sa | B39: DGDA Version Update | D39: DGDA Improvment | E39: Low | F39: 46008 | G39: 46008 | H39: Parthiban | I39: Completed | J39: Production | L39: 0 | M39: 0
A40: farnborough.com | B40: Farnborough Canceled Event | D40: Farnborough Canceled Event | E40: Low | F40: 46013 | G40: 46038 | H40: Parthiban | I40: Completed | J40: Production | L40: 0 | M40: 0
A41: www.dgda.gov.sa | B41: DGDA Version Update | D41: Actions to address CVE-2025-55182 and CVE-2025-66478 (Next.js/React Vulnerabilities) | E41: Low | F41: 46012 | G41: 46012 | H41: Abhicheke | I41: Completed | J41: Production | L41: 0 | M41: 0
A42: intranet.adfactorspr.com | B42: Holiday List Page | D42: Users must be allowed to download and add all holidays to their personal calendar via an .ics file. | E42: Low | F42: 45995 | G42: 46003 | H42: Parthiban | I42: Completed | J42: Production | L42: 25 | M42: 0
A43: intranet.adfactorspr.com | B43: Adfactor Home Page feature | D43: Fall Back Need to Get from Member | E43: Low | F43: 45995 | G43: 46003 | H43: Parthiban | I43: Completed | J43: Production | L43: 0 | M43: 0
A44: intranet.adfactorspr.com | B44: Adfactor Home Page feature | D44: Notification 30 sec refresh with Cache | E44: Low | F44: 45992 | G44: 45994 | H44: Parthiban | I44: Completed | J44: Production | L44: 0 | M44: 0
A45: farnborough.com | B45: Update the form date format | D45: Update the form date format | E45: Low | F45: 46002 | G45: 46002 | H45: Abhicheke | I45: Completed | J45: Production | L45: 0 | M45: 0
A46: www.dgs.sa | B46: SEO Assets for DGS Site | D46: SEO Assets for DGS Site - English | E46: Medium | F46: 45980 | H46: Regan | I46: Completed | J46: Local | L46: 0 | M46: 0 | O46: We have shared the document with the client on December 1, 2025 and are now awaiting their reply and approval. Once they approve the changes and provide the Arabic content, we will update the DGS live environment. 2nd follow-up sent on December 8, 2025. Awaiting client response | S46: SEO Assets for DGS Site (Discussed 11-11-2025)
A47: www.dgs.sa | B47: SEO Assets for DGS Site | D47: SEO Assets for DGS Site - Arabic | E47: Medium | F47: 45980 | H47: Regan | I47: Completed | J47: Local | L47: 0 | M47: 0 | O47: We have shared the document with the client on December 1, 2025 and are now awaiting their reply and approval. Once they approve the changes and provide the Arabic content, we will update the DGS live environment. 2nd follow-up sent on December 8, 2025. Awaiting client response | S47: SEO Assets for DGS Site (Discussed 11-11-2025)
A48: www.dgda.gov.sa | B48: XMCC Migration | D48: Conduct CH1 → XMCC Migration Impact Analysis. Document open questions, scope clarifications, and decisions. | E48: Critical / Blocker | H48: Regan | I48: Closed – Not Proceeding | L48: 0 | M48: 0 | O48: 1) Share the question with the client. 2) They need to decide whether to perform the migration this month or in April. 3) The DGDA team needs to give the Sitecore team GitHub access.
A49: www.dgda.gov.sa | B49: XMCC Migration | D49: Sandbox access approved + answers received so development and testing can proceed without risk. | E49: Critical / Blocker | H49: Regan | I49: Closed – Not Proceeding | L49: 0 | M49: 0 | O49: 1) Share the question with the client. 2) They need to decide whether to perform the migration this month or in April. 3) The DGDA team needs to give the Sitecore team GitHub access.
A50: www.dgda.gov.sa | B50: 360 Degree Image new website | D50: 360 Degree Image new website | E50: Low | H50: Regan | I50: Closed / Cancelled | L50: 0 | M50: 0
A51: www.dgda.gov.sa | B51: Form Tracking GA | D51: The Dev Team needs to review the form tracking and coordinate with Ranjith for validation. | E51: Low | F51: 45975 | G51: 45978 | H51: Ranjith | I51: Completed | J51: Production | L51: 0 | M51: 0
A52: intranet.adfactorspr.com | B52: Holiday List Page | D52: Holiday Content | E52: Low | H52: Sowndar | I52: Completed | J52: Production | L52: 0 | M52: 0 | O52: Need to check with Vishal
A53: farnboroughairshow.com | B53: FIA Changes on Show Theme | D53: The Show Pages Cards Change and color updates and fetch the pillars from the pillars folder | E53: Low | F53: 46028 | G53: 46041 | H53: Abhicheke | I53: Completed | J53: Production | L53: 0 | M53: 0
A54: www.dgda.gov.sa | B54: Summer Program Page | D54: Summer Program Page | E54: Low | F54: 45993 | G54: 46002 | H54: Abhicheke | I54: Completed | J54: Staging | L54: 0 | M54: 0 | O54: Presently on Staging Alwosta team completed the program activity and integration with CRM is completed on 23/12; Program postponed to November 2026 as advised by Dayel.
A55: www.dgda.gov.sa | B55: Summer Program Page | D55: Summer Program Page form | E55: Low | F55: 45993 | G55: 46002 | H55: Abhicheke | I55: Completed | J55: Staging | L55: 0 | M55: 0 | O55: Presently on Staging Alwosta team completed the program activity and integration with CRM is completed on 23/12; Program postponed to November 2026 as advised by Dayel. | Q55: https://preview-preprod.dgda.gov.sa/en/contact-us/diriyah-horizons
A56: www.dgda.gov.sa | B56: Uma Form | C56: 24-DEC-2025-1 | D56: UMA Content - Close-Out Report (New form) - Phase 1 | E56: Low | F56: 46015 | H56: Abhicheke | I56: Closed – Not Proceeding | J56: Staging | L56: 0 | M56: 0 | O56: C4C Intergraion Progress
A57: www.dgda.gov.sa | B57: Uma Form | C57: 24-DEC-2025-2 | D57: UMA Content - General Inquiry (Minor Change) - Phase 1 | E57: Low | F57: 46015 | I57: Closed – Not Proceeding | J57: Staging | L57: 0 | M57: 0 | O57: C4C Intergraion Progress ,Current Cateogry is differnt what they have shared on the doucment we need to check with cline and continueq
A58: www.dgda.gov.sa | B58: Uma Form | C58: 24-DEC-2025-3 | D58: UMA Content - Complaints (Minor Change) - Phase 1 | E58: Low | F58: 46015 | I58: Closed – Not Proceeding | J58: Staging | L58: 0 | M58: 0 | O58: C4C Intergraion Progress Current Cateogry is differnt what they have shared on the doucment we need to check with cline and continueq
A59: www.dgda.gov.sa | B59: Uma Form | C59: 24-DEC-2025-4 | D59: UMA Content - Service Request (New form) - Phase 1 | E59: Low | F59: 46015 | H59: Parthiban | I59: Closed – Not Proceeding | J59: Staging | L59: 0 | M59: 0 | O59: C4C Intergraion Progress English has compeleted arabic will start today
A60: www.dgda.gov.sa | B60: Uma Form | C60: 24-DEC-2025-5 | D60: UMA Content - Book a Meeting (New form) - Phase 1 | E60: Low | F60: 46015 | I60: Closed – Not Proceeding | J60: Staging | L60: 0 | M60: 0 | O60: C4C Intergraion Progress
A61: www.dgda.gov.sa | B61: Uma Form | C61: 24-DEC-2025-6 | D61: UMA Content - Staging Report (New form) - Phase 1 | E61: Low | F61: 46015 | H61: Parthiban | I61: Closed – Not Proceeding | J61: Staging | L61: 0 | M61: 0 | O61: C4C Intergraion Progress completed in local hoverever this form on phase 2 so we will share with clinet once done the above forms
A62: www.dgda.gov.sa | B62: Uma Form | C62: 24-DEC-2025-7 | D62: OTP Intergration on the Website | E62: Low | F62: 46015 | I62: Closed – Not Proceeding | L62: 0 | M62: 0
A63: www.dgda.gov.sa | B63: Uma Form | C63: 24-DEC-2025-8 | D63: Violation_DGDA Website_Integration API_V1.1 testing in local | E63: Low | F63: 46020 | H63: Abhicheke | I63: Closed – Not Proceeding | J63: Local | L63: 0 | M63: 0 | O63: 503 Application Shutting Down Error need to check with client
A64: www.dgs.sa | B64: DGS Home | C64: 31-DEC-2025-1 | D64: DGS Video Page(Coming Soon) Instead of the home page, create a new page and update the video on that page. | E64: Low | F64: 46022 | I64: Completed | J64: Production | L64: 0 | M64: 0 | O64: Once got the approval from client need to publish on Production
A65: www.dgs.sa | B65: DGS Home | C65: 31-DEC-2025-2 | D65: DGS pages unpublished and add redirection | E65: Low | F65: 46022 | I65: Completed | J65: Production | L65: 0 | M65: 0
A66: farnborough.com | D66: Venue Site Form Data Weekly Export and send to Client | E66: Low | F66: 46024 | H66: Abhicheke | I66: Completed | J66: Production | L66: 0 | M66: 0
A67: farnborough.com | B67: Venue Version Update | D67: Updated the Umbraco version 13.10.0 to 13.13.0 in Farnborough Vennue | E67: Low | F67: 46027 | G67: 46038 | H67: Abhicheke | I67: Completed | J67: Production | L67: 0 | M67: 0
A68: www.dgs.sa | B68: DGS Home | C68: 5-Jan-2026-1 | D68: Set up redirects for DGS to the home page since the seminar is over. | E68: Low | F68: 46027 | I68: Completed | J68: Production | L68: 0 | M68: 0 | O68: /en/agenda /en/speakers /en/past-seminars/dgs-2023 /en/past-seminars/dgs-2024 /en/accompanying-exhibition /en/salwa-stage-live-stream /en/alawja-stage-live-stream /en/dgs-registration-closed /en/privacy-policy en/terms-and-conditions /en/cookie-policy /ar/agenda /ar/speakers /ar/past-seminars/dgs-2023 /ar/past-seminars/dgs-2024 /ar/accompanying-exhibition /ar/salwa-stage-live-stream /ar/alawja-stage-live-stream /ar/dgs-registration-closed /ar/privacy-policy /ar/terms-and-conditions /ar/cookie-policy arabic pages to arabic home page is pending.
A69: farnboroughairshow.com | B69: FIA Version Update | D69: Version Update 13.9.1 to 13.13.0 in FarnboroughAirshow | E69: Low | F69: 46027 | H69: Abhicheke | I69: Completed | J69: Production | L69: 0 | M69: 0
A70: vajraglobal.com | B70: Internal Task | D70: Research on self hosted runners and their cost per usage for private and public repos in github | E70: Low | F70: 46027 | I70: Completed | J70: Production | L70: 0 | M70: 0 | O70: GitHub Actions Billing – Runner Cost Overview document done, need to check with Sowndar if he has something else that needs to cover and close this
A71: vajraglobal.com | B71: Internal Task | D71: Define industry-standard DevOps-as-a-Service offerings, competitive benchmarking, internal capability mapping, pricing structure, and operational readiness including AWS service scope and scaling considerations. | E71: Low | F71: 46027 | I71: Completed | J71: Production | L71: 0 | M71: 0 | O71: DevOps as a Service Need to get verification from Sowndar before taking it up with Sriram Sir
A72: www.dgda.gov.sa | B72: Uma Form | C72: 06-JAN-2025-1 | D72: Complaints Form Concerned Area remove and change the category and sub-category position | E72: Low | F72: 46028 | H72: Abhicheke | I72: Completed | J72: Staging | L72: 0 | M72: 0
A73: www.dgda.gov.sa | B73: Uma Form | C73: 06-JAN-2025-2 | D73: Staging Report,Book a Meeting content change | E73: Low | F73: 46028 | H73: Abhicheke | I73: Completed | J73: Staging | L73: 0 | M73: 0
A74: vajraglobal.com | B74: Internal Task | D74: Exhibitor Portal Plan | E74: Low | F74: 46028 | H74: Parthiban | I74: Completed | J74: Production | L74: 0 | M74: 0 | O74: The Process Has happen long before we will restart it later so we close it for now
A75: vajraglobal.com | B75: Internal Task | D75: Umbraco Log Check and send auto notification via email | E75: Low | F75: 46028 | H75: Abhicheke | I75: Completed | J75: Production | L75: 0 | M75: 0
A76: www.dgs.sa | B76: DGS Home | C76: 5-Jan-2026-2 | D76: Set up redirects for DGS to the home page in a way that all english pages go to english home page , and all arabic home pages go to arabic home pages since the seminar is over. | E76: Low | F76: 46028 | G76: 46028 | H76: Moswin | I76: Completed | J76: Production | L76: 0 | M76: 0
A77: www.astonbrooke.co.uk/ | B77: AB project CICD failing | D77: Aston Brooke CICD is failing because of No space is left because of too many artifacts, need to solve it and provide permanent solution for future proofing. | E77: High | F77: 46029 | G77: 46029 | H77: Moswin | I77: Completed | J77: Production | L77: 0 | M77: 0 | O77: Issue has been resolved. Issue: too many build has been happening in past few days so artifact storage has filled up. Immediate solution: Deleted older artifacts and freed up space , now working fine. Permanent solution: For build artifacts now have kept an expiry of 7 days, now the clean up activity of artifacts will happen by itself regularly.
A78: www.dgda.gov.sa | B78: Uma Form | C78: 07-JAN-2025-1 | D78: Service Request Form - This section will appear if category = Design Compliance and add new 4 fields | E78: Low | F78: 46029 | G78: 46029 | H78: Abhicheke | I78: Completed | J78: Staging | L78: 0 | M78: 0 | O78: 1. Missing fields How do you describe yourself and area ? need to check if we need to include If the user slects Design compliance in Category we will introduce the new section Do we need to place it as first and last name in Owner information or as Owner Name
A79: www.dgda.gov.sa | B79: DGDA DevSecOps pipelines set up | C79: 08-JAN-2025-1 | D79: Meeting to Work along with Saheel and set up Security pipelines in DGDA and generate reports | E79: Low | F79: 46030 | G79: 46030 | H79: Moswin | I79: Completed | J79: Local | L79: 0 | M79: 0 | O79: Discussed and provided details for the DGDA to proceed further with their set up for scnaning.
A80: www.dgda.gov.sa | B80: DGDA DevSecOps pipelines set up | C80: 08-JAN-2025-2 | D80: Document preparation with all the details required from the infra team from DGDA | E80: Low | F80: 46030 | G80: 46030 | H80: Moswin | I80: Completed | J80: Local | L80: 0 | M80: 0 | O80: DGDA_DGS DevSecOps implementation .docx
A81: www.dgda.gov.sa | B81: DGDA monitoring sheet update | D81: DGDA monitoring sheet updated for the last 5 days. | E81: Low | F81: 46030 | G81: 46030 | H81: Moswin | I81: Completed | J81: Production | L81: 0 | M81: 0 | O81: DGDA Monitoring Activities
A82: farnboroughairshow.com | B82: POT Feed Back Changes | C82: 09-JAN-2025-1 | D82: Homepage 'Welcome to Pioneers of Tomorrow' font needs to be bolder, use Lexend Black for main page titles Sub-headings, e.g. What's On, Ticket Types & Get Involved should also be Lexend Black You can check how the font weighting should display here: https://fonts.google.com/specimen/Lexend | E82: Low | F82: 46031 | G82: 46041 | H82: Abhicheke | I82: Completed | J82: Production | L82: 0 | M82: 0 | R82: FIA2026 Website Updates
A83: farnboroughairshow.com | B83: POT Feed Back Changes | C83: 09-JAN-2025-2 | D83: Menu Could you change the PoT section in the mega menu to the light blue, but keep the drop down as purple once hovered over? The purple blends in too much to the teal colour at the moment | E83: Low | F83: 46031 | G83: 46041 | H83: Abhicheke | I83: Completed | J83: Production | L83: 0 | M83: 0 | R83: FIA2026 Website Updates
A84: farnboroughairshow.com | B84: POT Feed Back Changes | C84: 09-JAN-2025-3 | D84: Key Features (summary) Title needs to be bolder (Lexend black) Sub-heading font is fine | E84: Low | F84: 46031 | G84: 46041 | H84: Abhicheke | I84: Completed | J84: Production | L84: 0 | M84: 0 | R84: FIA2026 Website Updates
A85: farnboroughairshow.com | B85: POT Feed Back Changes | C85: 09-JAN-2025-4 | D85: Key features (detail) Change useful links box to one of the lighter purple colours Title needs to be bolder (Lexend black) | E85: Low | F85: 46031 | G85: 46041 | H85: Abhicheke | I85: Completed | J85: Production | L85: 0 | M85: 0 | R85: FIA2026 Website Updates
A86: farnboroughairshow.com | B86: POT Feed Back Changes | C86: 09-JAN-2025-5 | D86: Get Involved (detail) Not publishing, but should sit under PoT section | E86: Low | F86: 46031 | G86: 46041 | H86: Abhicheke | I86: Completed | J86: Production | L86: 0 | M86: 0 | R86: FIA2026 Website Updates
A87: farnboroughairshow.com | B87: POT Feed Back Changes | C87: 09-JAN-2025-6 | D87: Tickets Reduce the size of the hero banner (same size as the trade FIA ticket page would be ideal) Titles needs to be bolder (Lexend black) When adding another ticket type the new box is FIA teal colour rather than purple | E87: Low | F87: 46031 | G87: 46041 | H87: Abhicheke | I87: Completed | J87: Production | L87: 0 | M87: 0 | R87: FIA2026 Website Updates
A88: farnboroughairshow.com | B88: POT Feed Back Changes | C88: 09-JAN-2025-7 | D88: FIA Homepage Theme Section – could the hover colour match the colour of the theme (see brand guidelines for hexcodes) | E88: Low | F88: 46031 | G88: 46041 | H88: Abhicheke | I88: Completed | J88: Production | L88: 0 | M88: 0 | R88: FIA2026 Website Updates
A89: farnborough.com | D89: Venue Site Form Data Weekly Export and send to Client | E89: Low | F89: 46031 | G89: 46031 | H89: Parthiban | I89: Completed | J89: Production | L89: 0 | M89: 0
A90: www.dgda.gov.sa | D90: Remove the Land Management Services From e-service | E90: Low | F90: 46034 | G90: 46034 | H90: Abhicheke | I90: Completed | J90: Production | L90: 0 | M90: 0
A91: farnboroughinternationalstudios.com | B91: Studio Site Version Update | D91: Version Update 13.9.1 to 13.13.0 in FarnboroughAirshow | E91: Low | F91: 46041 | G91: 46043 | H91: Abhicheke | I91: Completed | J91: Production | L91: 0 | M91: 0
A92: farnboroughairshow.com | D92: FIA Website Final Changes | E92: Low | F92: 46038 | G92: 46038 | H92: Abhicheke | I92: Completed | J92: Production | L92: 0 | M92: 0
A93: farnboroughairshow.com | D93: FIA 2026 and POT 2026 Changes moved to live and version update move to live | E93: Low | F93: 46041 | G93: 46041 | H93: Abhicheke | I93: Completed | J93: Production | L93: 0 | M93: 0 | R93: FIA2026 Website Updates
A94: intranet.adfactorspr.com | D94: Adfactors sso login issue fix and move the changes to staging and live and test the site | E94: High | F94: 46041 | G94: 46041 | H94: Abhicheke | I94: Completed | J94: Production | L94: 0 | M94: 0
A95: www.dgda.gov.sa | D95: DGDA Monitoring sheet update for the last 4 days | E95: Low | F95: 46035 | G95: 46035 | I95: Completed | J95: Production | L95: 2 | M95: 0
A96: www.dgda.gov.sa | D96: Cloudflare resolver issue analysis with the 1.1.1.1 IP. Have identified nothing to worry about in our particular case. | E96: Low | F96: 46043 | G96: 46043 | I96: Completed | J96: Production | L96: 3.5 | M96: 0
A97: www.dgda.gov.sa | D97: DGDA Diagram work for documentation | E97: Low | F97: 46049 | G97: 46049 | I97: Completed | J97: Production | L97: 3 | M97: 2
A98: www.dgda.gov.sa | B98: National Design System (DGA) | C98: 22-JAN-2026-1 | D98: National Design System design apply for home page and header and footer | E98: Low | F98: 46044 | G98: 46048 | H98: Abhicheke | I98: Completed | J98: Production | L98: 15 | M98: 10
A99: farnboroughinternationalstudios.com | B99: New Testimonial Page | D99: Develope Testimonials Page | E99: Medium | F99: 46051 | G99: 46055 | H99: Abhicheke | I99: Completed | J99: Production | L99: 0 | M99: 0 | O99: Design Link https://www.figma.com/design/rFsGHt32JQmdSu5yTx6Ni3/Farnborough-studios?node-id=128-2&t=b4BY2SVqY9tQB9mE-0 | R99: Studios website - testimonials
D100: Daily Monitoring and Update in sheet for all Websites | E100: Medium | F100: 46023 | G100: 46052 | H100: Parthiban | I100: Completed | J100: Production | L100: 0 | M100: 0 | O100: Daily mornitoring the websites (working status,log error,page speed)
A101: farnborough.com | D101: Venue Site Form Data Weekly Export and send to Client | E101: Medium | F101: 46052 | G101: 46052 | H101: Parthiban | I101: Completed | J101: Production | L101: 0 | M101: 0
A102: www.dgda.gov.sa | B102: Form Failed Feb-2026 | D102: Forms payload duplicate fix - Golf Club Hiring Opportunity form | E102: High | F102: 46056 | H102: Abhicheke | I102: Completed | J102: Production | L102: 0 | M102: 0
A103: www.dgda.gov.sa | B103: Content Update – Feb 2026 | D103: DGDA Content Update Menu 1.Diriyah Community changed to Life in Diriyah 2.url Changed from https://preview-preprod.dgda.gov.sa/en/diriyah-community to https://preview-preprod.dgda.gov.sa/en/life-in-diriyah 3.Update the page banner text from Diriyah Community changed to Life in Diriyah Learn at Diriyah https://preview-preprod.dgda.gov.sa/en/program/dal 1.Title Updated 2.Content Updated 3.Program Card Image Updated https://preview-preprod.dgda.gov.sa/en/program/dgs-students-poster-showcase 1.New Program Page Created 2.Title Updated 3.Content Updated 4.Banner Image Updated 5.Program Card Image Updated https://preview-preprod.dgda.gov.sa/en/program/diriyah-horizons 1.Title Updated 2.Content Updated 3.Banner Image Updated 4.Program Card Image Updated Heritage and Culture https://preview-preprod.dgda.gov.sa/en/place/at-turaif 1.Content Updated | E103: Medium | F103: 46058 | G103: 46058 | H103: Abhicheke | I103: Completed | J103: Production | L103: 0 | M103: 0 | O103: After got approval need to publish the page on live
A104: farnboroughinternationalstudios.com | D104: Film at Farnborough FAM Trip form fix | E104: Medium | F104: 46062 | G104: 46062 | I104: Completed | J104: Production | L104: 0 | M104: 0 | Q104: https://farnboroughinternationalstudios.com/film-at-farnborough-fam-trip/
A105: farnboroughinternationalstudios.com | D105: SEO optimization for the FIL Studios website | L105: 0 | M105: 0
A106: www.dgda.gov.sa | B106: Leadership component | D106: Leadership Component Change the Desgin for this Leadership Team and update the content and Images | E106: Medium | F106: 46062 | G106: 46062 | I106: Completed | J106: Production | L106: 0 | M106: 0 | Q106: https://preview-preprod.dgda.gov.sa/en/about/leadership
A107: intranet.adfactorspr.com | B107: Academy Page | C107: 05-FEB-2026-1 | D107: Create a Adfactors About adfactor academy,Internal Programmes,Cohort-based Programmes | E107: Medium | F107: 46058 | G107: 46059 | H107: Parthiban | I107: Completed | J107: Production | L107: 6 | M107: 0 | O107: Waiting for client approval to move live | Q107: https://intranetstaging.adfactorspr.com/knowledge-corner/adfactors-academy/
A108: intranet.adfactorspr.com | B108: Academy Page | C108: 05-FEB-2026-2 | D108: Academy Detail page | E108: Medium | F108: 46058 | G108: 46059 | H108: Parthiban | I108: Completed | J108: Production | L108: 2 | M108: 0 | O108: Waiting for client approval to move live | Q108: https://intranetstaging.adfactorspr.com/knowledge-corner/adfactors-academy/
...

Sheet Leave Tracker
A1: Employee Name | B1: Leave Type | C1: From Date | D1: To Date | E1: Actual Leave | F1: Which Actual Days | G1: Which Total Days | H1: Total Days | I1: Half Day / Full Day | J1: Status | K1: Comp Off Date | L1: Reason for Leave | M1: Any Deliver On This Week | N1: Emergency Leave | O1: Applied Date | P1: Leave Status | Q1: Approved By | R1: Approval Date | S1: Rejection Reason
A2: Moswin | B2: Casual Leave | C2: 46157 | D2: 46157 | E2: =IF(I2="First Half",0.5, IF(I2="Second Half",0.5, NETWORKDAYS(C2,D2))) -> 1 | F2: =IFERROR(__xludf.DUMMYFUNCTION("IF(I2=""First Half"", ""First Half - ""&TEXT(C2,""dddd""), IF(I2=""Second Half"", ""Second Half - ""&TEXT(C2,""dddd""), TEXTJOIN("", "",TRUE,FILTER(TEXT(SEQUENCE(D2-C2+1,1,C2),""dddd""),WEEKDAY(SEQUENCE(D2-C2+1,1,C2),2)<6))))"),"Friday") -> Friday | G2: {=IF(I2="First Half", "First Half - "&TEXT(C2,"dddd"), IF(I2="Second Half", IF(OR(WEEKDAY(C2)=2,WEEKDAY(D2)=6), "Saturday, Sunday, Second Half - "&TEXT(C2,"dddd")&", Saturday, Sunday", "Second Half - "&TEXT(C2,"dddd")), TEXTJOIN(", ",TRUE, TEXT( SEQUENCE( (D2-C2)+1+ IF(WEEKDAY(C2)=2,2,0)+ IF(WEEKDAY(D2)=6,2,0), 1, C2-IF(WEEKDAY(C2)=2,2,0) ), "dddd"))))} -> Friday, Saturday, Sunday | H2: =IF(I2="First Half", 0.5, IF(I2="Second Half", IF(OR(WEEKDAY(C2)=2,WEEKDAY(D2)=6),2.5,0.5), (D2-C2)+1+ IF(WEEKDAY(C2)=2,2,0)+ IF(WEEKDAY(D2)=6,2,0))) -> 3 | I2: Full Day | J2: =IF(Q2="Pending","Waiting Approval", IF(Q2="Rejected","Rejected", IF(Q2="Cancelled","Cancelled", IF(TODAY()<C2,"Upcoming", IF(AND(TODAY()>=C2,TODAY()<=R2),"In Progress", IF(TODAY()>R2,"Completed","")))))) -> Completed | M2: No | O2: 46149 | P2: Approved | Q2: Sunder | R2: 46149
A3: Abhicheke | B3: Casual Leave | C3: 46160 | D3: 46164 | E3: =IF(I3="First Half",0.5, IF(I3="Second Half",0.5, NETWORKDAYS(C3,D3))) -> 5 | F3: =IFERROR(__xludf.DUMMYFUNCTION("IF(I3=""First Half"", ""First Half - ""&TEXT(C3,""dddd""), IF(I3=""Second Half"", ""Second Half - ""&TEXT(C3,""dddd""), TEXTJOIN("", "",TRUE,FILTER(TEXT(SEQUENCE(D3-C3+1,1,C3),""dddd""),WEEKDAY(SEQUENCE(D3-C3+1,1,C3),2)<6))))"),"Monday, Tuesday, Wednesday, Thursday, Friday") -> Monday, Tuesday, Wednesday, Thursday, Friday | G3: {=IF(I3="First Half", "First Half - "&TEXT(C3,"dddd"), IF(I3="Second Half", IF(OR(WEEKDAY(C3)=2,WEEKDAY(D3)=6), "Saturday, Sunday, Second Half - "&TEXT(C3,"dddd")&", Saturday, Sunday", "Second Half - "&TEXT(C3,"dddd")), TEXTJOIN(", ",TRUE, TEXT( SEQUENCE( (D3-C3)+1+ IF(WEEKDAY(C3)=2,2,0)+ IF(WEEKDAY(D3)=6,2,0), 1, C3-IF(WEEKDAY(C3)=2,2,0) ), "dddd"))))} -> Saturday, Sunday, Monday, Tuesday, Wednesday, Thursday, Friday, Saturday, Sunday | H3: =IF(I3="First Half", 0.5, IF(I3="Second Half", IF(OR(WEEKDAY(C3)=2,WEEKDAY(D3)=6),2.5,0.5), (D3-C3)+1+ IF(WEEKDAY(C3)=2,2,0)+ IF(WEEKDAY(D3)=6,2,0))) -> 9 | I3: Full Day | J3: =IF(Q3="Pending","Waiting Approval", IF(Q3="Rejected","Rejected", IF(Q3="Cancelled","Cancelled", IF(TODAY()<C3,"Upcoming", IF(AND(TODAY()>=C3,TODAY()<=D3),"In Progress", IF(TODAY()>D3,"Completed","")))))) -> Completed | M3: No | O3: 46136 | P3: Approved | Q3: Sowndar | R3: 46121
A4: Rackesh Kumaran | B4: Sick Leave | C4: 46161 | D4: 46161 | E4: =IF(I4="First Half",0.5, IF(I4="Second Half",0.5, NETWORKDAYS(C4,D4))) -> 0.5 | F4: =IFERROR(__xludf.DUMMYFUNCTION("IF(I4=""First Half"", ""First Half - ""&TEXT(C4,""dddd""), IF(I4=""Second Half"", ""Second Half - ""&TEXT(C4,""dddd""), TEXTJOIN("", "",TRUE,FILTER(TEXT(SEQUENCE(D4-C4+1,1,C4),""dddd""),WEEKDAY(SEQUENCE(D4-C4+1,1,C4),2)<6))))"),"Second Half - Tuesday") -> Second Half - Tuesday | G4: {=IF(I4="First Half", "First Half - "&TEXT(C4,"dddd"), IF(I4="Second Half", IF(OR(WEEKDAY(C4)=2,WEEKDAY(D4)=6), "Saturday, Sunday, Second Half - "&TEXT(C4,"dddd")&", Saturday, Sunday", "Second Half - "&TEXT(C4,"dddd")), TEXTJOIN(", ",TRUE, TEXT( SEQUENCE( (D4-C4)+1+ IF(WEEKDAY(C4)=2,2,0)+ IF(WEEKDAY(D4)=6,2,0), 1, C4-IF(WEEKDAY(C4)=2,2,0) ), "dddd"))))} -> Second Half - Tuesday | H4: =IF(I4="First Half", 0.5, IF(I4="Second Half", IF(OR(WEEKDAY(C4)=2,WEEKDAY(D4)=6),2.5,0.5), (D4-C4)+1+ IF(WEEKDAY(C4)=2,2,0)+ IF(WEEKDAY(D4)=6,2,0))) -> 0.5 | I4: Second Half | J4: =IF(Q4="Pending","Waiting Approval", IF(Q4="Rejected","Rejected", IF(Q4="Cancelled","Cancelled", IF(TODAY()<C4,"Upcoming", IF(AND(TODAY()>=C4,TODAY()<=D4),"In Progress", IF(TODAY()>D4,"Completed","")))))) -> Completed | L4: Food Poison | M4: No | O4: 46161 | P4: Approved | Q4: Sowndar | R4: 46161
A5: Rackesh Kumaran | B5: Sick Leave | C5: 46162 | D5: 46162 | E5: =IF(I5="First Half",0.5, IF(I5="Second Half",0.5, NETWORKDAYS(C5,D5))) -> 1 | F5: =IFERROR(__xludf.DUMMYFUNCTION("IF(I5=""First Half"", ""First Half - ""&TEXT(C5,""dddd""), IF(I5=""Second Half"", ""Second Half - ""&TEXT(C5,""dddd""), TEXTJOIN("", "",TRUE,FILTER(TEXT(SEQUENCE(D5-C5+1,1,C5),""dddd""),WEEKDAY(SEQUENCE(D5-C5+1,1,C5),2)<6))))"),"Wednesday") -> Wednesday | G5: {=IF(I5="First Half", "First Half - "&TEXT(C5,"dddd"), IF(I5="Second Half", IF(OR(WEEKDAY(C5)=2,WEEKDAY(D5)=6), "Saturday, Sunday, Second Half - "&TEXT(C5,"dddd")&", Saturday, Sunday", "Second Half - "&TEXT(C5,"dddd")), TEXTJOIN(", ",TRUE, TEXT( SEQUENCE( (D5-C5)+1+ IF(WEEKDAY(C5)=2,2,0)+ IF(WEEKDAY(D5)=6,2,0), 1, C5-IF(WEEKDAY(C5)=2,2,0) ), "dddd"))))} -> Wednesday | H5: =IF(I5="First Half", 0.5, IF(I5="Second Half", IF(OR(WEEKDAY(C5)=2,WEEKDAY(D5)=6),2.5,0.5), (D5-C5)+1+ IF(WEEKDAY(C5)=2,2,0)+ IF(WEEKDAY(D5)=6,2,0))) -> 1 | I5: Full Day | J5: =IF(Q5="Pending","Waiting Approval", IF(Q5="Rejected","Rejected", IF(Q5="Cancelled","Cancelled", IF(TODAY()<C5,"Upcoming", IF(AND(TODAY()>=C5,TODAY()<=D5),"In Progress", IF(TODAY()>D5,"Completed","")))))) -> Completed | L5: Food Poison | M5: No | O5: 46162 | P5: Approved | Q5: Sowndar | R5: 46162
A6: Rackesh Kumaran | B6: Sick Leave | C6: 46163 | D6: 46163 | E6: =IF(I6="First Half",0.5, IF(I6="Second Half",0.5, NETWORKDAYS(C6,D6))) -> 1 | F6: =IFERROR(__xludf.DUMMYFUNCTION("IF(I6=""First Half"", ""First Half - ""&TEXT(C6,""dddd""), IF(I6=""Second Half"", ""Second Half - ""&TEXT(C6,""dddd""), TEXTJOIN("", "",TRUE,FILTER(TEXT(SEQUENCE(D6-C6+1,1,C6),""dddd""),WEEKDAY(SEQUENCE(D6-C6+1,1,C6),2)<6))))"),"Thursday") -> Thursday | G6: {=IF(I6="First Half", "First Half - "&TEXT(C6,"dddd"), IF(I6="Second Half", IF(OR(WEEKDAY(C6)=2,WEEKDAY(D6)=6), "Saturday, Sunday, Second Half - "&TEXT(C6,"dddd")&", Saturday, Sunday", "Second Half - "&TEXT(C6,"dddd")), TEXTJOIN(", ",TRUE, TEXT( SEQUENCE( (D6-C6)+1+ IF(WEEKDAY(C6)=2,2,0)+ IF(WEEKDAY(D6)=6,2,0), 1, C6-IF(WEEKDAY(C6)=2,2,0) ), "dddd"))))} -> Thursday | H6: =IF(I6="First Half", 0.5, IF(I6="Second Half", IF(OR(WEEKDAY(C6)=2,WEEKDAY(D6)=6),2.5,0.5), (D6-C6)+1+ IF(WEEKDAY(C6)=2,2,0)+ IF(WEEKDAY(D6)=6,2,0))) -> 1 | I6: Full Day | J6: =IF(Q6="Pending","Waiting Approval", IF(Q6="Rejected","Rejected", IF(Q6="Cancelled","Cancelled", IF(TODAY()<C6,"Upcoming", IF(AND(TODAY()>=C6,TODAY()<=D6),"In Progress", IF(TODAY()>D6,"Completed","")))))) -> Completed | L6: Food Poison | M6: No | O6: 46163 | P6: Approved | Q6: Sowndar | R6: 46163
A7: Rackesh Kumaran | B7: Sick Leave | C7: 46164 | D7: 46164 | E7: =IF(I7="First Half",0.5, IF(I7="Second Half",0.5, NETWORKDAYS(C7,D7))) -> 1 | F7: =IFERROR(__xludf.DUMMYFUNCTION("IF(I7=""First Half"", ""First Half - ""&TEXT(C7,""dddd""), IF(I7=""Second Half"", ""Second Half - ""&TEXT(C7,""dddd""), TEXTJOIN("", "",TRUE,FILTER(TEXT(SEQUENCE(D7-C7+1,1,C7),""dddd""),WEEKDAY(SEQUENCE(D7-C7+1,1,C7),2)<6))))"),"Friday") -> Friday | G7: {=IF(I7="First Half", "First Half - "&TEXT(C7,"dddd"), IF(I7="Second Half", IF(OR(WEEKDAY(C7)=2,WEEKDAY(D7)=6), "Saturday, Sunday, Second Half - "&TEXT(C7,"dddd")&", Saturday, Sunday", "Second Half - "&TEXT(C7,"dddd")), TEXTJOIN(", ",TRUE, TEXT( SEQUENCE( (D7-C7)+1+ IF(WEEKDAY(C7)=2,2,0)+ IF(WEEKDAY(D7)=6,2,0), 1, C7-IF(WEEKDAY(C7)=2,2,0) ), "dddd"))))} -> Friday, Saturday, Sunday | H7: =IF(I7="First Half", 0.5, IF(I7="Second Half", IF(OR(WEEKDAY(C7)=2,WEEKDAY(D7)=6),2.5,0.5), (D7-C7)+1+ IF(WEEKDAY(C7)=2,2,0)+ IF(WEEKDAY(D7)=6,2,0))) -> 3 | I7: Full Day | J7: =IF(Q7="Pending","Waiting Approval", IF(Q7="Rejected","Rejected", IF(Q7="Cancelled","Cancelled", IF(TODAY()<C7,"Upcoming", IF(AND(TODAY()>=C7,TODAY()<=D7),"In Progress", IF(TODAY()>D7,"Completed","")))))) -> Completed | L7: Food Poison | M7: No | O7: 46163 | P7: Approved | Q7: Sowndar | R7: 46163
A8: Rackesh Kumaran | B8: Sick Leave | C8: 46167 | D8: 46171 | E8: =IF(I8="First Half",0.5, IF(I8="Second Half",0.5, NETWORKDAYS(C8,D8))) -> 5 | F8: =IFERROR(__xludf.DUMMYFUNCTION("IF(I8=""First Half"", ""First Half - ""&TEXT(C8,""dddd""), IF(I8=""Second Half"", ""Second Half - ""&TEXT(C8,""dddd""), TEXTJOIN("", "",TRUE,FILTER(TEXT(SEQUENCE(D8-C8+1,1,C8),""dddd""),WEEKDAY(SEQUENCE(D8-C8+1,1,C8),2)<6))))"),"Monday, Tuesday, Wednesday, Thursday, Friday") -> Monday, Tuesday, Wednesday, Thursday, Friday | G8: {=IF(I8="First Half", "First Half - "&TEXT(C8,"dddd"), IF(I8="Second Half", IF(OR(WEEKDAY(C8)=2,WEEKDAY(D8)=6), "Saturday, Sunday, Second Half - "&TEXT(C8,"dddd")&", Saturday, Sunday", "Second Half - "&TEXT(C8,"dddd")), TEXTJOIN(", ",TRUE, TEXT( SEQUENCE( (D8-C8)+1+ IF(WEEKDAY(C8)=2,2,0)+ IF(WEEKDAY(D8)=6,2,0), 1, C8-IF(WEEKDAY(C8)=2,2,0) ), "dddd"))))} -> Saturday, Sunday, Monday, Tuesday, Wednesday, Thursday, Friday, Saturday, Sunday | H8: =IF(I8="First Half", 0.5, IF(I8="Second Half", IF(OR(WEEKDAY(C8)=2,WEEKDAY(D8)=6),2.5,0.5), (D8-C8)+1+ IF(WEEKDAY(C8)=2,2,0)+ IF(WEEKDAY(D8)=6,2,0))) -> 9 | I8: Full Day | J8: =IF(Q8="Pending","Waiting Approval", IF(Q8="Rejected","Rejected", IF(Q8="Cancelled","Cancelled", IF(TODAY()<C8,"Upcoming", IF(AND(TODAY()>=C8,TODAY()<=D8),"In Progress", IF(TODAY()>D8,"Completed","")))))) -> Completed | L8: Food Poison | M8: No | O8: 46163 | P8: Approved | Q8: Sowndar | R8: 46163
A9: Abhicheke | B9: Casual Leave | C9: 46170 | D9: 46171 | E9: =IF(I9="First Half",0.5, IF(I9="Second Half",0.5, NETWORKDAYS(C9,D9))) -> 2 | F9: =IFERROR(__xludf.DUMMYFUNCTION("IF(I9=""First Half"", ""First Half - ""&TEXT(C9,""dddd""), IF(I9=""Second Half"", ""Second Half - ""&TEXT(C9,""dddd""), TEXTJOIN("", "",TRUE,FILTER(TEXT(SEQUENCE(D9-C9+1,1,C9),""dddd""),WEEKDAY(SEQUENCE(D9-C9+1,1,C9),2)<6))))"),"Thursday, Friday") -> Thursday, Friday | G9: {=IF(I9="First Half", "First Half - "&TEXT(C9,"dddd"), IF(I9="Second Half", IF(OR(WEEKDAY(C9)=2,WEEKDAY(D9)=6), "Saturday, Sunday, Second Half - "&TEXT(C9,"dddd")&", Saturday, Sunday", "Second Half - "&TEXT(C9,"dddd")), TEXTJOIN(", ",TRUE, TEXT( SEQUENCE( (D9-C9)+1+ IF(WEEKDAY(C9)=2,2,0)+ IF(WEEKDAY(D9)=6,2,0), 1, C9-IF(WEEKDAY(C9)=2,2,0) ), "dddd"))))} -> Thursday, Friday, Saturday, Sunday | H9: =IF(I9="First Half", 0.5, IF(I9="Second Half", IF(OR(WEEKDAY(C9)=2,WEEKDAY(D9)=6),2.5,0.5), (D9-C9)+1+ IF(WEEKDAY(C9)=2,2,0)+ IF(WEEKDAY(D9)=6,2,0))) -> 4 | I9: Full Day | J9: =IF(Q9="Pending","Waiting Approval", IF(Q9="Rejected","Rejected", IF(Q9="Cancelled","Cancelled", IF(TODAY()<C9,"Upcoming", IF(AND(TODAY()>=C9,TODAY()<=D9),"In Progress", IF(TODAY()>D9,"Completed","")))))) -> Completed | L9: Going to Temple | M9: No | O9: 46136 | P9: Approved | Q9: Sowndar | R9: 46121
A10: Moswin | B10: Casual Leave | C10: 46171 | D10: 46171 | E10: =IF(I10="First Half",0.5, IF(I10="Second Half",0.5, NETWORKDAYS(C10,D10))) -> 0.5 | F10: =IFERROR(__xludf.DUMMYFUNCTION("IF(I10=""First Half"", ""First Half - ""&TEXT(C10,""dddd""), IF(I10=""Second Half"", ""Second Half - ""&TEXT(C10,""dddd""), TEXTJOIN("", "",TRUE,FILTER(TEXT(SEQUENCE(D10-C10+1,1,C10),""dddd""),WEEKDAY(SEQUENCE(D10-C10+1,1,C10),2)<6))))"),"Second Half - Friday") -> Second Half - Friday | G10: {=IF(I10="First Half", "First Half - "&TEXT(C10,"dddd"), IF(I10="Second Half", IF(OR(WEEKDAY(C10)=2,WEEKDAY(D10)=6), "Saturday, Sunday, Second Half - "&TEXT(C10,"dddd")&", Saturday, Sunday", "Second Half - "&TEXT(C10,"dddd")), TEXTJOIN(", ",TRUE, TEXT( SEQUENCE( (D10-C10)+1+ IF(WEEKDAY(C10)=2,2,0)+ IF(WEEKDAY(D10)=6,2,0), 1, C10-IF(WEEKDAY(C10)=2,2,0) ), "dddd"))))} -> Saturday, Sunday, Second Half - Friday, Saturday, Sunday | H10: =IF(I10="First Half", 0.5, IF(I10="Second Half", IF(OR(WEEKDAY(C10)=2,WEEKDAY(D10)=6),2.5,0.5), (D10-C10)+1+ IF(WEEKDAY(C10)=2,2,0)+ IF(WEEKDAY(D10)=6,2,0))) -> 2.5 | I10: Second Half | J10: =IF(Q10="Pending","Waiting Approval", IF(Q10="Rejected","Rejected", IF(Q10="Cancelled","Cancelled", IF(TODAY()<C10,"Upcoming", IF(AND(TODAY()>=C10,TODAY()<=D10),"In Progress", IF(TODAY()>D10,"Completed","")))))) -> Completed | L10: - | M10: No | O10: 46156 | P10: Approved | Q10: Sowndar | R10: 46171
A11: Parthiban | B11: Casual Leave | C11: 46174 | D11: 46174 | E11: =IF(I11="First Half",0.5, IF(I11="Second Half",0.5, NETWORKDAYS(C11,D11))) -> 1 | F11: =IFERROR(__xludf.DUMMYFUNCTION("IF(I11=""First Half"", ""First Half - ""&TEXT(C11,""dddd""), IF(I11=""Second Half"", ""Second Half - ""&TEXT(C11,""dddd""), TEXTJOIN("", "",TRUE,FILTER(TEXT(SEQUENCE(D11-C11+1,1,C11),""dddd""),WEEKDAY(SEQUENCE(D11-C11+1,1,C11),2)<6))))"),"Monday") -> Monday | G11: {=IF(I11="First Half", "First Half - "&TEXT(C11,"dddd"), IF(I11="Second Half", IF(OR(WEEKDAY(C11)=2,WEEKDAY(D11)=6), "Saturday, Sunday, Second Half - "&TEXT(C11,"dddd")&", Saturday, Sunday", "Second Half - "&TEXT(C11,"dddd")), TEXTJOIN(", ",TRUE, TEXT( SEQUENCE( (D11-C11)+1+ IF(WEEKDAY(C11)=2,2,0)+ IF(WEEKDAY(D11)=6,2,0), 1, C11-IF(WEEKDAY(C11)=2,2,0) ), "dddd"))))} -> Saturday, Sunday, Monday | H11: =IF(I11="First Half", 0.5, IF(I11="Second Half", IF(OR(WEEKDAY(C11)=2,WEEKDAY(D11)=6),2.5,0.5), (D11-C11)+1+ IF(WEEKDAY(C11)=2,2,0)+ IF(WEEKDAY(D11)=6,2,0))) -> 3 | I11: Full Day | J11: =IF(Q11="Pending","Waiting Approval", IF(Q11="Rejected","Rejected", IF(Q11="Cancelled","Cancelled", IF(TODAY()<C11,"Upcoming", IF(AND(TODAY()>=C11,TODAY()<=D11),"In Progress", IF(TODAY()>D11,"Completed","")))))) -> Completed | L11: Going to Native | M11: No | O11: 46156 | P11: Approved | Q11: Sowndar | R11: 46162
A12: Moswin | B12: Casual Leave | C12: 46175 | D12: 46175 | E12: =IF(I12="First Half",0.5, IF(I12="Second Half",0.5, NETWORKDAYS(C12,D12))) -> 0.5 | F12: =IFERROR(__xludf.DUMMYFUNCTION("IF(I12=""First Half"", ""First Half - ""&TEXT(C12,""dddd""), IF(I12=""Second Half"", ""Second Half - ""&TEXT(C12,""dddd""), TEXTJOIN("", "",TRUE,FILTER(TEXT(SEQUENCE(D12-C12+1,1,C12),""dddd""),WEEKDAY(SEQUENCE(D12-C12+1,1,C12),2)<6))))"),"Second Half - Tuesday") -> Second Half - Tuesday | G12: {=IF(I12="First Half", "First Half - "&TEXT(C12,"dddd"), IF(I12="Second Half", IF(OR(WEEKDAY(C12)=2,WEEKDAY(D12)=6), "Saturday, Sunday, Second Half - "&TEXT(C12,"dddd")&", Saturday, Sunday", "Second Half - "&TEXT(C12,"dddd")), TEXTJOIN(", ",TRUE, TEXT( SEQUENCE( (D12-C12)+1+ IF(WEEKDAY(C12)=2,2,0)+ IF(WEEKDAY(D12)=6,2,0), 1, C12-IF(WEEKDAY(C12)=2,2,0) ), "dddd"))))} -> Second Half - Tuesday | H12: =IF(I12="First Half", 0.5, IF(I12="Second Half", IF(OR(WEEKDAY(C12)=2,WEEKDAY(D12)=6),2.5,0.5), (D12-C12)+1+ IF(WEEKDAY(C12)=2,2,0)+ IF(WEEKDAY(D12)=6,2,0))) -> 0.5 | I12: Second Half | J12: =IF(Q12="Pending","Waiting Approval", IF(Q12="Rejected","Rejected", IF(Q12="Cancelled","Cancelled", IF(TODAY()<C12,"Upcoming", IF(AND(TODAY()>=C12,TODAY()<=D12),"In Progress", IF(TODAY()>D12,"Completed","")))))) -> Completed | L12: Going to Native | M12: No | O12: 46175 | P12: Approved | Q12: Sowndar | R12: 46175
A13: Moswin | B13: Casual Leave | C13: 46176 | D13: 46176 | E13: =IF(I13="First Half",0.5, IF(I13="Second Half",0.5, NETWORKDAYS(C13,D13))) -> 1 | F13: =IFERROR(__xludf.DUMMYFUNCTION("IF(I13=""First Half"", ""First Half - ""&TEXT(C13,""dddd""), IF(I13=""Second Half"", ""Second Half - ""&TEXT(C13,""dddd""), TEXTJOIN("", "",TRUE,FILTER(TEXT(SEQUENCE(D13-C13+1,1,C13),""dddd""),WEEKDAY(SEQUENCE(D13-C13+1,1,C13),2)<6))))"),"Wednesday") -> Wednesday | G13: {=IF(I13="First Half", "First Half - "&TEXT(C13,"dddd"), IF(I13="Second Half", IF(OR(WEEKDAY(C13)=2,WEEKDAY(D13)=6), "Saturday, Sunday, Second Half - "&TEXT(C13,"dddd")&", Saturday, Sunday", "Second Half - "&TEXT(C13,"dddd")), TEXTJOIN(", ",TRUE, TEXT( SEQUENCE( (D13-C13)+1+ IF(WEEKDAY(C13)=2,2,0)+ IF(WEEKDAY(D13)=6,2,0), 1, C13-IF(WEEKDAY(C13)=2,2,0) ), "dddd"))))} -> Wednesday | H13: =IF(I13="First Half", 0.5, IF(I13="Second Half", IF(OR(WEEKDAY(C13)=2,WEEKDAY(D13)=6),2.5,0.5), (D13-C13)+1+ IF(WEEKDAY(C13)=2,2,0)+ IF(WEEKDAY(D13)=6,2,0))) -> 1 | I13: Full Day | J13: =IF(Q13="Pending","Waiting Approval", IF(Q13="Rejected","Rejected", IF(Q13="Cancelled","Cancelled", IF(TODAY()<C13,"Upcoming", IF(AND(TODAY()>=C13,TODAY()<=D13),"In Progress", IF(TODAY()>D13,"Completed","")))))) -> Completed | L13: Going to Native | M13: No | O13: 46175 | P13: Approved | Q13: Sowndar | R13: 46175
A14: Parthiban | B14: Casual Leave | C14: 46181 | D14: 46181 | E14: =IF(I14="First Half",0.5, IF(I14="Second Half",0.5, NETWORKDAYS(C14,D14))) -> 1 | F14: =IFERROR(__xludf.DUMMYFUNCTION("IF(I14=""First Half"", ""First Half - ""&TEXT(C14,""dddd""), IF(I14=""Second Half"", ""Second Half - ""&TEXT(C14,""dddd""), TEXTJOIN("", "",TRUE,FILTER(TEXT(SEQUENCE(D14-C14+1,1,C14),""dddd""),WEEKDAY(SEQUENCE(D14-C14+1,1,C14),2)<6))))"),"Monday") -> Monday | G14: {=IF(I14="First Half", "First Half - "&TEXT(C14,"dddd"), IF(I14="Second Half", IF(OR(WEEKDAY(C14)=2,WEEKDAY(D14)=6), "Saturday, Sunday, Second Half - "&TEXT(C14,"dddd")&", Saturday, Sunday", "Second Half - "&TEXT(C14,"dddd")), TEXTJOIN(", ",TRUE, TEXT( SEQUENCE( (D14-C14)+1+ IF(WEEKDAY(C14)=2,2,0)+ IF(WEEKDAY(D14)=6,2,0), 1, C14-IF(WEEKDAY(C14)=2,2,0) ), "dddd"))))} -> Saturday, Sunday, Monday | H14: =IF(I14="First Half", 0.5, IF(I14="Second Half", IF(OR(WEEKDAY(C14)=2,WEEKDAY(D14)=6),2.5,0.5), (D14-C14)+1+ IF(WEEKDAY(C14)=2,2,0)+ IF(WEEKDAY(D14)=6,2,0))) -> 3 | I14: Full Day | J14: =IF(Q14="Pending","Waiting Approval", IF(Q14="Rejected","Rejected", IF(Q14="Cancelled","Cancelled", IF(TODAY()<C14,"Upcoming", IF(AND(TODAY()>=C14,TODAY()<=D14),"In Progress", IF(TODAY()>D14,"Completed","")))))) -> Completed | L14: Medical apointment for mother | M14: No | O14: 46177 | P14: Approved | Q14: Sowndar | R14: 46177
H79: =IF(TRIM(I79)="Half Day",((D79-C79)+1)-0.5,IF(TRIM(I79)="Full Day",(D79-C79)+1,""))
H80: =IF(TRIM(I80)="Half Day",((D80-C80)+1)-0.5,IF(TRIM(I80)="Full Day",(D80-C80)+1,""))
H81: =IF(TRIM(I81)="Half Day",((D81-C81)+1)-0.5,IF(TRIM(I81)="Full Day",(D81-C81)+1,""))
H82: =IF(TRIM(I82)="Half Day",((D82-C82)+1)-0.5,IF(TRIM(I82)="Full Day",(D82-C82)+1,""))
H83: =IF(TRIM(I83)="Half Day",((D83-C83)+1)-0.5,IF(TRIM(I83)="Full Day",(D83-C83)+1,""))
H84: =IF(TRIM(I84)="Half Day",((D84-C84)+1)-0.5,IF(TRIM(I84)="Full Day",(D84-C84)+1,""))
H85: =IF(TRIM(I85)="Half Day",((D85-C85)+1)-0.5,IF(TRIM(I85)="Full Day",(D85-C85)+1,""))
H86: =IF(TRIM(I86)="Half Day",((D86-C86)+1)-0.5,IF(TRIM(I86)="Full Day",(D86-C86)+1,""))
H87: =IF(TRIM(I87)="Half Day",((D87-C87)+1)-0.5,IF(TRIM(I87)="Full Day",(D87-C87)+1,""))
H88: =IF(TRIM(I88)="Half Day",((D88-C88)+1)-0.5,IF(TRIM(I88)="Full Day",(D88-C88)+1,""))
H89: =IF(TRIM(I89)="Half Day",((D89-C89)+1)-0.5,IF(TRIM(I89)="Full Day",(D89-C89)+1,""))
H90: =IF(TRIM(I90)="Half Day",((D90-C90)+1)-0.5,IF(TRIM(I90)="Full Day",(D90-C90)+1,""))
... H94: =IF(TRIM(I94)="Half Day",((D94-C94)+1)-0.5,IF(TRIM(I94)="Full Day",(D94-C94)+1,""))

Sheet Internal Tracker 2026
A1: Project Name | B1: Website Url | C1: Task | D1: Priority | E1: Assign | F1: S Date | G1: E Date | H1: As Per WO | I1: Status | J1: Env | K1: Efforts | L1: Actual Effors | M1: Informed | N1: Support Needed / Blocker | O1: Dependency Detail | P1: Page Url | Q1: Mail Subject | R1: Internal Mail Subject | S1: Functionality | T1: My Understanding
A2: Vajra Global | B2: vajraglobal.com | C2: Meeting with Sundar on Next Week | D2: Low | E2: Sowndar | F2: 46105 | G2: 46105 | H2: 46105 | I2: Completed | K2: =IF( COUNTIFS('Internal Tracker Sub 2026'!$A$2:$A$5050, TRIM($B2&""), 'Internal Tracker Sub 2026'!$B$2:$B$5050, TRIM($C2&""))=0, "No Subtasks", IF( SUMPRODUCT( --(TRIM('Internal Tracker Sub 2026'!$A$2:$A$5050&"")=TRIM($B2&"")), --(TRIM('Internal Tracker Sub 2026'!$B$2:$B$5050&"")=TRIM($C2&"")), --(LEN(TRIM('Internal Tracker Sub 2026'!$L$2:$L$5050&""))=0) )>0, "⚠ Missing Effort", SUMIFS( 'Internal Tracker Sub 2026'!$L$2:$L$5050, 'Internal Tracker Sub 2026'!$A$2:$A$5050, TRIM($B2&""), 'Internal Tracker Sub 2026'!$B$2:$B$5050, TRIM($C2&"") ) ) ) -> No Subtasks | N2: I have set the meeting with Sundar on 24 March
A3: Vajra Global | C3: Rakesh Traing | D3: Low | E3: Sowndar | I3: Completed | K3: =IF( COUNTIFS('Internal Tracker Sub 2026'!$A$2:$A$5050, TRIM($B3&""), 'Internal Tracker Sub 2026'!$B$2:$B$5050, TRIM($C3&""))=0, "No Subtasks", IF( SUMPRODUCT( --(TRIM('Internal Tracker Sub 2026'!$A$2:$A$5050&"")=TRIM($B3&"")), --(TRIM('Internal Tracker Sub 2026'!$B$2:$B$5050&"")=TRIM($C3&"")), --(LEN(TRIM('Internal Tracker Sub 2026'!$L$2:$L$5050&""))=0) )>0, "⚠ Missing Effort", SUMIFS( 'Internal Tracker Sub 2026'!$L$2:$L$5050, 'Internal Tracker Sub 2026'!$A$2:$A$5050, TRIM($B3&""), 'Internal Tracker Sub 2026'!$B$2:$B$5050, TRIM($C3&"") ) ) ) -> No Subtasks | N3: Training has done. We start giving the basic task. We gradually increase the work on upcoming days
A4: Vajra Global | B4: vajraglobal.com | C4: Request for Additional Static IP for Chennai Office | D4: Low | E4: Sowndar | F4: 46100 | G4: 46113 | I4: Completed | K4: =IF( COUNTIFS('Internal Tracker Sub 2026'!$A$2:$A$5050, TRIM($B4&""), 'Internal Tracker Sub 2026'!$B$2:$B$5050, TRIM($C4&""))=0, "No Subtasks", IF( SUMPRODUCT( --(TRIM('Internal Tracker Sub 2026'!$A$2:$A$5050&"")=TRIM($B4&"")), --(TRIM('Internal Tracker Sub 2026'!$B$2:$B$5050&"")=TRIM($C4&"")), --(LEN(TRIM('Internal Tracker Sub 2026'!$L$2:$L$5050&""))=0) )>0, "⚠ Missing Effort", SUMIFS( 'Internal Tracker Sub 2026'!$L$2:$L$5050, 'Internal Tracker Sub 2026'!$A$2:$A$5050, TRIM($B4&""), 'Internal Tracker Sub 2026'!$B$2:$B$5050, TRIM($C4&"") ) ) ) -> No Subtasks
A5: Vajra Global | B5: vajraglobal.com | C5: Upcoming Leave Notification For Sai | D5: Low | E5: Sowndar | G5: 46099 | I5: Completed | K5: =IF( COUNTIFS('Internal Tracker Sub 2026'!$A$2:$A$5050, TRIM($B5&""), 'Internal Tracker Sub 2026'!$B$2:$B$5050, TRIM($C5&""))=0, "No Subtasks", IF( SUMPRODUCT( --(TRIM('Internal Tracker Sub 2026'!$A$2:$A$5050&"")=TRIM($B5&"")), --(TRIM('Internal Tracker Sub 2026'!$B$2:$B$5050&"")=TRIM($C5&"")), --(LEN(TRIM('Internal Tracker Sub 2026'!$L$2:$L$5050&""))=0) )>0, "⚠ Missing Effort", SUMIFS( 'Internal Tracker Sub 2026'!$L$2:$L$5050, 'Internal Tracker Sub 2026'!$A$2:$A$5050, TRIM($B5&""), 'Internal Tracker Sub 2026'!$B$2:$B$5050, TRIM($C5&"") ) ) ) -> No Subtasks | N5: Sai will be unavailable from May 22 to June 07, 2026, due to his wedding. We will require an alternative resource to manage the project during his absence As we disscussed over the meeting Regan will take care of Fanborought and I will coordinate with Adfactor team | R5: [NEW TASK] [Vajra] Sai Vacation Holiday
A6: Vajra Global | B6: vajraglobal.com | C6: Upcoming Leave Notification For abhicheke | D6: Low | E6: Sowndar | G6: 46099 | I6: In Progress | K6: =IF( COUNTIFS('Internal Tracker Sub 2026'!$A$2:$A$5050, TRIM($B6&""), 'Internal Tracker Sub 2026'!$B$2:$B$5050, TRIM($C6&""))=0, "No Subtasks", IF( SUMPRODUCT( --(TRIM('Internal Tracker Sub 2026'!$A$2:$A$5050&"")=TRIM($B6&"")), --(TRIM('Internal Tracker Sub 2026'!$B$2:$B$5050&"")=TRIM($C6&"")), --(LEN(TRIM('Internal Tracker Sub 2026'!$L$2:$L$5050&""))=0) )>0, "⚠ Missing Effort", SUMIFS( 'Internal Tracker Sub 2026'!$L$2:$L$5050, 'Internal Tracker Sub 2026'!$A$2:$A$5050, TRIM($B6&""), 'Internal Tracker Sub 2026'!$B$2:$B$5050, TRIM($C6&"") ) ) ) -> No Subtasks | N6: Abhishek Wedding Leave (Staggered Schedule): Based on project requirements, the leave has been restructured into a staggered format to maintain momentum: 11 May & 12 May: Leave 18 May – 24 May: Leave 25 May – 27 May: Working / Check-in Window (To address urgent blockers) 28 May & 29 May: Leave | R6: [NEW TASK] [Vajra] Abi Vacation Holiday
A7: Vajra Global | B7: vajraglobal.com | C7: Umbraco sites Pitch | D7: Low | E7: Sowndar | F7: 46028 | I7: In Progress | K7: =IF( COUNTIFS('Internal Tracker Sub 2026'!$A$2:$A$5050, TRIM($B7&""), 'Internal Tracker Sub 2026'!$B$2:$B$5050, TRIM($C7&""))=0, "No Subtasks", IF( SUMPRODUCT( --(TRIM('Internal Tracker Sub 2026'!$A$2:$A$5050&"")=TRIM($B7&"")), --(TRIM('Internal Tracker Sub 2026'!$B$2:$B$5050&"")=TRIM($C7&"")), --(LEN(TRIM('Internal Tracker Sub 2026'!$L$2:$L$5050&""))=0) )>0, "⚠ Missing Effort", SUMIFS( 'Internal Tracker Sub 2026'!$L$2:$L$5050, 'Internal Tracker Sub 2026'!$A$2:$A$5050, TRIM($B7&""), 'Internal Tracker Sub 2026'!$B$2:$B$5050, TRIM($C7&"") ) ) ) -> No Subtasks | R7: New Outreach Project: Targeting Legacy Umbraco 7,8,9 & 10 Sites
A8: Vajra Global | B8: vajraglobal.com | C8: CI/CD Automation For all Website | D8: Low | E8: Moswin | I8: In Progress | K8: =IF( COUNTIFS('Internal Tracker Sub 2026'!$A$2:$A$5050, TRIM($B8&""), 'Internal Tracker Sub 2026'!$B$2:$B$5050, TRIM($C8&""))=0, "No Subtasks", IF( SUMPRODUCT( --(TRIM('Internal Tracker Sub 2026'!$A$2:$A$5050&"")=TRIM($B8&"")), --(TRIM('Internal Tracker Sub 2026'!$B$2:$B$5050&"")=TRIM($C8&"")), --(LEN(TRIM('Internal Tracker Sub 2026'!$L$2:$L$5050&""))=0) )>0, "⚠ Missing Effort", SUMIFS( 'Internal Tracker Sub 2026'!$L$2:$L$5050, 'Internal Tracker Sub 2026'!$A$2:$A$5050, TRIM($B8&""), 'Internal Tracker Sub 2026'!$B$2:$B$5050, TRIM($C8&"") ) ) ) -> No Subtasks | R8: Important mainly because it was sent directly to you
A9: Vajra Global | B9: vajraglobal.com | C9: Updated Updated SEO Automation BRD BRD | D9: Low | E9: Moswin | I9: In Progress | K9: =IF( COUNTIFS('Internal Tracker Sub 2026'!$A$2:$A$5050, TRIM($B9&""), 'Internal Tracker Sub 2026'!$B$2:$B$5050, TRIM($C9&""))=0, "No Subtasks", IF( SUMPRODUCT( --(TRIM('Internal Tracker Sub 2026'!$A$2:$A$5050&"")=TRIM($B9&"")), --(TRIM('Internal Tracker Sub 2026'!$B$2:$B$5050&"")=TRIM($C9&"")), --(LEN(TRIM('Internal Tracker Sub 2026'!$L$2:$L$5050&""))=0) )>0, "⚠ Missing Effort", SUMIFS( 'Internal Tracker Sub 2026'!$L$2:$L$5050, 'Internal Tracker Sub 2026'!$A$2:$A$5050, TRIM($B9&""), 'Internal Tracker Sub 2026'!$B$2:$B$5050, TRIM($C9&"") ) ) ) -> No Subtasks | R9: Click to teach Vajra Global Consulting Services LLP Mail this conversation is not important
A10: Vajra Global | B10: vajraglobal.com | C10: Server Inventory | D10: Low | E10: Moswin | F10: 46076 | G10: 46127 | H10: 46120 | I10: In Progress | K10: =IF( COUNTIFS('Internal Tracker Sub 2026'!$A$2:$A$5050, TRIM($B10&""), 'Internal Tracker Sub 2026'!$B$2:$B$5050, TRIM($C10&""))=0, "No Subtasks", IF( SUMPRODUCT( --(TRIM('Internal Tracker Sub 2026'!$A$2:$A$5050&"")=TRIM($B10&"")), --(TRIM('Internal Tracker Sub 2026'!$B$2:$B$5050&"")=TRIM($C10&"")), --(LEN(TRIM('Internal Tracker Sub 2026'!$L$2:$L$5050&""))=0) )>0, "⚠ Missing Effort", SUMIFS( 'Internal Tracker Sub 2026'!$L$2:$L$5050, 'Internal Tracker Sub 2026'!$A$2:$A$5050, TRIM($B10&""), 'Internal Tracker Sub 2026'!$B$2:$B$5050, TRIM($C10&"") ) ) ) -> No Subtasks
A11: Vajra Global | B11: vajraglobal.com | C11: Internal links | D11: Low | E11: Moswin | F11: 46120 | G11: 46129 | H11: 46129 | I11: In Progress | K11: =IF( COUNTIFS('Internal Tracker Sub 2026'!$A$2:$A$5050, TRIM($B11&""), 'Internal Tracker Sub 2026'!$B$2:$B$5050, TRIM($C11&""))=0, "No Subtasks", IF( SUMPRODUCT( --(TRIM('Internal Tracker Sub 2026'!$A$2:$A$5050&"")=TRIM($B11&"")), --(TRIM('Internal Tracker Sub 2026'!$B$2:$B$5050&"")=TRIM($C11&"")), --(LEN(TRIM('Internal Tracker Sub 2026'!$L$2:$L$5050&""))=0) )>0, "⚠ Missing Effort", SUMIFS( 'Internal Tracker Sub 2026'!$L$2:$L$5050, 'Internal Tracker Sub 2026'!$A$2:$A$5050, TRIM($B11&""), 'Internal Tracker Sub 2026'!$B$2:$B$5050, TRIM($C11&"") ) ) ) -> ⚠ Missing Effort
A12: Vajra Global | B12: vajraglobal.com | C12: DevOps as a Service (DaaS) | D12: Low | E12: Moswin | F12: 46119 | G12: 46125 | H12: 46125 | I12: In Progress | K12: =IF( COUNTIFS('Internal Tracker Sub 2026'!$A$2:$A$5050, TRIM($B12&""), 'Internal Tracker Sub 2026'!$B$2:$B$5050, TRIM($C12&""))=0, "No Subtasks", IF( SUMPRODUCT( --(TRIM('Internal Tracker Sub 2026'!$A$2:$A$5050&"")=TRIM($B12&"")), --(TRIM('Internal Tracker Sub 2026'!$B$2:$B$5050&"")=TRIM($C12&"")), --(LEN(TRIM('Internal Tracker Sub 2026'!$L$2:$L$5050&""))=0) )>0, "⚠ Missing Effort", SUMIFS( 'Internal Tracker Sub 2026'!$L$2:$L$5050, 'Internal Tracker Sub 2026'!$A$2:$A$5050, TRIM($B12&""), 'Internal Tracker Sub 2026'!$B$2:$B$5050, TRIM($C12&"") ) ) ) -> ⚠ Missing Effort | P12: Vajra_DevOps_as_a_Service.xlsx
K13: =IF( COUNTIFS('Internal Tracker Sub 2026'!$A$2:$A$5050, TRIM($B13&""), 'Internal Tracker Sub 2026'!$B$2:$B$5050, TRIM($C13&""))=0, "No Subtasks", IF( SUMPRODUCT( --(TRIM('Internal Tracker Sub 2026'!$A$2:$A$5050&"")=TRIM($B13&"")), --(TRIM('Internal Tracker Sub 2026'!$B$2:$B$5050&"")=TRIM($C13&"")), --(LEN(TRIM('Internal Tracker Sub 2026'!$L$2:$L$5050&""))=0) )>0, "⚠ Missing Effort", SUMIFS( 'Internal Tracker Sub 2026'!$L$2:$L$5050, 'Internal Tracker Sub 2026'!$A$2:$A$5050, TRIM($B13&""), 'Internal Tracker Sub 2026'!$B$2:$B$5050, TRIM($C13&"") ) ) ) -> ⚠ Missing Effort
K14: =IF( COUNTIFS('Internal Tracker Sub 2026'!$A$2:$A$5050, TRIM($B14&""), 'Internal Tracker Sub 2026'!$B$2:$B$5050, TRIM($C14&""))=0, "No Subtasks", IF( SUMPRODUCT( --(TRIM('Internal Tracker Sub 2026'!$A$2:$A$5050&"")=TRIM($B14&"")), --(TRIM('Internal Tracker Sub 2026'!$B$2:$B$5050&"")=TRIM($C14&"")), --(LEN(TRIM('Internal Tracker Sub 2026'!$L$2:$L$5050&""))=0) )>0, "⚠ Missing Effort", SUMIFS( 'Internal Tracker Sub 2026'!$L$2:$L$5050, 'Internal Tracker Sub 2026'!$A$2:$A$5050, TRIM($B14&""), 'Internal Tracker Sub 2026'!$B$2:$B$5050, TRIM($C14&"") ) ) ) -> ⚠ Missing Effort
K15: =IF( COUNTIFS('Internal Tracker Sub 2026'!$A$2:$A$5050, TRIM($B15&""), 'Internal Tracker Sub 2026'!$B$2:$B$5050, TRIM($C15&""))=0, "No Subtasks", IF( SUMPRODUCT( --(TRIM('Internal Tracker Sub 2026'!$A$2:$A$5050&"")=TRIM($B15&"")), --(TRIM('Internal Tracker Sub 2026'!$B$2:$B$5050&"")=TRIM($C15&"")), --(LEN(TRIM('Internal Tracker Sub 2026'!$L$2:$L$5050&""))=0) )>0, "⚠ Missing Effort", SUMIFS( 'Internal Tracker Sub 2026'!$L$2:$L$5050, 'Internal Tracker Sub 2026'!$A$2:$A$5050, TRIM($B15&""), 'Internal Tracker Sub 2026'!$B$2:$B$5050, TRIM($C15&"") ) ) ) -> ⚠ Missing Effort
K16: =IF( COUNTIFS('Internal Tracker Sub 2026'!$A$2:$A$5050, TRIM($B16&""), 'Internal Tracker Sub 2026'!$B$2:$B$5050, TRIM($C16&""))=0, "No Subtasks", IF( SUMPRODUCT( --(TRIM('Internal Tracker Sub 2026'!$A$2:$A$5050&"")=TRIM($B16&"")), --(TRIM('Internal Tracker Sub 2026'!$B$2:$B$5050&"")=TRIM($C16&"")), --(LEN(TRIM('Internal Tracker Sub 2026'!$L$2:$L$5050&""))=0) )>0, "⚠ Missing Effort", SUMIFS( 'Internal Tracker Sub 2026'!$L$2:$L$5050, 'Internal Tracker Sub 2026'!$A$2:$A$5050, TRIM($B16&""), 'Internal Tracker Sub 2026'!$B$2:$B$5050, TRIM($C16&"") ) ) ) -> ⚠ Missing Effort
K17: =IF( COUNTIFS('Internal Tracker Sub 2026'!$A$2:$A$5050, TRIM($B17&""), 'Internal Tracker Sub 2026'!$B$2:$B$5050, TRIM($C17&""))=0, "No Subtasks", IF( SUMPRODUCT( --(TRIM('Internal Tracker Sub 2026'!$A$2:$A$5050&"")=TRIM($B17&"")), --(TRIM('Internal Tracker Sub 2026'!$B$2:$B$5050&"")=TRIM($C17&"")), --(LEN(TRIM('Internal Tracker Sub 2026'!$L$2:$L$5050&""))=0) )>0, "⚠ Missing Effort", SUMIFS( 'Internal Tracker Sub 2026'!$L$2:$L$5050, 'Internal Tracker Sub 2026'!$A$2:$A$5050, TRIM($B17&""), 'Internal Tracker Sub 2026'!$B$2:$B$5050, TRIM($C17&"") ) ) ) -> ⚠ Missing Effort
K18: =IF( COUNTIFS('Internal Tracker Sub 2026'!$A$2:$A$5050, TRIM($B18&""), 'Internal Tracker Sub 2026'!$B$2:$B$5050, TRIM($C18&""))=0, "No Subtasks", IF( SUMPRODUCT( --(TRIM('Internal Tracker Sub 2026'!$A$2:$A$5050&"")=TRIM($B18&"")), --(TRIM('Internal Tracker Sub 2026'!$B$2:$B$5050&"")=TRIM($C18&"")), --(LEN(TRIM('Internal Tracker Sub 2026'!$L$2:$L$5050&""))=0) )>0, "⚠ Missing Effort", SUMIFS( 'Internal Tracker Sub 2026'!$L$2:$L$5050, 'Internal Tracker Sub 2026'!$A$2:$A$5050, TRIM($B18&""), 'Internal Tracker Sub 2026'!$B$2:$B$5050, TRIM($C18&"") ) ) ) -> ⚠ Missing Effort
K19: =IF( COUNTIFS('Internal Tracker Sub 2026'!$A$2:$A$5050, TRIM($B19&""), 'Internal Tracker Sub 2026'!$B$2:$B$5050, TRIM($C19&""))=0, "No Subtasks", IF( SUMPRODUCT( --(TRIM('Internal Tracker Sub 2026'!$A$2:$A$5050&"")=TRIM($B19&"")), --(TRIM('Internal Tracker Sub 2026'!$B$2:$B$5050&"")=TRIM($C19&"")), --(LEN(TRIM('Internal Tracker Sub 2026'!$L$2:$L$5050&""))=0) )>0, "⚠ Missing Effort", SUMIFS( 'Internal Tracker Sub 2026'!$L$2:$L$5050, 'Internal Tracker Sub 2026'!$A$2:$A$5050, TRIM($B19&""), 'Internal Tracker Sub 2026'!$B$2:$B$5050, TRIM($C19&"") ) ) ) -> ⚠ Missing Effort
K20: =IF( COUNTIFS('Internal Tracker Sub 2026'!$A$2:$A$5050, TRIM($B20&""), 'Internal Tracker Sub 2026'!$B$2:$B$5050, TRIM($C20&""))=0, "No Subtasks", IF( SUMPRODUCT( --(TRIM('Internal Tracker Sub 2026'!$A$2:$A$5050&"")=TRIM($B20&"")), --(TRIM('Internal Tracker Sub 2026'!$B$2:$B$5050&"")=TRIM($C20&"")), --(LEN(TRIM('Internal Tracker Sub 2026'!$L$2:$L$5050&""))=0) )>0, "⚠ Missing Effort", SUMIFS( 'Internal Tracker Sub 2026'!$L$2:$L$5050, 'Internal Tracker Sub 2026'!$A$2:$A$5050, TRIM($B20&""), 'Internal Tracker Sub 2026'!$B$2:$B$5050, TRIM($C20&"") ) ) ) -> ⚠ Missing Effort
K21: =IF( COUNTIFS('Internal Tracker Sub 2026'!$A$2:$A$5050, TRIM($B21&""), 'Internal Tracker Sub 2026'!$B$2:$B$5050, TRIM($C21&""))=0, "No Subtasks", IF( SUMPRODUCT( --(TRIM('Internal Tracker Sub 2026'!$A$2:$A$5050&"")=TRIM($B21&"")), --(TRIM('Internal Tracker Sub 2026'!$B$2:$B$5050&"")=TRIM($C21&"")), --(LEN(TRIM('Internal Tracker Sub 2026'!$L$2:$L$5050&""))=0) )>0, "⚠ Missing Effort", SUMIFS( 'Internal Tracker Sub 2026'!$L$2:$L$5050, 'Internal Tracker Sub 2026'!$A$2:$A$5050, TRIM($B21&""), 'Internal Tracker Sub 2026'!$B$2:$B$5050, TRIM($C21&"") ) ) ) -> ⚠ Missing Effort

Sheet Team Capacity
A1: Member | B1: Project | C1: Type | D1: Activity | E1: Task | F1: Status | G1: Week 1 | H1: Week 2 | I1: Week 3 | J1: Week 4 | K1: Week 5 | L1: Monthly Overall Utilization | M1: Monthly Available
A2: Sowndar | B2: Internal Communcation | C2: Non - Billable | D2: PM | E2: Communication | G2: 10 | H2: 5 | I2: 5 | J2: 5 | K2: 2 | L2: =G7+H7+I7+J7+K7 -> 117 | M2: =G8+H8+I8+J8+K8 -> 108
B3: Client Communication | C3: Non - Billable | D3: Dev | E3: Communication | G3: 3 | H3: 3 | I3: 3 | J3: 3 | K3: 3
B4: EM | C4: Billable | D4: PM/Dev | E4: Dev/Communication | G4: 15 | H4: 15 | I4: 15 | J4: 15 | K4: 15
B5: FIA | C5: Billable | D5: Dev | E5: Exhibitor API
F7: Weekly Utilization | G7: =G2+G3+G4+G5 -> 28 | H7: =H2+H3+H4+H5 -> 23 | I7: =I2+I3+I4+I5 -> 23 | J7: =J2+J3+J4+J5 -> 23 | K7: =K2+K3+K4+K5 -> 20
F8: Weekly Available | G8: =45-G7 -> 17 | H8: =45-H7 -> 22 | I8: =45-I7 -> 22 | J8: =45-J7 -> 22 | K8: =45-K7 -> 25
A11: Member | B11: Project | C11: Type | D11: Activity | E11: Task | F11: Status | G11: Week 1 | H11: Week 2 | I11: Week 3 | J11: Week 4 | K11: Week 5 | L11: Monthly Overall Utilization | M11: Monthly Available
A12: Abhicheke | B12: DGDA | C12: Billable | D12: Dev | E12: National Design System design apply for all Pages feedback changes | F12: Waiting for Client Input | G12: 25 | H12: 0 | I12: 0 | J12: 0 | K12: 0 | L12: =G19+H19+I19+J19+K19 -> 195 | M12: =G20+H20+I20+J20+K20 -> 30
B13: Work Adfactors | C13: Billable | D13: Live | E13: Work Adfactors Staging and Live Restore cross test | F13: Not Started | G13: 0 | H13: 0 | I13: 20 | J13: 5 | K13: 5
B14: DGDA | C14: Billable | D14: Dev | E14: Quamatic Integration | F14: Waiting for Client Input | G14: 0 | H14: 0 | I14: 5 | J14: 5 | K14: 5
B15: DGDA | C15: Billable | D15: Dev | E15: Emergency services form | F15: Waiting for Client Input | G15: 10 | H15: 15 | I15: 0 | J15: 5 | K15: 0
B16: DGDA | C16: Billable | D16: Dev | E16: Whatsapp integration | F16: Waiting for Client Input | G16: 0 | H16: 20 | I16: 0 | J16: 15 | K16: 0
B17: Farnborough Airshow | C17: Billable | D17: Live | E17: Event Task and Landing Page and forms | F17: Waiting for Client Input | G17: 0 | H17: 0 | I17: 10 | J17: 10 | K17: 20
B18: Internal Communication | C18: Non - Billable | D18: - | E18: Task Discussion,Team Call | F18: In Progress | G18: 5 | H18: 5 | I18: 0 | J18: 5 | K18: 5
F19: Weekly Utilization | G19: =SUM(G12:G18) -> 40 | H19: =SUM(H12:H18) -> 40 | I19: =SUM(I12:I18) -> 35 | J19: =SUM(J12:J18) -> 45 | K19: =SUM(K12:K18) -> 35
F20: Weekly Available | G20: =45-G19 -> 5 | H20: =45-H19 -> 5 | I20: =45-I19 -> 10 | J20: =45-J19 -> 0 | K20: =45-K19 -> 10
A23: Member | B23: Project | C23: Type | D23: Activity | E23: Task | F23: Status | G23: Week 1 | H23: Week 2 | I23: 5 | J23: Week 4 | K23: Week 5 | L23: Monthly Overall Utilization | M23: Monthly Available
B24: Adfactors | C24: Billable | D24: Live | E24: Home page and brand kit changes | F24: In Progress | G24: 12 | H24: 0 | I24: 0 | J24: 5 | K24: 0
A25: Parthiban | B25: Adfactors | C25: Billable | D25: Live | E25: Enchance Admin dashboard | F25: Not Started | G25: 0 | H25: 0 | J25: 0 | K25: 0 | L25: 120 | M25: 105
B26: Adfactors | C26: Billable | D26: Live | E26: Case Study-New Templete | F26: Not Started | G26: 0 | H26: 13 | I26: 0 | J26: 0 | K26: 0
B27: Adfactors | C27: Billable | D27: Live,staging | E27: Adfactors Chnages June | F27: Not Started | G27: 0 | H27: 5 | I27: 0 | J27: 20 | K27: 0
B28: Work Adfactors | C28: Billable | D28: Live | E28: Work Adfactors Staging and Live Restore and test all pages | F28: Not Started | G28: 0 | H28: 0 | I28: 25 | J28: 5 | K28: 10
B29: Adfactors | C29: Billable | D29: Live,staging | E29: Add Mention tag and get notfication for the Corresponding User after system generated post | F29: Not Started | G29: 0 | H29: 0 | I29: 0 | J29: 0 | K29: 5
B30: Internal Communication | C30: Non - Billable | D30: - | E30: Task Discussion,Team Call | F30: In Progress | G30: 5 | H30: 5 | I30: 5 | J30: 5 | K30: 5
F31: Weekly Utilization | G31: =SUM(G24:G30) -> 17 | H31: =SUM(H24:H30) -> 23 | I31: =SUM(I24:I28) -> 25 | J31: =SUM(J24:J30) -> 35 | K31: =SUM(K24:K30) -> 20
F32: Weekly Available | G32: =45-G31 -> 28 | H32: =45-H31 -> 22 | I32: =45-I31 -> 20 | J32: =45-J31 -> 10 | K32: =45-K31 -> 25
A34: Member | B34: Project | C34: Type | D34: Activity | E34: Task | F34: Status | G34: Week 1 | H34: Week 2 | I34: Week 3 | J34: Week 4 | K34: Week 5 | L34: Monthly Overall Utilization | M34: Monthly Available
A35: Rackesh | B35: DGDA | C35: Billable | D35: live | E35: Site cross testing & Form Testing | F35: In Progress | G35: 5 | H35: 5 | I35: 5 | J35: 5 | K35: 5 | L35: 195 | M35: 30
B36: Adfactors | C36: Billable | D36: live | E36: Site cross testing & Form Testing | F36: In Progress | G36: 5 | H36: 5 | I36: 5 | J36: 5 | K36: 5
B37: SEO Automation Tool | C37: Non - Billable | D37: Dev | E37: Make the frontend and backend setup and working in the login and signin/up functionality | F37: In Progress | G37: 20 | H37: 20 | I37: 20 | J37: 20 | K37: 20
B38: n8n automation | C38: Non - Billable | D38: local | E38: Learning and implementation to automate the process | F38: In Progress | G38: 2 | H38: 2 | I38: 2 | J38: 2 | K38: 2
B39: Internal Communication | C39: Non - Billable | D39: - | E39: Task Discussion,Team Call | F39: In Progress | G39: 5 | H39: 5 | I39: 5 | J39: 5 | K39: 5
B40: AEM | C40: Non - Billable | D40: live | E40: Learning and implementation | F40: In Progress | G40: 2 | H40: 2 | I40: 2 | J40: 2 | K40: 2
B41: adfactors | C41: Billable | D41: live | E41: phase 2 changes | F41: In Progress | G41: 0 | H41: 0 | I41: 0 | J41: 0 | K41: 0
F42: Weekly Utilization | G42: 39 | H42: 39 | I42: 39 | J42: 39 | K42: 39
F43: Weekly Available | G43: 6 | H43: 6 | I43: 6 | J43: 6 | K43: 6
A46: Member | B46: Project | C46: Type | D46: Activity | E46: Task | F46: Status | G46: Week 1 | H46: Week 2 | I46: Week 3 | J46: Week 4 | K46: Week 5 | L46: Monthly Overall Utilization | M46: Monthly Available
A47: Moswin | B47: SEO Automation | C47: Non - Billable | D47: Dev | E47: Roadmap planning + N8n UI Build | F47: In Progress | G47: 10 | H47: 10 | I47: 10 | J47: 0 | K47: 0 | L47: =G56+H56+I56+J56+K56 -> 207 | M47: =G57+H57+I57+J57+K57 -> 18
B49: SEO Automation | C49: Non - Billable | D49: Live | E49: Competitor analysis | F49: In Progress | G49: 35 | H49: 5 | I49: 0 | J49: 0 | K49: 0
B50: SEO Automation | C50: Non - Billable | D50: Live | E50: Backllink Monitoring | F50: Not Started | G50: 0 | H50: 25 | I50: 5 | J50: 0 | K50: 0
B51: Vajra Product Applications Monitoring. | C51: Non - Billable | D51: Live | E51: Monitoring set up with external tools for all our Internal projects. | F51: Not Started | G51: 0 | H51: 0 | I51: 25 | J51: 5 | K51: 0
B52: DGDA Monitoing | C52: Billable | D52: Live | E52: DGDA Monitoing | F52: In Progress | G52: 2 | H52: 2 | I52: 2 | J52: 2 | K52: 2
B53: Maintain and backup Client cloud cluster data base. | C53: Non - Billable | D53: Live | E53: https://clients.cloudclusters.io/ understanding and set up backup. | F53: Not Started | G53: 0 | H53: 0 | I53: 2 | J53: 20 | K53: 0
B54: SEO Automation | C54: Non - Billable | D54: Live | E54: Indexing Status | F54: Not Started | G54: 0 | H54: 0 | I54: 0 | J54: 15 | K54: 10
B55: SEO Automation | C55: Non - Billable | D55: Live | E55: Keyword Research | F55: Not Started | G55: 0 | H55: 0 | I55: 0 | J55: 0 | K55: 20
F56: Weekly Utilization | G56: 47 | H56: 42 | I56: 44 | J56: 42 | K56: 32
F57: Weekly Available | G57: =45-G56 -> -2 | H57: =45-H56 -> 3 | I57: =45-I56 -> 1 | J57: =45-J56 -> 3 | K57: =45-K56 -> 13

Sheet Internal Tracker Sub 2026
A1: Project Name | B1: Main Task Name | C1: Ticket Id | D1: Task | E1: Priority | F1: S Date | G1: E Date | H1: Assigned to | I1: Status | J1: Env | K1: As Per WO | L1: Efforts | M1: Actual Efforts | N1: Informed | O1: Support Needed / Blocker | P1: Dependency Detail | Q1: Page Url | R1: Mail Subject | S1: Internal Mail Subject
A2: www.vajraglobal.com/ | B2: Umbraco sites Pitch | D2: Targeting Legacy Umbraco 7,8,9 & 10 Sites | E2: Low | F2: 46028 | G2: 46028 | H2: Sowndar | I2: Completed | J2: Production | L2: 0 | M2: 0
A3: www.vajraglobal.com/ | B3: Umbraco sites Pitch | D3: Targeting Legacy Umbraco 7,8,9 & 10 Sites | E3: Low | F3: 46065 | G3: 46065 | H3: Sowndar | I3: Completed | J3: Production | L3: 0 | M3: 0
B4: Updated Updated SEO Automation BRD BRD | D4: Updated Updated SEO Automation BRD BRD | L4: 0 | M4: 0
A5: vajraglobal.com | B5: Review High CPU Usage | D5: Server Inventory | E5: Low | F5: 46101 | G5: 46101 | H5: Moswin | I5: In Progress | J5: Production | L5: 0 | M5: 0
B6: Server Inventory | D6: Migration of MarketingOps frontent and backend, DB to the new server is done. Frontend and backend health is working. There are some application connection issues in there. Will work with Boopesh to chck on that today. | E6: Medium | F6: 46094 | G6: 46094 | H6: Moswin | I6: Completed | J6: Production | L6: 6 | M6: 0
B7: Updated SEO Automation BRD | D7: Competitor analysis started working as discussed. but the project api which we are using wasnt able to fetch the output that we required. So need to find an alternate method. | E7: Low | F7: 46097 | G7: 46097 | H7: Moswin | I7: Completed | J7: Production | L7: 3 | M7: 0
B8: Updated SEO Automation BRD | C8: 19-Mar-2026-1 | D8: Alt text workflow phase 1 completed and shared with valli and team for validation. | E8: Low | F8: 46100 | G8: 46100 | H8: Moswin | I8: Completed | J8: Production | L8: 9 | M8: 0
B9: Updated SEO Automation BRD | C9: 19-Mar-2026-2 | D9: 2 improvements on 19-Mar-2026-1 completed | E9: Low | F9: 46104 | G9: 46104 | H9: Moswin | I9: Completed | J9: Production | L9: 6 | M9: 0 | O9: Following our review, we've made two improvements: Alt Text Quality — The generated alt texts were too generic. We've refined the prompt by providing context from the article title, page context, and the image itself and after reviewing the latest outputs, the quality now meets our expectations. Image Filtering — A number of images being pulled were standalone assets not attached to any articles. We've updated the workflow to skip these entirely, so only relevant article images are processed.
B10: Server Inventory | D10: Snapshot of the server taken, and decommisioned the server. Server and projects were monitored for the last 5 days. | E10: Medium | F10: 46104 | G10: 46104 | H10: Moswin | I10: Completed | J10: Production | L10: 2 | M10: 0 | O10: Everything looks stable and normal. We have taken a backup snapshot of the server and decommissioned it. The snapshot will be retained for the next 5 days as a safety net before deletion. Additionally, I believe we have an opportunity to reduce one more server by consolidating and redistributing some projects. I will discuss this with Sunder Sir and come back with a plan tomorrow.
B11: AstonBrooke local environment set up. | D11: For Aston Brooke set up the private key files in Kushall's laptop and have provided the updated commands to move the backend project into the server. | E11: Medium | F11: 46101 | G11: 46101 | H11: Moswin | I11: Completed | J11: Production | L11: 1 | M11: 0
B12: AstonBrooke local environment set up. | D12: FTP set up done for AB in Kushall's laptop for Filezilla | E12: Medium | F12: 46105 | G12: 46105 | H12: Moswin | I12: Completed | J12: Production | L12: 2 | M12: 0
B13: Kreab billing invoice | D13: Kreab billing cycle invoice fetch from AWS and sent to accounts team. MFA was with Ram so had to get it from him and further have changed it my device for future purposes | E13: Medium | F13: 46105 | G13: 46105 | H13: Moswin | I13: Completed | J13: Production | L13: 2 | M13: 0
B14: Server Inventory | D14: Backup plan and cost sheet has been prepared ( | E14: Medium | F14: 46105 | G14: 46105 | H14: Moswin | I14: Completed | J14: Production | L14: 2 | M14: 0
A15: https://automation.vajraglobal.com/ | B15: Updated SEO Automation BRD | D15: Alt text Phase 2 - Pause mechanism planned and how we can get validation and update only the ones that are approved have been finalized with Valli. Initiall set up has also been started | E15: Medium | F15: 46105 | G15: 46105 | H15: Moswin | I15: Completed | J15: Production | L15: 2 | M15: 0
A16: https://automation.vajraglobal.com/ | B16: Updated SEO Automation BRD | D16: Have completed Alt text end to end. ( 7 hours) Phase 1 : from collecting missing alt texts information with the details. Phase 2 : generating alt texts and confirming approval from the SEO team. Phase 3 : Inject only the approved alt texts in the site. Pending : Need to plan with valli for creating a button to initiate the workflow externally. | F16: 46106 | G16: 46106 | H16: Moswin | I16: Completed | J16: Production | L16: 7 | M16: 0
A17: https://msmehealthengine.fametn.com/ | B17: MSME | D17: Working with Bboopesh on MSME for creation of super admin user, docker issues, setting up in a way that another repo can also move the backend to the same server | F17: 46106 | G17: 46106 | H17: Moswin | I17: Completed | J17: Production | L17: 2 | M17: 0
A18: https://msmehealthengine.fametn.com/ | B18: MSME | D18: MSME super admin user issues resolved and moved the code to staging. | F18: 46107 | G18: 46107 | H18: Moswin | I18: Completed | J18: Production | L18: 3 | M18: 0
A19: https://automation.vajraglobal.com/ | B19: Updated SEO Automation BRD | D19: ALT text - Need to plan with valli for creating a button to initiate the workflow externally. Button trigger for both the workflows through webhooks created new issues. All resolved and now everything is ready. | F19: 46107 | G19: 46107 | H19: Moswin | I19: Completed | J19: Production | L19: 5 | M19: 0
A20: vajraglobal.com | B20: Server Inventory | D20: 1C2GB-N8n.monitoringTools.ContentPubWDS-LIVE server clean up activity done brining down the space from 42 GB to 29 GB saving cost for backing up and potentially move project too in there. | F20: 46107 | G20: 46107 | H20: Moswin | I20: Completed | J20: Production | L20: 2 | M20: 0
A21: vajraglobal.com | B21: Server Inventory | D21: 2C4GB-Intranet.Kreab.thoughtleadership-STAGING storage brought down from 43 to 26 GB by doing some housekeeping activities and clearing old images, and logs. | F21: 46108 | G21: 46108 | H21: Moswin | I21: Completed | J21: Production | L21: 3 | M21: 0
A22: vajraglobal.com | B22: Server Inventory | D22: backups set up for all servers. Plan and cost estimation sheet is also done Server Inventory - Vajra | F22: 46108 | G22: 46108 | H22: Moswin | I22: Completed | J22: Production | L22: 2 | M22: 0
A23: vajraglobal.com | B23: Server Inventory | D23: Alerts and monitoring for all servers is also set up in Digital ocean | F23: 46108 | G23: 46108 | H23: Moswin | I23: Completed | J23: Production | L23: 2 | M23: 0
A24: https://astonbrooke.co.uk/ | B24: Aston Brooke | D24: Aston Brooke nginix set up call with Kushall | F24: 46111 | G24: 46111 | H24: Moswin | I24: Completed | J24: Production | L24: 2 | M24: 0
A25: https://automation.vajraglobal.com/ | B25: Updated SEO Automation BRD | D25: Tracking code and robots.txt failed due to too many requests in Excel. Have set up service accounts for them and it's working now. | F25: 46111 | G25: 46111 | H25: Moswin | I25: Completed | J25: Production | L25: 2 | M25: 0
A26: https://msmehealthengine.fametn.com/ | B26: MSME | D26: msme backend changes moved to staging - worked with Bboopesh | F26: 46111 | G26: 46111 | H26: Moswin | I26: Completed | J26: Production | L26: 2 | M26: 0
A27: https://automation.vajraglobal.com/ | B27: Updated SEO Automation BRD | D27: Alt text have set up so that credentials are taken in dynamically and used in the workflows as per the project | F27: 46111 | G27: 46111 | H27: Moswin | I27: Completed | J27: Production | L27: 4 | M27: 0
... A40: vajraglobal.com | B40: DevOps as a Service (DaaS) | D40: Prepare sales pitch required details to Sriram sir for DevOps as a Service(DaaS) https://docs.google.com/spreadsheets/d/1VcZ3dgg0Ass8GliDR3zhezHmsi_LzdkC/edit?usp=sharing&ouid=108220845174973423951&rtpof=true&sd=true | F40: 46119 | G40: 46120 | H40: Moswin | I40: Completed | J40: Production | L40: 3 | M40: 0
A41: vajraglobal.com | B41: Updated SEO Automation BRD | D41: Internal Links - Have set up credentials and fetching all pages with pagination steps are done. | F41: 46120 | G41: 46120 | H41: Moswin | I41: Completed | J41: Production
A42: vajraglobal.com | B42: Internal links | D42: Internal links | F42: 46121 | G42: 46129 | H42: Moswin | I42: In Progress | J42: Local | L42: 90 | O42: 50 % completed.
A43: vajraglobal.com | B43: Internal links | D43: Workflow architecture plan | F43: 46120 | G43: 46120 | H43: Moswin | I43: Completed | J43: Local | L43: 3
A44: vajraglobal.com | B44: Internal links | D44: Google Sheet approval schema | F44: 46120 | G44: 46120 | H44: Moswin | I44: Completed | J44: Local | L44: 3
A45: vajraglobal.com | B45: Internal links | D45: N8N WP credentials setup | F45: 46120 | G45: 46120 | H45: Moswin | I45: Completed | J45: Local | L45: 3
A46: vajraglobal.com | B46: Internal links | D46: Phase 1 — Crawl workflow | F46: 46121 | G46: 46121 | H46: Moswin | I46: Completed | J46: Local | L46: 3
A47: vajraglobal.com | B47: Internal links | D47: Phase 1 — OpenAI suggestion engine | F47: 46121 | G47: 46121 | H47: Moswin | I47: Completed | J47: Local | L47: 3
A48: vajraglobal.com | B48: Internal links | D48: Phase 1 — dry run on 5 posts | F48: 46121 | G48: 46121 | H48: Moswin | I48: Completed | J48: Local | L48: 3
A49: vajraglobal.com | B49: Internal links | D49: Phase 1 - Improvements. Generate source, target, anchor text, paragraph context, insertion text for the eligible high confidence interlinks. | F49: 46122 | G49: 46122 | H49: Moswin | I49: Completed | J49: Local | L49: 5
A50: www.vajraglobal.com/ | B50: Server Inventory | D50: Route traffic of 3 applications to their respective updated server machines. | F50: 46120 | G50: 46122 | H50: Moswin | I50: Completed | J50: Production | L50: 2 | M50: 5
A51: vajraglobal.com | B51: Internal links | D51: Phase 1 - Fixes pending. Remove duplicates, EMPTY / INVALID ITEMS with low confidence, improve ANCHOR TEXT QUALITY, handle SYMMETRICAL LINKS | F51: 46122 | G51: 46125 | H51: Moswin | I51: Completed | J51: Local | L51: 8 | M51: 12 | O51: Outputs for all pages received as expected,
A52: vajraglobal.com | B52: Internal links | D52: Generated values of keywords topic id title url slug excerpt content_short content_full source_url target_url anchor_text insertion_text row_type reason confidence decision edited_anchor edited_insertion status fetched and updated in sheet properly with the multiple suggestion logic. | F52: 46126 | G52: 46126 | H52: Moswin | I52: Completed | J52: Local | L52: 6 | M52: 6 | O52: Completed. added new coloumn for the suggestions so the seo team can singularly select only those to approve.
A53: vajraglobal.com | B53: Internal links | D53: Read final sheet, prepare inject content, extract post content , prepare and inject only if approved , update in sheet the status. | F53: 46127 | G53: 46127 | H53: Moswin | I53: Completed | J53: Local | L53: 6 | M53: 6 | O53: Completed with this too. some inputs mismatatched which led to some issues. that took some time to troubleshoot.. Pending: Get approval from Naresh and do a test run in staging wordpress sites.
A54: vajraglobal.com | B54: DevOps as a Service (DaaS) | D54: Research Upwork and LinkedIn, find similar profiles and share with Sriram Sir with details of what all we can do like that. | F54: 46127 | G54: 46129 | H54: Moswin | I54: Completed | J54: Local | L54: 2 | M54: 2 | O54: Comment: Upwork_DevOps_research.xlsx Created a profile in upwork and research the kind of jobs we can do. and found some other freelancers by loggin in hiring mode. and fetched some people who do something like this full time and have good rating. LinkedIn will do tomorrow.
A56: https://msmehealthengine.fametn.com/ | B56: MSME | D56: N8n workflow to fetch and provide invalid(non-deliverable) emails out of the list. | F56: 46129 | G56: 46129 | H56: Moswin | I56: Completed | J56: Production | L56: 6 | M56: 6
A57: https://msmehealthengine.fametn.com/ | B57: MSME | D57: 1. Plan how we can set up filters on top of AWS SES to find bounce back mails. 2. Send client with steps needed to be done. | F57: 46132 | G57: 46132 | H57: Moswin | I57: Completed | J57: Local | L57: 5 | M57: 5
A58: vajraglobal.com | B58: Server Inventory | D58: Nginx set up, SSL cert set up, IP pointing done. One application has issues, have shared it with the dev team. | H58: Moswin | I58: Completed | L58: 4 | M58: 4 | O58: With the dev team for troubleshooting issues in backend.
A59: vajraglobal.com | B59: Updated SEO Automation BRD | D59: 1. Prepare new data and keep it ready for Demo with Valli 2. Collect data on time saved information. 3. Complete demo call | F59: 46133 | G59: 46133 | H59: Moswin | I59: Completed | J59: Local | L59: 6 | M59: 6
A60: vajraglobal.com | B60: DevOps Vajra Voyage | D60: "System Stability post Go-Live ≥ 98%" this means all servers should be up and running. if something goes wrong we need a plan to recover and be back up and running without any data lose. I need to detail plan for this. Also for all applications should be running and that also needs to be tracked regularly. if it goes down, how to bring them up and running. We need document for all applications | F60: 46129 | G60: 46134 | H60: Moswin | I60: Completed | J60: Local | L60: 8 | M60: 8 | O60: https://docs.google.com/document/d/1KHg8muxaUMm2emsl9NOzYrZwD9Nzd7dR/edit?usp=sharing&ouid=108220845174973423951&rtpof=true&sd=true
A61: https://msmehealthengine.fametn.com/ | B61: MSME | D61: Discussion call with Kiruba, Thamil and Bboopesh on the bounce back mail alternatives. Corrections has been done and moved to live for testing. Pritunl issue in Bboopesh laptop, cant find the rootcause. Running it temporarily in my laptop | F61: 46133 | G61: 46133 | H61: Moswin | I61: Completed | J61: Staging | L61: 3 | M61: 3
A62: https://msmehealthengine.fametn.com/ | B62: MSME | D62: Mail otp expiry is 2 mins in code. But is 10 mins by default. Figure out a way to reduce to 2 mins using aws. | F62: 46136 | G62: 46136 | H62: Moswin | I62: Completed | J62: Production
A63: vajraglobal.com | B63: Server Inventory | D63: Delete Droplet | F63: 46136 | G63: 46136 | H63: Moswin | I63: Completed | J63: Production
A64: vajraglobal.com | B64: Internal links | D64: Ui buttons for generation and Inject procedure. | F64: 46136 | G64: 46136 | H64: Moswin | I64: Completed | J64: Production
A65: vajraglobal.com | B65: Server Inventory | D65: For all our applications set up uptime monitoring for health endpoint api. | F65: 46139 | G65: 46141 | H65: Moswin | I65: Completed | J65: Production | L65: 4 | P65: need health enpoints from the dev team. or ask them to set up end points then.
A66: vajraglobal.com | B66: Server Inventory | D66: Analyse best monitoring tool we can set up for the error logs define thresholds and set up proper mailing system for increased error from specific applications and provide details to Sunder Sir | F66: 46139 | G66: 46139 | H66: Moswin | I66: Completed | J66: Production | O66: Grafana + Loki + Promtail | P66: need dev team to set up logs. send mail to the team.
A67: vajraglobal.com | B67: Updated SEO Automation BRD | D67: Prepare FRD for SEO Automation | F67: 46140 | G67: 46141 | H67: Moswin | I67: Completed | L67: 4
A68: vajraglobal.com | B68: Updated SEO Automation BRD | D68: Discussion with Kiruba for UI set for SEO Automation. | F68: 46140 | G68: 46140 | H68: Moswin | I68: Completed | L68: 3 | M68: 3
A69: vajraglobal.com | B69: Updated SEO Automation BRD | D69: Preparation and Discussion with Valli and Balaji for UI set up for SEO Automation. | F69: 46141 | G69: 46141 | H69: Moswin | I69: Completed | L69: 2
A70: vajraglobal.com | B70: Server Inventory | D70: Client CloudClusters understanding and backup set up. | F70: 46140 | G70: 46141 | H70: Moswin | I70: Completed | L70: 6 | P70: Have responded to G sir and Sunder Sir queries. Need approval from sir for the cost, post that will enable db backups.
A71: vajraglobal.com | B71: Updated SEO Automation BRD | D71: demo video send for alt text for context for balaji | F71: 46142 | G71: 46172 | H71: Moswin | I71: Completed
A72: vajraglobal.com | B72: Goal towards 99.99% availability | D72: tech team applications uptime monitoring set up for their end points | F72: 46142 | G72: 46142 | H72: Moswin | I72: Completed | J72: Production
A73: vajraglobal.com | B73: Goal towards 99.99% availability | D73: Mail send for error logs set up and mail to Sriram sir with all the documents and data required. | F73: 46142 | G73: 46142 | H73: Moswin | I73: Completed | J73: Production
A74: vajraglobal.com | B74: ?? | D74: Hi Moswin, can you read on this topic and explain to me. no time pressure. take you own time. but we need to understand this in detail. https://www.linkedin.com/posts/leadgenmanthan_claude-code-can-now-run-any-cli-for-you-activity-7453738322599763968--WZH | F74: 46146 | G74: 46147 | H74: Moswin | I74: Completed | J74: Production | L74: 6 | M74: 8 | P74: Completed on my end, Sir told he will get back when he is available.
A75: vajraglobal.com | B75: Updated SEO Automation BRD | D75: Prepare Road map / demo / discussion with Valli on the same. | F75: 46146 | G75: 46146 | H75: Moswin | I75: Completed | J75: Production
A76: vajraglobal.com | B76: DevOps as a Service (DaaS) | D76: Devops as a service sales team discussion this week with Sriram Sir | F76: 46147 | G76: 46148 | H76: Moswin | I76: Completed | J76: Production
A77: vajraglobal.com | B77: CI/CD | D77: Testing for all CICD workflows in Hellowiz and corrections for the same | F77: 46153 | G77: 46153 | H77: Moswin | I77: Completed | J77: Production
A78: vajraglobal.com | B78: Updated SEO Automation BRD | D78: Alt text generation for Vachi HR - Staging | F78: 46153 | G78: 46155 | H78: Moswin | I78: Completed | J78: Production | L78: 6 | M78: 6
A79: vajraglobal.com | B79: Updated SEO Automation BRD | D79: Alt text generation for Vachi HR - Live | F79: 46156 | G79: 46160 | H79: Moswin | I79: Completed | J79: Production | L79: 8 | M79: 8
A80: vajraglobal.com | B80: DevOps as a Service (DaaS) | D80: LinkedIn Optimization for devops visibility | F80: 46155 | G80: 46156 | H80: Moswin | I80: Completed | J80: Production | L80: 4 | M80: 4 | Q80: https://www.linkedin.com/posts/moswin_aws-eks-kubernetes-activity-7462126509927927808--uMs?utm_source=share&utm_medium=member_desktop&rcm=ACoAACoz00YBMtL992VJP8rD2-2VhlT-0tzwdTs
A81: https://msmehealthengine.fametn.com/ | B81: MSME | D81: MSME live moving and testing | F81: 46156 | G81: 46157 | H81: Moswin | I81: Completed | J81: Production | L81: 2 | M81: 2
B82: Thought leadership developement | D82: Thought leadership project set up and run | F82: 46160 | G82: 46162 | H82: Moswin | I82: Completed | J82: Production | L82: 12 | M82: 12
B83: Thought leadership developement | D83: 1. Gradle version 2. Missing packages install 3. Missing dependencies install | F83: 46163 | G83: 46163 | H83: Moswin | I83: Completed | J83: Production | L83: 6 | M83: 6
B84: Thought leadership developement | D84: Identify firebase and include Device SHA code | F84: 46164 | G84: 46164 | H84: Moswin | I84: On Hold / Blocked | J84: Local | L84: 3
A85: vajraglobal.com | B85: Goal towards 99.99% availability | D85: Internal monitoring and alert set up with error logs planning and tool identification | F85: 46157 | G85: 46157 | H85: Moswin | I85: Completed | L85: 2 | M85: 2
A86: vajraglobal.com | B86: neo4j implementation + deployment | D86: Learn + understand neo4j | F86: 46163 | G86: 46169 | H86: Moswin | I86: Completed | J86: Local | L86: 15 | M86: 8
A87: vajraglobal.com | B87: Backlink call with Padma | F87: 46164 | G87: 46164 | H87: Moswin | I87: Completed | J87: Local | L87: 1 | M87: 1
A88: vajraglobal.com | B88: Updated SEO Automation BRD | D88: Vachi live Alt text insertion | F88: 46163 | G88: 46169 | H88: Moswin | I88: Completed | J88: Production | L88: 2 | M88: 2
A89: vajraglobal.com | B89: CI/CD | D89: Hello Wiz - WIzard Staging + Production CICD Pipeline | F89: 46148 | G89: 46149 | H89: Moswin | I89: Under Review & Testing | J89: Local | L89: 0.5 | O89: Have built and set up pipelines for each project. Will push into the repository as a maintainance activity on third week of June. | P89: Dev team to test the workflow and client approval to go ahead with this implementation
A90: vajraglobal.com | B90: CI/CD | D90: Hello Wiz - Admin Staging + Production CICD Pipeline | F90: 46148 | G90: 46149 | H90: Moswin | I90: Under Review & Testing | J90: Local | L90: 0.5 | O90: Have built and set up pipelines for each project. Will push into the repository as a maintainance activity on third week of June. | P90: Dev team to test the workflow and client approval to go ahead with this implementation
A91: vajraglobal.com | B91: CI/CD | D91: Hello Wiz - Client Staging + Production CICD Pipeline | F91: 46148 | G91: 46149 | H91: Moswin | I91: Under Review & Testing | J91: Local | L91: 0.5 | O91: Have built and set up pipelines for each project. Will push into the repository as a maintainance activity on third week of June. | P91: Dev team to test the workflow and client approval to go ahead with this implementation
A92: vajraglobal.com | B92: CI/CD | D92: Hello Wiz - Backend Staging + Production CICD Pipeline | F92: 46148 | G92: 46149 | H92: Moswin | I92: Under Review & Testing | J92: Local | L92: 0.5 | O92: Have built and set up pipelines for each project. Will push into the repository as a maintainance activity on third week of June. | P92: Dev team to test the workflow and client approval to go ahead with this implementation
A93: automation.vajraglobal.com | B93: Updated SEO Automation BRD | D93: Backlink Monitoring | F93: 46163 | G93: 46170 | H93: Moswin | I93: In Progress | J93: Local | L93: 6 | O93: Done with the requirement build and corrections. | P93: Need full list of backlinks targets urls and project urls so we can set this up for those and follow that
A94: vajraglobal.com | B94: Updated SEO Automation BRD | D94: Plan and document neo4j hosting options and cost and set up for clients documentation | F94: 46170 | G94: 46176 | H94: Moswin | I94: In Progress | J94: Local | L94: 8
A95: vajraglobal.com | B95: neo4j implementation + deployment | D95: neo4j infra set up for clients plan with cloud self managed or server on prem hosting plan and cost split No due date | F95: 46178 | G95: 46178 | H95: Moswin | I95: Pipeline / To Do | J95: Local | L95: 5
A96: vajraglobal.com | B96: Updated SEO Automation BRD | D96: Monitoring and alert set up in all servers as proposed | F96: 46170 | G96: 46176 | H96: Moswin | I96: Pipeline / To Do | J96: Local | L96: 8
A97: vajraglobal.com | B97: Updated SEO Automation BRD | D97: Review + decision call and mail convo close with Padma and Valli | F97: 46171 | G97: 46171 | I97: Completed
A98: vajraglobal.com | B98: Updated SEO Automation BRD | D98: Make the changes in backlink. | F98: 46171 | G98: 46171 | I98: In Progress
B99: Kreab developement | D99: Set up frontend ,backend and understand code | F99: 46171 | G99: 46174 | I99: Completed
A100: vajraglobal.com | D100: Share 30/60 days plan with G sir. | F100: 46171 | G100: 46171
A101: vajraglobal.com | D101: Backlink Monitoring- changes from Padma | F101: 46175 | G101: 46175 | L101: 4
A106: automation.vajraglobal.com | B106: Updated SEO Automation BRD | D106: Competitor Analysis | F106: 46142 | G106: 46150 | H106: Moswin | I106: Pipeline / To Do | J106: Local
A107: automation.vajraglobal.com | B107: Updated SEO Automation BRD | D107: Indexing Status | G107: 46150 | H107: Moswin | I107: Pipeline / To Do | J107: Local
A108: automation.vajraglobal.com | B108: Updated SEO Automation BRD | D108: Keyword Research | H108: Moswin | I108: Pipeline / To Do | J108: Local

Sheet DGDA GitHub
A1: S.No | B1: From | C1: To | D1: Date | E1: Available | F1: Description
A2: 1 | B2: Feat/Seo | C2: Main | D2: 20-08-2025 | E2: Deleted | F2: Move The Changes
A3: 2 | B3: Main | C3: feat/water-dispenser-latest | D3: 28-08-2025 | F3: Take a Backup
A4: 3 | B4: feat/water-dispenser-latest | C4: Main | D4: 45697 | E4: Deleted
A5: 4 | B5: sapc4cintegration | C5: feat/datareq | D5: 45756 | E5: Deleted | F5: Due to conflict
A6: 5 | B6: feat/datareq | C6: Main | D6: 45939
A7: 6 | B7: Main | C7: feat/dalstudent | D7: 45970
A8: 7 | B8: feat/dalstudent | C8: Main | E8: Deleted | F8: Remove 'dgdaGeneralEnquiry','dgdaFeedback', 'dgdaComplaints', On C4C
A9: 8 | B9: feat/dalstudent | C9: Main | D9: 45912 | E9: Deleted | F9: Move the water dispenser sponsors logo fix
A10: 9 | B10: Main | C10: Release | D10: 45912 | F10: C4C Water Pen Testing Changes
A11: 10 | B11: feat/dalstudent | C11: Main | D11: 45917 | E11: Deleted | F11: Terraform Code Update
A12: 11 | B12: feat/saudi-national-day | C12: Main | D12: 45918 | E12: Deleted | F12: Test if it is working or not
A13: 12 | B13: feat/saudi-national-day | C13: Main | D13: 45919 | E13: Deleted
A14: 13 | B14: main | C14: release/dgda | D14: 45920
A15: 14 | B15: main | C15: release/dgda | D15: 45921 | F15: National Day Page move to Production
A16: 15 | B16: feat/saudi-national-day | C16: Main | D16: 45922 | E16: Deleted | F16: National Day Page Fonts update
A17: 16 | B17: Main | C17: release/dgda | D17: 45922 | E17: Deleted | F17: National Day Page Fonts update
A18: 17 | B18: feat/al-masar-program | C18: Main | D18: 45931 | F18: Al Masar Program Page Development and lint error fix
A19: 18 | B19: feat/feat-school-fixed | C19: Main | D19: 45937 | F19: School Visit form student condtion fix
A20: 19 | B20: Main | C20: release/dgda | D20: 45938 | F20: School Visit form student condtion fix
A21: 20 | B21: feat/CTProgram | C21: Main | D21: 45943 | F21: Curatorial Training Program Page
A22: 21 | B22: feat/CTProgram | C22: Main | D22: 45946 | F22: Form Language Fix
A23: 22 | B23: Main | C23: release/dgda | D23: 45946 | F23: Form Language Fix
A24: 23 | B24: feat/CTProgram | C24: Main | D24: 45952 | F24: video library Page code uncomment and move it to main
A25: 24 | B25: Main | C25: release/dgda | D25: 45952 | F25: video library Page code uncomment and move it to live
A26: 25 | B26: feat/CTProgram | C26: Main | D26: 45959 | F26: Royal Golf Club Hiring Opportunity form add to C4C Bab Samhan Hiring Opportunity Survey form add to C4C
A27: 26 | B27: feat/CTProgram | C27: Main | D27: 45960 | F27: School Visit Form Grade Validation Fix
A28: 27 | B28: Main | C28: release/dgda | D28: 45960 | F28: School Visit Form Grade Validation Fix
A29: 28 | B29: feat/CTProgram | C29: Main | D29: 45968 | F29: Move the Water Dispenser Form Intrest Type code to Staging
... A32: 31 | B32: Main | C32: release/dgda | D32: 45971 | F32: Water Dispenser CTA Target Fix move to live
A33: 32 | B33: feat/CTProgram | C33: Main | D33: 17-11-2025 | F33: CT Program
A34: 33 | B34: Main | C34: release/dgda | D34: 17-11-2025 | F34: CT Program
A35: 34 | B35: feat/CTProgram | C35: Main | D35: 18-11-2025 | F35: Fix the Category
A36: 35 | B36: Main | C36: release/dgda | D36: 18-11-2025 | F36: Fix the Category
A37: 36 | B37: feat/CTProgram | C37: Main | D37: 24-11-2025 | F37: banner video responsive fix
A38: 37 | B38: Main | C38: release/dgda | D38: 24-11-2025 | F38: banner video responsive fix
A39: 38 | B39: feat/CTProgram | C39: Main | D39: 28-11-2025 | F39: Phone Number Validation after user remove the data Fix the validaion in coding
A40: 39 | B40: feat/CTProgram | C40: Main | D40: 45669 | F40: Date picker not working on single click fix on DGDA and remove the special chacter on the some of the form input id
A41: 40 | B41: Main | C41: release/dgda | D41: 45669 | F41: Date picker not working on single click fix on DGDA and remove the special chacter on the some of the form input id
A42: 41 | B42: feat/CTProgram | C42: Main | D42: 45728 | F42: Form Empty Value fix for mail template
A43: 42 | B43: Main | C43: release/dgda | D43: 45728 | F43: Form Empty Value fix for mail template
A44: 43 | B44: feat/CTProgram | C44: Main | D44: 45789 | F44: Dummy Push for variable update - Moswin
A45: 44 | B45: Main | C45: release/dgda | D45: 45789 | F45: Dummy Push for variable update - Moswin
A46: 45 | B46: feat/CTProgram | C46: Main | D46: 45942 | F46: Googe Tag Manager Tracking - Sowndar
A47: 46 | B47: Main | C47: release/dgda | D47: 45789 | F47: Dummy Push for variable update - Moswin
A48: 47 | B48: feat/version-update | C48: Main | D48: 18-12-2025 | F48: Version Upudate from 14.2.25 to 15.5.9
A49: 48 | B49: Main | C49: release/dgda | D49: 23-12-2025 | F49: Version Upudate from 14.2.25 to 15.5.9
A50: 49 | B50: feat/version-update | C50: Main | D50: 26-12-2025 | F50: UMA Forms Type Add
A51: 50 | B51: feat/version-update | C51: Main | D51: 29-12-2025 | F51: Register Number Logic
A52: 51 | B52: Main | C52: release/dgda | D52: 29-12-2025 | F52: Register Number Logic
A53: 52 | B53: feat/version-update | C53: Main | D53: 46056 | F53: Forms payload duplicate fix
A54: 53 | B54: Main | C54: release/dgda | D54: 46085 | F54: Forms payload duplicate fix
A55: 54 | B55: feat/version-update | C55: Main | D55: 46062 | F55: Leadership Components
A56: 55 | B56: feat/version-update | C56: Main | D56: 46064 | F56: Leadership Components Text Alignment
A57: 56 | B57: feat/version-update | C57: Main | D57: 46065 | F57: Leadership Components Text Alignment in Arabic
A58: 57 | B58: feat/version-update | C58: Main | D58: 46066 | F58: CTA and Header Tracking Code Update
A59: 58 | B59: Main | C59: release/dgda | D59: 46077 | F59: Leadership Components (HRH) Text Alignment fix in coding and CEO Message Design Moved to Production
A60: 59 | B60: feat/finding-details | C60: Main | D60: 46184 | F60: Move the Founding Details Single Page
A61: 60 | B61: Main | C61: release/dgda | D61: 46185 | F61: Move the Founding Details Single Page

Sheet DGS GitHub
A1: S.No | B1: From | C1: To | D1: Date | E1: Available | F1: Description
A2: 1 | B2: dev/DGS | C2: Main | D2: 19-11-2025 | F2: Add the Target on the hedaer button
A3: 2 | B3: Main | C3: release/dgs | D3: 19-11-2025 | F3: Add the Target on the hedaer button
A4: 3 | B4: dev/DGS | C4: Main | D4: 19-11-2025 | F4: Header Item Align right
A5: 4 | B5: Main | C5: release/dgs | D5: 19-11-2025 | F5: Header Item Align right
A6: 5 | B6: dev/DGS | C6: Main | D6: 27-11-2025 | F6: OG Image - Moswin
A7: 6 | B7: Main | C7: release/dgs | D7: 27-11-2025 | F7: OG Image - Moswin
A8: 7 | B8: dev/DGS | C8: Main | D8: 28-11-2025 | F8: Phone Number Validation after user remove the data Fix the validaion in coding
A9: 8 | B9: Main | C9: release/dgs | D9: 28-11-2025 | F9: Phone Number Validation after user remove the data Fix the validaion in coding
A10: 9 | B10: Main | C10: Main | D10: 45669 | F10: Date picker not working on single click fix on DGS and remove the special chacter on the some of the form input id
A11: 10 | B11: dev/DGS | C11: release/dgs | D11: 45669 | F11: Date picker not working on single click fix on DGS and remove the special chacter on the some of the form input id
A12: 11 | B12: dev/DGS | C12: Main | D12: 45669 | F12: Recaptcha fix - Moswin
A13: 12 | B13: Main | C13: release/dgs | D13: 45669 | F13: Recaptcha fix - Moswin
A14: 13 | B14: dev/DGS | C14: Main | D14: 45669 | F14: Speaker Page categories issue Fix
A15: 14 | B15: Main | C15: release/dgs | D15: 45669 | F15: Speaker Page categories issue Fix
A16: 15 | B16: dev/DGS | C16: Main | D16: 45728 | F16: Form Empty Value fix for mail template
A17: 16 | B17: Main | C17: release/dgs | D17: 45728 | F17: Form Empty Value fix for mail template
A18: 17 | B18: dev/DGS | C18: Main | D18: 45759 | F18: Dummy Push for Variable Update - Moswin
A19: 18 | B19: Main | C19: release/dgs | D19: 45759 | F19: Dummy Push for Variable Update - Moswin
A20: 19 | B20: dev/DGS | C20: Main | D20: 45789 | F20: Dummy Push for variables update - Moswin
A21: 20 | B21: Main | C21: release/dgs | D21: 45789 | F21: Dummy Push for variables update - Moswin
... A27: 25 | B27: Main | C27: release/dgs | D27: 46022 | F27: DGS Video Page(Coming Soon) Instead of the home page, create a new page and update the video on that page.

Sheet DGDA Environment
B1: AWS Name | C1: Link | D1: Coding | E1: Content | F1: GitHub
A2: 1 | B2: dgda-prod | C2: https://www.dgda.gov.sa | D2: Production | E2: Production | F2: release/dgda | G2: prod | H2: Delivery | I2: PROD GitHub to AWS-SSM Sync env vars & secrets
A3: 2 | B3: dgda-prod-preview | C3: https://preview.dgda.gov.sa/en | D3: Production | E3: Staging | F3: release/dgda | G3: prod | H3: Preview | I3: PROD GitHub to AWS-SSM Sync env vars & secrets
A4: 3 | B4: dgda-preprod-preview | C4: https://preview-preprod.dgda.gov.sa/en | D4: Staging | E4: Staging | F4: main | G4: preprod | H4: Preview | I4: PREPROD GitHub to AWS-SSM Sync env vars & secrets
A5: 4 | B5: dgda-preprod | C5: https://preprod.dgda.gov.sa/ | D5: Staging | E5: Production | F5: main | G5: preprod | H5: Delivery | I5: PREPROD GitHub to AWS-SSM Sync env vars & secrets
A6: 5 | B6: dgda-dev | C6: link as branch name | D6: Staging | E6: Staging | G6: preprod | H6: Preview

Sheet DGS Environment
A1: # | B1: AWS Name | C1: Temp Url | D1: Link | E1: Coding | F1: Content | G1: GitHub
A2: 1 | B2: dgs-prod | C2: https://release-dgs.d1ae5b5egxa43d.amplifyapp.com/ | D2: https://www.dgs.sa/ | E2: Production | F2: Production | G2: release/dgs
A3: 2 | B3: dgs-prod-preview | C3: https://release-dgs.dl1b7xhxrjhbe.amplifyapp.com/ | D3: https://preview.dgs.sa/ | E3: Production | F3: Staging | G3: release/dgs
A4: 3 | B4: dgs-preprod-preview | C4: https://main.d3kmmfy327jwr7.amplifyapp.com/ | D4: https://preview-preprod.dgs.sa/ | E4: Staging | F4: Staging | G4: main | H4: Error 1016
A5: 4 | B5: dgs-preprod | C5: https://main.d1lnkvi8pnbqc9.amplifyapp.com/en | D5: https://preprod.dgs.sa/ | E5: Staging | F5: Production | G5: main | H5: Error 1016
A6: 5 | B6: dgs-dev | C6: https://dev-dgs.ddz0gzz9umix8.amplifyapp.com/ | D6: link as branch name | E6: Staging | F6: Staging

Sheet Dropdown
A1: WebsiteName | B1: Website Url | C1: Status | D1: Status Definistion | E1: Env | F1: Env Definition | G1: Priority | H1: Priority Definition | I1: Leave Status | J1: Half Day / Full Day | K1: Employee Details | L1: Leave Type
A2: FIA | B2: farnborough.com | C2: Pipeline / To Do | D2: Approved tasks that are queued for work but have not yet been started by a resource. | E2: Local | F2: Individual developer’s sandbox. Work here is isolated and does not affect any other team members. | G2: Low | H2: Minor enhancements, cosmetic tweaks, or "nice-to-have" items with no impact on current functionality. | I2: Pending | J2: First Half | K2: Abhicheke | L2: Casual Leave
A3: FIA | B3: farnboroughairshow.com | C3: Requirements Not Clear | D3: Task is paused because the scope, logic, or design instructions are insufficient to proceed. | E3: Staging | F3: The integration environment where all code is combined to test for bugs and system stability. | G3: Medium | H3: Standard tasks that provide value but are not time-sensitive. To be completed in the normal work cycle. | I3: Approved | J3: Second Half | K3: Moswin | L3: Sick Leave
A4: FIA | B4: farnboroughinternational.org | C4: In Progress | D4: Active development or configuration is currently underway by the assigned resource. | E4: UAT | F4: User Acceptance Testing. A stable environment where the client validates that the solution meets their needs. | G4: High | H4: Important features or significant bugs that affect user experience. Requires prioritization in the next 24-48 hours. | I4: Rejected | J4: Full Day | K4: Parthiban | L4: Earned Leave
A5: FIA | B5: aerospaceglobalforum.com | C5: On Hold / Blocked | D5: Work has stopped due to a technical dependency, internal bottleneck, or resource unavailability. | E5: Production | F5: The "Live" environment used by end-users. Any changes here are final and affect the actual business. | G5: Urgent | H5: Time-critical tasks or major functional defects that impede a deadline. Requires immediate team focus. | I5: Cancelled | K5: Rackesh Kumaran | L5: Maternity Leave
A6: FIA | B6: events.farnboroughinternational.org | C6: Waiting for Client Input | D6: Work cannot proceed until the client provides required data, access, or clarification. | G6: Critical / Blocker | H6: System-wide failure or total work stoppage. Critical security risks or production outages requiring "all hands on deck." | K6: Regan | L6: Paternity Leave
A7: FIA | B7: farnboroughinternationalstudios.com | C7: Under Review & Testing | D7: Development is completed and the task is undergoing internal QA, validation, or peer review. | K7: Sunder | L7: Comp Off
A8: Adfactors PR Private Limited | B8: intranet.adfactorspr.com | C8: Changes Requested / Rework | D8: Client or QA has requested modifications; task is sent back for further development or correction | K8: Sowndar
A9: Adfactors PR Private Limited | B9: work.adfactorspr.com | C9: Ready for Execution | D9: All approvals are completed; task is finalized and ready for production release.
A10: Diriyah Gate Development Authority | B10: www.dgda.gov.sa | C10: Completed | D10: The task is successfully deployed, verified in Production, and officially signed off.
A11: Diriyah Gate Development Authority | B11: www.dgs.sa | C11: Closed / Cancelled | D11: The task was created in error or decided against before significant work began.
A12: Vajra Global | B12: vajraglobal.com | C12: Closed – Billable | D12: Development was completed, but the client chose not to go live. Hours worked are subject to final invoicing.
A13: MSME | B13: https://msmehealthengine.fametn.com/ | C13: Closed – Not Proceeding | D13: The project or task has been terminated mid-way; no further work or deployment will occur.

Sheet Agreed Hours
A1: # | B1: Website List | C1: Website URL | D1: CMS | E1: Overall Allocated Hours/Month | F1: Allocated Hours for Website Maintenance/Month | G1: Allocated Hours for Development Support/Month
A2: 1 | B2: Farnborough International Corporate | C2: https://www.farnboroughinternational.org/ | D2: Umbraco | E2: 18 | F2: 18 | G2: -
A3: 2 | B3: Farnborough International Exhibition & Conference Centre | C3: https://www.farnborough.com/ | D3: Umbraco | E3: 30 | F3: 18 | G3: 12
A4: 3 | B4: Farnborough International Airshow | C4: https://www.farnboroughairshow.com/ | D4: Umbraco | E4: 35 | F4: 18 | G4: 17
A5: 4 | B5: Farnborough International Studios | C5: https://farnboroughinternationalstudios.com/ | D5: Umbraco | E5: 18 | F5: 18 | G5: -
A6: 5 | B6: Farnborough International Aerospace Events | C6: https://events.farnboroughinternational.org/ | D6: Umbraco | E6: 18 | F6: 18 | G6: -
A7: 6 | B7: Aerospace Global Forum | C7: https://www.aerospaceglobalforum.com/ | D7: Umbraco | E7: 18 | F7: 18 | G7: -
A8: 7 | B8: Farnborough International Space Show | D8: WordPress | E8: 20 | F8: 11 | G8: 9
A9: 8 | B9: Sustainable Skies World Summit | D9: WordPress | E9: 20 | F9: 11 | G9: 9
A10: 9 | B10: International Symposium on Remote Sensing of Environment | D10: WordPress | E10: 11 | F10: 11 | G10: -
A11: 10 | B11: Adfactor Intranet | C11: https://intranet.adfactorspr.com/ | D11: Umbraco | E11: 110
A12: 11 | B12: Adfactor Hubspot | D12: Hubspot | E12: 25

Sheet Umbraco Update For all Website
A1: WebSite Vesrion | B1: Current Version | C1: New Version | D1: End-of-Life | E1: Balance Day | F1: Comment
A2: farnborough.com | B2: 8.18.15 | C2: 13.12.0 | D2: 46370 | E2: =IF(D2="", "", IF(D2 - TODAY() <= 0, "Update Required", D2 - TODAY() & " days remaining")) -> 178 days remaining | F2: New Site in Staging need to move it to live
A3: farnboroughairshow.com | B3: 13.9.1 | C3: 13.12.0 | D3: 46370 | E3: =IF(D3="", "", IF(D3 - TODAY() <= 0, "Update Required", D3 - TODAY() & " days remaining")) -> 178 days remaining
A4: aerospaceglobalforum.com | B4: 10.8.7 | C4: 13.12.0 | D4: 46370 | E4: =IF(D4="", "", IF(D4 - TODAY() <= 0, "Update Required", D4 - TODAY() & " days remaining")) -> 178 days remaining | F4: Nail is ooo we need to waiting for billing
A5: events.farnboroughinternational.org | B5: 8.18.15 | C5: 13.12.0 | D5: 46370 | E5: =IF(D5="", "", IF(D5 - TODAY() <= 0, "Update Required", D5 - TODAY() & " days remaining")) -> 178 days remaining
A6: farnboroughinternationalstudios.com | B6: 10.8.7 | C6: 13.12.0 | D6: 46370 | E6: =IF(D6="", "", IF(D6 - TODAY() <= 0, "Update Required", D6 - TODAY() & " days remaining")) -> 178 days remaining
A7: farnboroughinternational.org | B7: 7.15.11 | C7: 13.12.0 | D7: 46370 | E7: =IF(D7="", "", IF(D7 - TODAY() <= 0, "Update Required", D7 - TODAY() & " days remaining")) -> 178 days remaining
A8: intranet.adfactorspr.com | B8: 10.8.9 | C8: 13.12.0 | D8: 46370 | E8: =IF(D8="", "", IF(D8 - TODAY() <= 0, "Update Required", D8 - TODAY() & " days remaining")) -> 178 days remaining
A9: work.adfactorspr.com | B9: 10.8.9 | C9: 13.12.0 | D9: 46370 | E9: =IF(D9="", "", IF(D9 - TODAY() <= 0, "Update Required", D9 - TODAY() & " days remaining")) -> 178 days remaining

Sheet Farnborough Server Path
B1: Site | C1: Path | D1: File Size | E1: DB Name | F1: Production / Staging | G1: PDF Key
A2: 1 | B2: farnboroughairshow.com | C2: D:\inetpub\wwwroot\live\NewSite\2025\FIA2025 | D2: 3.72 GB | E2: Farnborough_Airshow_Production | F2: Production
A3: 2 | B3: farnborough.com | C3: D:\inetpub\wwwroot\live\NewSite\2025\Venue2025 | D3: 6.22 GB | E3: Farnborough_Venue_Production | F3: Production
A4: 3 | B4: events.farnboroughinternational.org | C4: D:\inetpub\wwwroot\live\NewSite\2023\FarnboroughInt | D4: 2.69 GB | E4: FarnboroughInt_Production | F4: Production
A5: 4 | B5: FarnboroughInternational.org | C5: D:\inetpub\wwwroot\live\farnboroughinternational.org\http | D5: 2.84 GB | E5: FarnboroughInt_Production | F5: Production
A6: 5 | B6: www.farnboroughinternationalstudios.com | C6: D:\inetpub\wwwroot\live\NewSite\2024\farnborughfilmstudios.com | D6: 1.12 GB | E6: farnboroughstudios_live | F6: Production
A7: 6 | B7: www.aerospaceglobalforum.com | C7: D:\inetpub\wwwroot\live\NewSite\2024\AGF | D7: 998 MB | E7: AGF_Airshow_Production | F7: Production
A9: 7 | B9: http://intranet.adfactorspr.com/ | C9: /VAJRA/Newintranet.adfactorspr.com | E9: AdfIntranet03052024 | F9: Production | G9: 221cc1a570764cd09f244f8625b03e32
A10: 8 | B10: https://work.adfactorspr.com/ | C10: /VAJRA/work.adfactorspr.com/work.file | E10: workadfactorspr | F10: Production | G10: 7789c40d42bb49aea84d2faa8b317300
A12: 9 | B12: https://eventsstaging.farnboroughinternational.org/ | C12: D:\inetpub\wwwroot\Staging\UAT\2023\FarnboroughInt | D12: 2.14 GB | E12: FarnboroughInt_Staging | F12: Staging
A13: 10 | B13: https://staging.farnborough.com/ | C13: D:\inetpub\wwwroot\Staging\UAT\2025\Venue2025Update\Staging | D13: 6.8 GB | E13: Farnborough_Venue_Staging_2025 | F13: Staging
A14: 11 | B14: staging.farnboroughairshow.com | C14: D:\inetpub\wwwroot\Staging\UAT\2024\FIA2025 | D14: 3.45 GB | E14: Farnborough_Airshow_Staging24 | F14: Staging
A15: 12 | B15: staging.farnboroughinternational.org | C15: D:\inetpub\wwwroot\Staging\Farnborough_International\Farnborough_International | D15: 2.21 GB | E15: FarnboroughInt_Staging | F15: Staging
A16: 13 | B16: staging.farnborughfilmstudios.com | C16: D:\inetpub\wwwroot\Staging\UAT\2025\staging.farnborughfilmstudios.com | D16: 1.15 GB | E16: farnboroughstudios_staging_2024 | F16: Staging
A17: 14 | B17: staging.aerospaceglobalforum.com | C17: D:\inetpub\wwwroot\Staging\UAT\2024\AGF | D17: 939 GB | E17: AGF_Airshow_Staging | F17: Staging
A19: 15 | B19: https://intranetstaging.adfactorspr.com/ | C19: /VAJRA/VAJRA/intranetstaging.adfactorspr.com | E19: AdfactorStaging | F19: Staging | G19: 8db1e45b79c247679a2113931cf7536c
A20: 16 | B20: https://workstaging.adfactorspr.com/ | C20: /VAJRA/workstaging.adfactorspr.com | E20: WorkAdfactorsprStaging | F20: Staging | G20: No Key for workstaging
